Workbook
Name CÓDIGOS_TIPO_DE_FUENTES_DE_FINANCIACIÓN: '[1]Fuentes de Financiación'!$B$3:$B$218
Name Energia_Sostenible: PD_2024_2027!#REF!
Name Energia_Sostenible: Listas!#REF!
Name SALDO_PPT: [1]Presentación!$E$3
Name SALDO_TES: [1]Presentación!$G$3

Sheet Contratos Marco
D1: EMERGENCIAS
B2: Datos Generales Contratación | M2: Datos Financieros Gerencia y proyectos_ Si aplica
B3: # | C3: Contrato Marco | D3: Entidad Contratante [Ejemplo: ADI | Secretaría de Obras Públicas | Edubar | PDO] | E3: Convenio o Contrato Interadministrativo [Si no aplica: N/A] | F3: Aliado Contrato Interadministrativo [Si no aplica: N/A] | G3: Fuente de Recurso [ Propios_Alcaldía | Cofinanciación | Otros ] | I3: Fecha de Inicio [dd/mm/aaaa] | J3: Fecha de Terminación Inicial [dd/mm/aaaa] | K3: Fecha de Terminación Final [dd/mm/aaaa] | M3: Valor inicial Contrato de Gerencia | N3: Valor total adicionado Contrato de Gerencia | O3: Valor total Contrato de Gerencia | P3: Valor para Gerencia | Q3: Valor total Facturado Contrato de Gerencia | R3: Valor total Pagado Contrato de Gerencia | S3: Valor para Ejecución [Contrato Ejecución + Interventoría] | T3: Valor total Facturado Ejecución [Contrato Ejecución + Interventoría] | U3: Valor total Pagado Ejecución [Contrato Ejecución + Interventoría] | W3: Observaciones
B4: 1 | C4: ECOPARQUE UF1 Y TREN TAJAMAR | D4: Distrito Especial Industrial y Portuario de Barranquilla NIT. 890.102.018-1 | E4: Contrato Interadministrativo No. CD-12-2020-2435 | F4: N/A | G4: Cofinanciación | I4: 44327 | J4: 44561 | K4: 45382 | M4: =+P4+S4 -> 133184208608 | O4: =+M4+N4 -> 133184208608 | P4: 2420000000 | Q4: 2178000000 | R4: =Q4 -> 2178000000 | S4: 130764208608 | T4: 1.1137917e+11 | U4: 1.0877791e+11
B5: 2 | C5: ECOPARQUE UF2 | D5: 1. Empresa Nacional Promotora del Desarrollo Territorial – Enterritorio – Ministerio de Hacienda y Crédito Público NIT 899.999.316-1 en calidad de mandatario del Departamento Nacional de Planeación (DNP) en virtud del Contrato Interadministrativo de Mandato DNP 877-2021 Enterritorio 221009 – ENTERRITORIO. 2. Distrito Especial Industrial y Portuario de Barranquilla NIT. 890.102.018-1 3. Establecimiento Público Ambiental Barranquilla Verde NIT. 901.034.433-0 | E5: Contrato Específico No. 2210698 Derivado del Pacto Funcional Atlántico - CONTRATO DE MANDATO N.º 221009 – Suscrito entre EL DNP Y ENTERRITORIO | F5: ENTERRITORIO | G5: Distrito: $ 16.408.845.503,32 DNP: $105.000.000.000 | I5: 44544 | J5: 45121 | M5: =121408845503.32+508517168 -> 1.2191736e+11 | O5: =+M5 -> 1.2191736e+11 | P5: 5.7380996e+09 | Q5: 4.3035747e+09 | R5: 4.3035747e+09 | S5: =115670745934+508517168 -> 116179263102 | T5: 9.7371767e+10 | U5: 9.7371767e+10
B6: 3 | C6: RECUPERACIÓN PLAYA PUERTO MOCHO | D6: Distrito Especial Industrial y Portuario de Barranquilla NIT. 890.102.018-1 | E6: Contrato Interadministrativo No.CD-12-2021-4477 | F6: N/A | G6: Distrito | I6: 44531 | J6: 44926 | K6: 45337 | M6: 2.6776982e+10 | O6: =+M6+N6 -> 2.6776982e+10 | P6: 1.195401e+09 | Q6: 1.0692198e+09 | R6: =1069219751.2-112898979.92 -> 9.5632077e+08 | S6: =23091329705+1673561307 -> 24764891012 | T6: =13753311978.97+850671212 -> 1.4603983e+10 | U6: =+(13753311978.97-2014528783)+850671212 -> 1.2589454e+10 | W6: Se esra trámitando una prórroga al Contrato Interadministrativo por 2 meses más a partir de la fecha de terminación del mismo.
B7: 4 | C7: GRAN BAZAR Y NUEVOS MERCADOS | D7: Distrito Especial Industrial y Portuario de Barranquilla NIT. 890.102.018-1 | E7: Contrato Interadministrativo No. CD-57-2021-2989 | F7: Gobernación del Atlántico NIT: 890.102.006-1 | G7: Cofinanciación Gobernación del Atlántico por valor de $17.500.000.000 | I7: 44328 | J7: 44561 | K7: 45504 | M7: 6700000000 | N7: 1.1638559e+11 | O7: =+M7+N7 -> 1.2308559e+11 | P7: 9.9238789e+09 | Q7: 8.931491e+09 | R7: =+Q7 -> 8.931491e+09 | S7: 1.1316171e+11 | T7: 9.2628533e+10 | U7: 8.0310588e+10
B8: 5 | C8: TEU - TRANSFORMACIÓN DE ENTORNOS URBANOS | D8: Distrito Especial Industrial y Portuario de Barranquilla NIT. 890.102.018-1 | E8: Contrato Interadministrativo No. CD-57-2020-2438 | F8: N/A | I8: 44706 | J8: 44926 | K8: 45504 | M8: 30000000000 | O8: 30000000000 | P8: 1926605505 | Q8: 1.6439367e+09 | R8: 1.6439367e+09 | S8: 28068651772 | T8: 24449905435 | U8: 24449905435
B9: 6 | C9: CAÑO DE LA AHUYAMA | D9: 1. Empresa Nacional Promotora del Desarrollo Territorial – Enterritorio – Ministerio de Hacienda y Crédito Público NIT 899.999.316-1 en calidad de mandatario del Departamento Nacional de Planeación (DNP) en virtud del Contrato Interadministrativo de Mandato DNP 877-2021 Enterritorio 221009 – ENTERRITORIO. 2. Distrito Especial Industrial y Portuario de Barranquilla NIT. 890.102.018-1 3. Establecimiento Público Ambiental Barranquilla Verde NIT. 901.034.433-0 | E9: Contrato Específico No. 2210681 Derivado del Pacto Funcional Atlántico - CONTRATO DE MANDATO N.º 221009 – Suscrito entre EL DNP Y ENTERRITORIO | F9: ENTERRITORIO | G9: Distrito: $ 4.747.433.502,01 DNP: $ 99.979.996.094 | I9: 44529 | J9: 45045 | K9: 45504 | M9: =+S9+O9 -> 1.0472743e+11 | O9: 4.7474335e+09 | P9: 4.7474335e+09 | Q9: 3.5605751e+09 | R9: 3.5605751e+09 | S9: =93425142894+6554853200 -> 99979996094 | T9: 5.5051036e+10 | U9: 5.4560733e+10
B10: 7 | C10: CICLOMONTAÑISMO | D10: Distrito Especial Industrial y Portuario de Barranquilla NIT. 890.102.018-1 | E10: CD-58-2021-4425 | F10: N/A | G10: Cofinanciación | I10: 44525 | J10: 44926 | K10: 45412 | M10: 3.3759879e+10 | O10: =+M10+N10 -> 3.3759879e+10 | P10: 1607613301 | Q10: 1.446852e+09 | R10: 1.446852e+09 | S10: 3.1980741e+10 | T10: 2.8779232e+10 | U10: 2.8779232e+10
B11: 8 | C11: HOSPITALES | D11: Distrito Especial Industrial y Portuario de Barranquilla NIT. 890.102.018-1 | E11: No. 012016001893 | F11: N/A | G11: Estampilla Prohospital ICLD FONPET | I11: 42524 | J11: 45657 | K11: 45657 | M11: 164361579387 | N11: =900213284+6000000000+2494297665+19170000000+28750000000 -> 57314510949 | O11: =+M11+N11 -> 221676090336 | P11: 0 | Q11: 0 | R11: 0 | S11: =+O11 -> 221676090336 | T11: =149768557393.23+13623178167.94 -> 1.6339174e+11 | U11: =149768557393.23+13055502565.61 -> 1.6282406e+11
B12: 9 | C12: BARRIOS A LA OBRA | D12: Distrito Especial Industrial y Portuario de Barranquilla NIT. 890.102.018-1 | E12: Contrato Interadministrativo No. CD-12-2020-2429 | F12: N/A | G12: Propios_Alcaldía | I12: 44442 | J12: 44561 | K12: 45656 | M12: 110625302170 | N12: 71726921600 | O12: =+M12+N12 -> 182352223770 | P12: 7883906190 | Q12: 5.4182428e+09 | R12: 5333717843 | S12: 173745194193 | T12: 1.2351558e+11 | U12: 1.2259868e+11 | W12: Se realizaron prorrogas y adiciones a contratos de obra e interventoria para ejecucion hasta 30 de julio del 2024 y con fecha de ejecucion de la gerencia hasta 30 de diciembre del 2024
B13: 10 | C13: AMPLIACIÓN Y MEJORAMIENTO DE IEDs | D13: Distrito Especial Industrial y Portuario de Barranquilla NIT. 890.102.018-1 | E13: Contrato Interadministrativo No. CD-05-2022-3691 | F13: N/A | G13: Cofinanciación | I13: 44757 | J13: 44926 | K13: 45382 | M13: 30000000000 | O13: =+M13+N13 -> 30000000000 | P13: 2392620000 | Q13: 2033727000 | R13: =+Q13 -> 2033727000 | S13: =25672996396.61+1349952660 -> 2.7022949e+10 | T13: =17405858399.13+874384041.14 -> 1.8280242e+10 | U13: =1934476065.17+4224296240.76+2964678266.08+2350000000+323844203 -> 1.1797295e+10 | W13: Se adeuda la suma de $6.482.947.665,26
B14: 11 | C14: MANTENIMIENTO DE LOS ESCENARIOS DEPORTIVOS DEL DISTRITO DE BARRANQUILLA | D14: Distrito Especial Industrial y Portuario de Barranquilla NIT. 890.102.018-1 | E14: Contrato Interadministrativo No. CD-58-2023-3275 | F14: N/A | G14: Cofinanciación | I14: 45070 | J14: 45291 | K14: 45503 | M14: 10000000000 | O14: =+M14+N14 -> 10000000000 | P14: 800000000 | Q14: 720000000 | R14: =+Q14 -> 720000000 | S14: 9200000000 | T14: 1.5960513e+09 | U14: 0 | W14: Se adeuda la suma de $ 1.596.051.256,56

Sheet Proyectos Base digitable
A1: ID | B1: Reporte a cargo de: | C1: Convenio o Contrato Interadministrativo | D1: Línea Estratégica Plan de Desarrollo 2024-2027 | E1: Sectores | F1: Programas | G1: Nombre Proyecto | H1: Localidad | I1: Barrios | J1: Dirección | K1: Localización | L1: x | M1: y | N1: Estado Proyecto | O1: Subestado Proyecto | P1: Valor total de proyecto | Q1: % Programado físico | R1: % Ejecutado físico | S1: Atraso | T1: Semáforo Cronograma | U1: Fecha de Adjudicación | V1: Fecha de Firma Contrato | W1: Fecha de Inicio | X1: Fecha de Terminación Inicial | Y1: Fecha de Terminación Final | Z1: Semáforo Fecha Terminación | AA1: Semáforo Críticos | AB1: ¿Proyecto con ampliación de plazo contractual? | AC1: Fecha estimada para terminación según prórroga a tramitar | AD1: Fecha de Entrega | AE1: No. Contrato Ejecución | AF1: Nombre Contratista Ejecución | AG1: Miembros Consorcios o UT | AH1: Representante Legal | AI1: No. Contrato Interventoría | AJ1: Nombre Contratista Interventoría | AK1: Miembros Consorcios o UT 2 | AL1: Representante Legal3 | AM1: Valor inicial de Obra | AN1: Valor total adicionado de obra | AO1: Valor total de Obra | AP1: Valor total Facturadode Obra | AQ1: Valor total Pagado de Obra | AR1: Valor inicial de Interventoría | AS1: Valor total adicionado de Interventoría | AT1: Valor total de Interventoría | AU1: Valor total Facturado de Interventoría | AV1: Valor total Pagado de Interventoría | AW1: Población Beneficiada [ Indicar cantidad y tipo de población. Ej: 100 Estudiantes ] | AX1: Indicador 1 | AY1: Indicador 2 | AZ1: Indicador 3 | BA1: Actividades Ejecutadas ultima semana | BB1: Observaciones de acciones ejecutivas | BC1: Emblemático Gerente
A2: 1 | B2: Obras Públicas | C2: CD-12-2020-2429 | D2: Línea Económica_Ciudad Dinámica | E2: Trasporte | F2: Barrios a la obra | G2: BAO_VII_2429_M1 | H2: Varias | I2: La Paz - El Carmen - Olaya - Santuario - Evaristo Sourdis - Villa San Pedro II - Villa Flor - Campo Alegre - Sevilla Real - Las Granjas - Villa Sevilla - Corregimiento La Playa - Alameda Del Rio - El Pueblo - Los Angeles III - Siete de Abril - Boyacá | J2: - | K2: 10°58'6.7'' N 74°46'52.8'' O | L2: -74.781333 | M2: 10.968528 | N2: Postcontractual | O2: Terminado | P2: =+AO2+AT2 -> 1.7501823e+10 | Q2: 1 | R2: 1 | S2: =+R2-Q2 -> 0 | T2: {=+_xlfn.IFS($P2<=10000000000,IF(S2>-0.05,"Verde",IF(S2<=-0.1,"Rojo","Amarillo")),$P2>10000000000,IF(S2>-0.03,"Verde",IF(S2<=-0.07,"Rojo","Amarillo")))} -> Verde | U2: 44305 | V2: 44334 | W2: 44442 | X2: 44561 | Y2: 45504 | Z2: =+IF(AND(O2="En_Ejecución",OR(T2="Rojo",T2="Amarillo")),IF(($Y2-(TODAY())<15),"Rojo",IF(($Y2-TODAY())>=45,"Verde","Amarillo")),O2) -> Terminado | AA2: =+IF(AND(Z2="Amarillo",T2="Rojo"),"En_Seguimiento",IF(AND(Z2="Rojo",T2="Amarillo"),"En_Seguimiento",IF(AND(Z2="Rojo",T2="Rojo"),"En_Seguimiento",IF(AND(Z2="Suspendido",T2="Amarillo"),"En_Seguimiento",IF(AND(Z2="Suspendido",T2="Rojo"),"En_Seguimiento","-"))))) -> - | AB2: No | AD2: 45504 | AE2: EDU-356-2021 | AF2: CONSORCIO VIAL DISTRITAL | AG2: HB INGENIEROS CIVILES S.A.S. (80%) A.S.B. LIMITADA (10%) CONSTRUCCIONES CARCIV S.A.S. (10%) | AH2: Alvaro Henriquez Medrano | AI2: EDU-388-2021 | AJ2: CONSORCIO INTERVIAS BARRANQUILLA | AK2: COMPAÑÍA DE INTERVENTORIAS Y CONSULTORIAS DE LA COSTA S.A.S. (59%) ROCCIA S.A.S. (30%) CGB (10%) INEXIA S.A.S. (1%) | AL2: CARLOS MASS GUERRERO | AM2: 10087941782 | AN2: 6614286460 | AO2: =AM2+AN2 -> 16702228242 | AP2: 15865781158 | AQ2: 15865781158 | AR2: 2589999997 | AS2: 1425826605 | AT2: 7.9959426e+08 | AU2: 3.4917114e+09 | AV2: 3.1115436e+09 | AW2: 4880 Habitantes | AX2: Metros Lineales intervenidos | AY2: Kilometros recuperados por Barrio | AZ2: Tramos viales inaugurados | BA2: Proceso de liquidación | BC2: No
A3: =+A2+1 -> 2 | B3: Obras Públicas | C3: CD-12-2020-2429 | D3: Línea Económica_Ciudad Dinámica | E3: Trasporte | F3: Barrios a la obra | G3: BAO_VII_2429_M2 | H3: Varias | I3: La Gloria - El Bosque - El Pueblo - California - Cordialidad - Villa San Pedro I - Villa San Carlos - Santo Domingo de Guzman | J3: - | K3: 10°58'6.7'' N 74°46'52.8'' O | N3: Postcontractual | O3: Terminado | P3: =+AO3+AT3 -> 1.8006561e+10 | Q3: 1 | R3: 1 | S3: =+R3-Q3 -> 0 | T3: {=+_xlfn.IFS($P3<=10000000000,IF(S3>-0.05,"Verde",IF(S3<=-0.1,"Rojo","Amarillo")),$P3>10000000000,IF(S3>-0.03,"Verde",IF(S3<=-0.07,"Rojo","Amarillo")))} -> Verde | U3: 44305 | V3: 44334 | W3: 44442 | X3: 44561 | Y3: 44985 | Z3: =+IF(AND(O3="En_Ejecución",OR(T3="Rojo",T3="Amarillo")),IF(($Y3-(TODAY())<15),"Rojo",IF(($Y3-TODAY())>=45,"Verde","Amarillo")),O3) -> Terminado | AA3: =+IF(AND(Z3="Amarillo",T3="Rojo"),"En_Seguimiento",IF(AND(Z3="Rojo",T3="Amarillo"),"En_Seguimiento",IF(AND(Z3="Rojo",T3="Rojo"),"En_Seguimiento",IF(AND(Z3="Suspendido",T3="Amarillo"),"En_Seguimiento",IF(AND(Z3="Suspendido",T3="Rojo"),"En_Seguimiento","-"))))) -> - | AB3: No | AD3: 44985 | AE3: EDU-357-2021 | AF3: BF CONSTRUYE SAS | AG3: BF CONSTRUYE S.A.S. (100%) | AH3: Maria Isabel Valenzuela Benitez | AI3: EDU-389-2021 | AJ3: CONSORCIO RUT 2021 | AK3: COINCO DE COLOMBIA S.A.S. (50%) INGENIERIA MASTER S.A.S. (25%) CONSULTORIA TECNICA DE OBRAS S.A.S. (25%) | AL3: DAVINSON GRAVINI POLO | AM3: 7596189806 | AN3: 9.5106915e+09 | AO3: =AM3+AN3 -> 1.7106881e+10 | AP3: 17105644167 | AQ3: 17105644167 | AR3: 2353659350 | AS3: 1.9320403e+09 | AT3: 8.9967999e+08 | AU3: 3242593169 | AV3: 3242593169 | AW3: 3204 Habitantes | AX3: Metros Lineales intervenidos | AY3: Kilometros recuperados por Barrio | AZ3: Tramos viales inaugurados | BA3: Proceso de liquidación | BC3: No
A4: =+A3+1 -> 3 | B4: Obras Públicas | C4: CD-12-2020-2429 | D4: Línea Económica_Ciudad Dinámica | E4: Trasporte | F4: Barrios a la obra | G4: BAO_VII_2429_M3 | H4: Suroccidente | I4: Por Fin - La Manga | J4: - | K4: 10°58'6.7'' N 74°46'52.8'' O | N4: Postcontractual | O4: Terminado | P4: =+AO4+AT4 -> 1.3596535e+10 | Q4: 1 | R4: 1 | S4: =+R4-Q4 -> 0 | T4: {=+_xlfn.IFS($P4<=10000000000,IF(S4>-0.05,"Verde",IF(S4<=-0.1,"Rojo","Amarillo")),$P4>10000000000,IF(S4>-0.03,"Verde",IF(S4<=-0.07,"Rojo","Amarillo")))} -> Verde | U4: 44305 | V4: 44334 | W4: 44442 | X4: 44561 | Y4: 45626 | Z4: =+IF(AND(O4="En_Ejecución",OR(T4="Rojo",T4="Amarillo")),IF(($Y4-(TODAY())<15),"Rojo",IF(($Y4-TODAY())>=45,"Verde","Amarillo")),O4) -> Terminado | AA4: =+IF(AND(Z4="Amarillo",T4="Rojo"),"En_Seguimiento",IF(AND(Z4="Rojo",T4="Amarillo"),"En_Seguimiento",IF(AND(Z4="Rojo",T4="Rojo"),"En_Seguimiento",IF(AND(Z4="Suspendido",T4="Amarillo"),"En_Seguimiento",IF(AND(Z4="Suspendido",T4="Rojo"),"En_Seguimiento","-"))))) -> - | AB4: No | AD4: 45626 | AE4: EDU-358-2021 | AF4: CONSTRUCTORA DE OBRAS DE VIVIENDA E INGENIERIA SAS (COVEIN) | AG4: CONSTRUCTORA DE OBRAS DE VIVIENDA E INGENIERIA S.A.S. (COVEIN) (100%) | AH4: Guillermo Alberto Cuello Gieseken | AI4: EDU-389-2021 | AJ4: CONSORCIO RUT 2021 | AK4: COINCO DE COLOMBIA S.A.S. (50%) INGENIERIA MASTER S.A.S. (25%) CONSULTORIA TECNICA DE OBRAS S.A.S. (25%) | AL4: DAVINSON GRAVINI POLO | AM4: 7615449800 | AN4: 5301748132 | AO4: =AM4+AN4 -> 12917197932 | AP4: 8.7661794e+09 | AQ4: 8.7661794e+09 | AR4: 0 | AS4: 0 | AT4: 6.7933741e+08 | AU4: 0 | AV4: 0 | AW4: 588 Habitantes | AX4: Metros Lineales intervenidos | AY4: Kilometros recuperados por Barrio | AZ4: Tramos viales inaugurados | BA4: Se realizo actividades de Nivelación y replanteo de via, Excavación y retiro de material, Señalizacion de frentes de obra, instalación de relleno en material seleccionado, instalación de concreto fluido, fundida en pavimento en concreto rigido | BC4: No
A5: =+A4+1 -> 4 | B5: Obras Públicas | C5: CD-12-2020-2429 | D5: Línea Económica_Ciudad Dinámica | E5: Trasporte | F5: Barrios a la obra | G5: BAO_VII_2429_M4 | H5: Metropolitana | I5: Siete de Abril | J5: - | K5: 10°58'6.7'' N 74°46'52.8'' O | N5: Postcontractual | O5: Terminado | P5: =+AO5+AT5 -> 1.370699e+10 | Q5: 1 | R5: 1 | S5: =+R5-Q5 -> 0 | T5: {=+_xlfn.IFS($P5<=10000000000,IF(S5>-0.05,"Verde",IF(S5<=-0.1,"Rojo","Amarillo")),$P5>10000000000,IF(S5>-0.03,"Verde",IF(S5<=-0.07,"Rojo","Amarillo")))} -> Verde | U5: 44305 | V5: 44334 | W5: 44442 | X5: 44561 | Y5: 45504 | Z5: =+IF(AND(O5="En_Ejecución",OR(T5="Rojo",T5="Amarillo")),IF(($Y5-(TODAY())<15),"Rojo",IF(($Y5-TODAY())>=45,"Verde","Amarillo")),O5) -> Terminado | AA5: =+IF(AND(Z5="Amarillo",T5="Rojo"),"En_Seguimiento",IF(AND(Z5="Rojo",T5="Amarillo"),"En_Seguimiento",IF(AND(Z5="Rojo",T5="Rojo"),"En_Seguimiento",IF(AND(Z5="Suspendido",T5="Amarillo"),"En_Seguimiento",IF(AND(Z5="Suspendido",T5="Rojo"),"En_Seguimiento","-"))))) -> - | AB5: No | AD5: 45504 | AE5: EDU-359-2021 | AF5: CONSORCIO BARRIOS A LA OBRA 2021 | AG5: EDUARDO ENRIQUE CABALLERO AVILA (50%) CONSTRUCCIONES E INVERSIONES FVR S.A.S. (40%) PROYECTOS DE INGENIERÍA INOSVA S.A.S. (10%) | AH5: Eduardo Enrique Caballero Avila | AI5: EDU-389-2021 | AJ5: CONSORCIO RUT 2021 | AK5: COINCO DE COLOMBIA S.A.S. (50%) INGENIERIA MASTER S.A.S. (25%) CONSULTORIA TECNICA DE OBRAS S.A.S. (25%) | AL5: DAVINSON GRAVINI POLO | AM5: 7591113018 | AN5: 5431020644 | AO5: =AM5+AN5 -> 13022133662 | AP5: 1.2360972e+10 | AQ5: 1.2360972e+10 | AR5: 0 | AS5: 0 | AT5: 6.8485616e+08 | AU5: 0 | AV5: 0 | AW5: 2392 Habitantes | AX5: Metros Lineales intervenidos | AY5: Kilometros recuperados por Barrio | AZ5: Tramos viales inaugurados | BA5: Tramites de recibo final y terminacion, cierres de actas de vecindad, pqrs y pendientes en campo | BC5: No
A6: =+A5+1 -> 5 | B6: Obras Públicas | C6: CD-12-2020-2429 | D6: Línea Económica_Ciudad Dinámica | E6: Trasporte | F6: Barrios a la obra | G6: BAO_VII_2429_M5 | H6: Varias | I6: Colombia - El Porvenir - Altos del Limon - Centro - Villa Santos - Las Americas - Las Malvinas - Barrios Abajo - La Chinita - Las Flores - San Salvador - San Francisco - La Luz - Chiquinquira - Las Mercedes - Los Jobos - San Jose - La Victoria - Las Delicias - La Ceiba - San Felipe - Olaya Herrera - Las Estrellas - La Florida - Santa Maria - San Luis - Los Andes | J6: - | K6: 10°58'6.7'' N 74°46'52.8'' O | N6: Postcontractual | O6: Terminado | P6: =+AO6+AT6 -> 1.6211544e+10 | Q6: 1 | R6: 1 | S6: =+R6-Q6 -> 0 | T6: {=+_xlfn.IFS($P6<=10000000000,IF(S6>-0.05,"Verde",IF(S6<=-0.1,"Rojo","Amarillo")),$P6>10000000000,IF(S6>-0.03,"Verde",IF(S6<=-0.07,"Rojo","Amarillo")))} -> Verde | U6: 44305 | V6: 44334 | W6: 44442 | X6: 44561 | Y6: 45565 | Z6: =+IF(AND(O6="En_Ejecución",OR(T6="Rojo",T6="Amarillo")),IF(($Y6-(TODAY())<15),"Rojo",IF(($Y6-TODAY())>=45,"Verde","Amarillo")),O6) -> Terminado | AA6: =+IF(AND(Z6="Amarillo",T6="Rojo"),"En_Seguimiento",IF(AND(Z6="Rojo",T6="Amarillo"),"En_Seguimiento",IF(AND(Z6="Rojo",T6="Rojo"),"En_Seguimiento",IF(AND(Z6="Suspendido",T6="Amarillo"),"En_Seguimiento",IF(AND(Z6="Suspendido",T6="Rojo"),"En_Seguimiento","-"))))) -> - | AB6: No | AD6: 45565 | AE6: EDU-360-2021 | AF6: A CONSTRUIR SA | AG6: A CONSTRUIR S.A. (100%) | AH6: Ivan Alberto Jimenez Aguirre | AI6: EDU-388-2021 | AJ6: CONSORCIO INTERVIAS BARRANQUILLA | AK6: COMPAÑÍA DE INTERVENTORIAS Y CONSULTORIAS DE LA COSTA S.A.S. (59%) ROCCIA S.A.S. (30%) CGB (10%) INEXIA S.A.S. (1%) | AL6: CARLOS MASS GUERRERO | AM6: 9610407989 | AN6: 5860489797 | AO6: =AM6+AN6 -> 15470897786 | AP6: 14553426871 | AQ6: 14553426871 | AR6: 0 | AS6: 0 | AT6: 7.4064615e+08 | AU6: 0 | AV6: 0 | AW6: 3100 Habitantes | AX6: Metros Lineales intervenidos | AY6: Kilometros recuperados por Barrio | AZ6: Tramos viales inaugurados | BA6: Tramites de recibo final y terminacion, cierres de actas de vecindad, pqrs y pendientes en campo | BC6: No
A7: =+A6+1 -> 6 | B7: Obras Públicas | C7: CD-12-2020-2429 | D7: Línea Económica_Ciudad Dinámica | E7: Trasporte | F7: Barrios a la obra | G7: BAO_VII_2429_M6 | H7: Varias | I7: Las Americas - Santuario - Las Malvinas - Ciudadela 20 de Julio - Ciudad Modesto | J7: - | K7: 10°58'6.7'' N 74°46'52.8'' O | N7: Postcontractual | O7: Terminado | P7: =+AO7+AT7 -> 1.5213349e+10 | Q7: 1 | R7: 1 | S7: =+R7-Q7 -> 0 | T7: {=+_xlfn.IFS($P7<=10000000000,IF(S7>-0.05,"Verde",IF(S7<=-0.1,"Rojo","Amarillo")),$P7>10000000000,IF(S7>-0.03,"Verde",IF(S7<=-0.07,"Rojo","Amarillo")))} -> Verde | U7: 44305 | V7: 44334 | W7: 44442 | X7: 44561 | Y7: 45565 | Z7: =+IF(AND(O7="En_Ejecución",OR(T7="Rojo",T7="Amarillo")),IF(($Y7-(TODAY())<15),"Rojo",IF(($Y7-TODAY())>=45,"Verde","Amarillo")),O7) -> Terminado | AA7: =+IF(AND(Z7="Amarillo",T7="Rojo"),"En_Seguimiento",IF(AND(Z7="Rojo",T7="Amarillo"),"En_Seguimiento",IF(AND(Z7="Rojo",T7="Rojo"),"En_Seguimiento",IF(AND(Z7="Suspendido",T7="Amarillo"),"En_Seguimiento",IF(AND(Z7="Suspendido",T7="Rojo"),"En_Seguimiento","-"))))) -> - | AB7: No | AD7: 45565 | AE7: EDU-361-2021 | AF7: DONADO ARCE & CIA SAS | AG7: DONADO ARCE & CIA S.A.S. (100%) | AH7: Roberto Carlo Donado Arce | AI7: EDU-388-2021 | AJ7: CONSORCIO INTERVIAS BARRANQUILLA | AK7: COMPAÑÍA DE INTERVENTORIAS Y CONSULTORIAS DE LA COSTA S.A.S. (59%) ROCCIA S.A.S. (30%) CGB (10%) INEXIA S.A.S. (1%) | AL7: CARLOS MASS GUERRERO | AM7: 8708323997 | AN7: 5809982432 | AO7: =AM7+AN7 -> 14518306429 | AP7: 1.2927145e+10 | AQ7: 1.2927145e+10 | AR7: 0 | AS7: 0 | AT7: 6.9504226e+08 | AU7: 0 | AV7: 0 | AW7: 2916 Habitantes | AX7: Metros Lineales intervenidos | AY7: Kilometros recuperados por Barrio | AZ7: Tramos viales inaugurados | BA7: Tramites de recibo final y terminacion, cierres de actas de vecindad, pqrs y pendientes en campo | BC7: No
A8: =+A7+1 -> 7 | B8: Obras Públicas | C8: CD-12-2020-2429 | D8: Línea Económica_Ciudad Dinámica | E8: Trasporte | F8: Barrios a la obra | G8: BAO_VII_2429_M7 | H8: Varias | I8: El Bosque - El Eden 2000 - Florida Sur - Evaristo Sourdis - Villa del Rosario - Ciudad Jardin - Las Estrellas | J8: - | K8: 10°58'6.7'' N 74°46'52.8'' O | N8: Postcontractual | O8: Terminado | P8: =+AO8+AT8 -> 1.6944274e+10 | Q8: 1 | R8: 1 | S8: =+R8-Q8 -> 0 | T8: {=+_xlfn.IFS($P8<=10000000000,IF(S8>-0.05,"Verde",IF(S8<=-0.1,"Rojo","Amarillo")),$P8>10000000000,IF(S8>-0.03,"Verde",IF(S8<=-0.07,"Rojo","Amarillo")))} -> Verde | U8: 44305 | V8: 44334 | W8: 44442 | X8: 44561 | Y8: 45428 | Z8: =+IF(AND(O8="En_Ejecución",OR(T8="Rojo",T8="Amarillo")),IF(($Y8-(TODAY())<15),"Rojo",IF(($Y8-TODAY())>=45,"Verde","Amarillo")),O8) -> Terminado | AA8: =+IF(AND(Z8="Amarillo",T8="Rojo"),"En_Seguimiento",IF(AND(Z8="Rojo",T8="Amarillo"),"En_Seguimiento",IF(AND(Z8="Rojo",T8="Rojo"),"En_Seguimiento",IF(AND(Z8="Suspendido",T8="Amarillo"),"En_Seguimiento",IF(AND(Z8="Suspendido",T8="Rojo"),"En_Seguimiento","-"))))) -> - | AB8: No | AD8: 45428 | AE8: EDU-362-2021 | AF8: CONSTRUCTORA FG SA | AG8: CONSTRUCTORA FG S.A. (100%) | AH8: Eduardo Santos Martinez | AI8: EDU-388-2021 | AJ8: CONSORCIO INTERVIAS BARRANQUILLA | AK8: COMPAÑÍA DE INTERVENTORIAS Y CONSULTORIAS DE LA COSTA S.A.S. (59%) ROCCIA S.A.S. (30%) CGB (10%) INEXIA S.A.S. (1%) | AL8: CARLOS MASS GUERRERO | AM8: 10200564715 | AN8: 5969587668 | AO8: =AM8+AN8 -> 16170152383 | AP8: 15284701905 | AQ8: 15284701905 | AR8: 0 | AS8: 0 | AT8: 7.7412192e+08 | AU8: 0 | AV8: 0 | AW8: 2248 Habitantes | AX8: Metros Lineales intervenidos | AY8: Kilometros recuperados por Barrio | AZ8: Tramos viales inaugurados | BA8: Proceso de liquidación | BC8: No
A9: =+A8+1 -> 8 | B9: Obras Públicas | C9: CD-12-2020-2429 | D9: Línea Económica_Ciudad Dinámica | E9: Trasporte | F9: Barrios a la obra | G9: BAO_VII_2429_M8 | H9: Suroccidente | I9: Me Quejo - San Felipe - Carlos Meisel - La Esmeralda - La Libertad | J9: - | K9: 10°58'6.7'' N 74°46'52.8'' O | N9: Postcontractual | O9: Terminado | P9: =+AO9+AT9 -> 1.3792195e+10 | Q9: 1 | R9: 1 | S9: =+R9-Q9 -> 0 | T9: {=+_xlfn.IFS($P9<=10000000000,IF(S9>-0.05,"Verde",IF(S9<=-0.1,"Rojo","Amarillo")),$P9>10000000000,IF(S9>-0.03,"Verde",IF(S9<=-0.07,"Rojo","Amarillo")))} -> Verde | U9: 44305 | V9: 44334 | W9: 44442 | X9: 44561 | Y9: 45504 | Z9: =+IF(AND(O9="En_Ejecución",OR(T9="Rojo",T9="Amarillo")),IF(($Y9-(TODAY())<15),"Rojo",IF(($Y9-TODAY())>=45,"Verde","Amarillo")),O9) -> Terminado | AA9: =+IF(AND(Z9="Amarillo",T9="Rojo"),"En_Seguimiento",IF(AND(Z9="Rojo",T9="Amarillo"),"En_Seguimiento",IF(AND(Z9="Rojo",T9="Rojo"),"En_Seguimiento",IF(AND(Z9="Suspendido",T9="Amarillo"),"En_Seguimiento",IF(AND(Z9="Suspendido",T9="Rojo"),"En_Seguimiento","-"))))) -> - | AB9: No | AD9: 45504 | AE9: EDU-363-2021 | AF9: CONSORCIO VIAS URBANAS BARRANQUILLA 2021 | AG9: SOLUCIONES DE INFRAESTRUCTURA Y LOGISTICA S.A.S. (60%) TOSHIRA KENETSU S.A.S. (15%) INFRAESTRUCTURA TÉCNICA COLOMBIANA S.A.S. (25%) | AH9: Fabiam Alvarado Paternina | AI9: EDU-389-2021 | AJ9: CONSORCIO RUT 2021 | AK9: COINCO DE COLOMBIA S.A.S. (50%) INGENIERIA MASTER S.A.S. (25%) CONSULTORIA TECNICA DE OBRAS S.A.S. (25%) | AL9: DAVINSON GRAVINI POLO | AM9: 7638300700 | AN9: 5464780815 | AO9: =AM9+AN9 -> 13103081515 | AP9: 12447568529 | AQ9: 12447568529 | AR9: 0 | AS9: 0 | AT9: 6.8911335e+08 | AU9: 0 | AV9: 0 | AW9: 2048 Habitantes | AX9: Metros Lineales intervenidos | AY9: Kilometros recuperados por Barrio | AZ9: Tramos viales inaugurados | BA9: Proceso de liquidación | BC9: No
A10: =+A9+1 -> 9 | B10: Obras Públicas | C10: CD-12-2020-2429 | D10: Línea Económica_Ciudad Dinámica | E10: Trasporte | F10: Barrios a la obra | G10: BAO_VII_2429_M9 | H10: Varias | I10: Barlovento - Kalamary - San Roque | J10: - | K10: 10°58'6.7'' N 74°46'52.8'' O | N10: Postcontractual | O10: Terminado | P10: =+AO10+AT10 -> 1.3025165e+10 | Q10: 1 | R10: 1 | S10: =+R10-Q10 -> 0 | T10: {=+_xlfn.IFS($P10<=10000000000,IF(S10>-0.05,"Verde",IF(S10<=-0.1,"Rojo","Amarillo")),$P10>10000000000,IF(S10>-0.03,"Verde",IF(S10<=-0.07,"Rojo","Amarillo")))} -> Verde | U10: 44305 | V10: 44334 | W10: 44442 | X10: 44561 | Y10: 45596 | Z10: =+IF(AND(O10="En_Ejecución",OR(T10="Rojo",T10="Amarillo")),IF(($Y10-(TODAY())<15),"Rojo",IF(($Y10-TODAY())>=45,"Verde","Amarillo")),O10) -> Terminado | AA10: =+IF(AND(Z10="Amarillo",T10="Rojo"),"En_Seguimiento",IF(AND(Z10="Rojo",T10="Amarillo"),"En_Seguimiento",IF(AND(Z10="Rojo",T10="Rojo"),"En_Seguimiento",IF(AND(Z10="Suspendido",T10="Amarillo"),"En_Seguimiento",IF(AND(Z10="Suspendido",T10="Rojo"),"En_Seguimiento","-"))))) -> - | AB10: No | AD10: 45596 | AE10: EDU-364-2021 | AF10: CONSORCIO MODULO IX | AG10: CARLOS JOAQUIN PUCHE LIZARAZO (80%) DBD INGENIERIA S.A.S. (20%) | AH10: Carlos Joaquin Puche Lizarazo | AI10: EDU-389-2021 | AJ10: CONSORCIO RUT 2021 | AK10: COINCO DE COLOMBIA S.A.S. (50%) INGENIERIA MASTER S.A.S. (25%) CONSULTORIA TECNICA DE OBRAS S.A.S. (25%) | AL10: DAVINSON GRAVINI POLO | AM10: 7593881776 | AN10: 4780494120 | AO10: =AM10+AN10 -> 12374375896 | AP10: 10705414795 | AQ10: 10705414795 | AR10: 0 | AS10: 0 | AT10: 6.5078948e+08 | AU10: 0 | AV10: 0 | AW10: 440 Habitantes | AX10: Metros Lineales intervenidos | AY10: Kilometros recuperados por Barrio | AZ10: Tramos viales inaugurados | BA10: Tramites de recibo final y terminacion, cierres de actas de vecindad, pqrs y pendientes en campo | BC10: No
A11: =+A10+1 -> 10 | B11: Obras Públicas | C11: CD-12-2020-2429 | D11: Línea Económica_Ciudad Dinámica | E11: Trasporte | F11: Barrios a la obra | G11: BAO_VII_2429_M10 | H11: Varias | I11: Los Angeles - Los Angeles II - Los Angeles III - Las Nieves - Simon Bolivar | J11: - | K11: 10°58'6.7'' N 74°46'52.8'' O | N11: Postcontractual | O11: Terminado | P11: =+AO11+AT11 -> 1.3721468e+10 | Q11: 1 | R11: 1 | S11: =+R11-Q11 -> 0 | T11: {=+_xlfn.IFS($P11<=10000000000,IF(S11>-0.05,"Verde",IF(S11<=-0.1,"Rojo","Amarillo")),$P11>10000000000,IF(S11>-0.03,"Verde",IF(S11<=-0.07,"Rojo","Amarillo")))} -> Verde | U11: 44305 | V11: 44334 | W11: 44442 | X11: 44561 | Y11: 45596 | Z11: =+IF(AND(O11="En_Ejecución",OR(T11="Rojo",T11="Amarillo")),IF(($Y11-(TODAY())<15),"Rojo",IF(($Y11-TODAY())>=45,"Verde","Amarillo")),O11) -> Terminado | AA11: =+IF(AND(Z11="Amarillo",T11="Rojo"),"En_Seguimiento",IF(AND(Z11="Rojo",T11="Amarillo"),"En_Seguimiento",IF(AND(Z11="Rojo",T11="Rojo"),"En_Seguimiento",IF(AND(Z11="Suspendido",T11="Amarillo"),"En_Seguimiento",IF(AND(Z11="Suspendido",T11="Rojo"),"En_Seguimiento","-"))))) -> - | AB11: No | AD11: 45596 | AE11: EDU-365-2021 | AF11: CARLOS JOAQUIN PUCHE LIZARAZO | AG11: CARLOS JOAQUIN PUCHE LIZARAZO (100%) | AH11: Carlos Joaquin Puche Lizarazo | AI11: EDU-389-2021 | AJ11: CONSORCIO RUT 2021 | AK11: COINCO DE COLOMBIA S.A.S. (50%) INGENIERIA MASTER S.A.S. (25%) CONSULTORIA TECNICA DE OBRAS S.A.S. (25%) | AL11: DAVINSON GRAVINI POLO | AM11: 7713151737 | AN11: 5322736268 | AO11: =AM11+AN11 -> 13035888005 | AP11: 1.0364113e+10 | AQ11: 1.0364113e+10 | AR11: 0 | AS11: 0 | AT11: 6.8557953e+08 | AU11: 0 | AV11: 0 | AW11: 1400 Habitantes | AX11: Metros Lineales intervenidos | AY11: Kilometros recuperados por Barrio | AZ11: Tramos viales inaugurados | BA11: Tramites de recibo final y terminacion, cierres de actas de vecindad, pqrs y pendientes en campo | BC11: No
A12: =+A11+1 -> 11 | B12: Obras Públicas | C12: CD-12-2020-2429 | D12: Línea Económica_Ciudad Dinámica | E12: Trasporte | F12: Barrios a la obra | G12: BAO_VII_2429_M11 | H12: Varias | I12: Alboraya - Carrizal - Las Palmas - Primero de Mayo - San Nicolas - Siape - Buenos Aires | J12: - | K12: 10°58'6.7'' N 74°46'52.8'' O | N12: Postcontractual | O12: Terminado | P12: =+AO12+AT12 -> 1.3891374e+10 | Q12: 1 | R12: 1 | S12: =+R12-Q12 -> 0 | T12: {=+_xlfn.IFS($P12<=10000000000,IF(S12>-0.05,"Verde",IF(S12<=-0.1,"Rojo","Amarillo")),$P12>10000000000,IF(S12>-0.03,"Verde",IF(S12<=-0.07,"Rojo","Amarillo")))} -> Verde | U12: 44305 | V12: 44334 | W12: 44442 | X12: 44561 | Y12: 45596 | Z12: =+IF(AND(O12="En_Ejecución",OR(T12="Rojo",T12="Amarillo")),IF(($Y12-(TODAY())<15),"Rojo",IF(($Y12-TODAY())>=45,"Verde","Amarillo")),O12) -> Terminado | AA12: =+IF(AND(Z12="Amarillo",T12="Rojo"),"En_Seguimiento",IF(AND(Z12="Rojo",T12="Amarillo"),"En_Seguimiento",IF(AND(Z12="Rojo",T12="Rojo"),"En_Seguimiento",IF(AND(Z12="Suspendido",T12="Amarillo"),"En_Seguimiento",IF(AND(Z12="Suspendido",T12="Rojo"),"En_Seguimiento","-"))))) -> - | AB12: No | AD12: 45596 | AE12: EDU-366-2021 | AF12: CONSORCIO ATLANTA | AG12: IDC 21 S.A.S. (55%) PROYECTOS DE INGENIERIA Y CONSTRUCCIONES A.R. S.A.S. (40%) AZUL CONSTRUCCIÓN Y MINERIA S.A.S. (5%) | AH12: Ismael Enrique Gomez Prada | AI12: EDU-388-2021 | AJ12: CONSORCIO INTERVIAS BARRANQUILLA | AK12: COMPAÑÍA DE INTERVENTORIAS Y CONSULTORIAS DE LA COSTA S.A.S. (59%) ROCCIA S.A.S. (30%) CGB (10%) INEXIA S.A.S. (1%) | AL12: CARLOS MASS GUERRERO | AM12: 7727867246 | AN12: 5528860714 | AO12: =AM12+AN12 -> 13256727960 | AP12: 11221659834 | AQ12: 11221659834 | AR12: 0 | AS12: 0 | AT12: 6.3464607e+08 | AU12: 0 | AV12: 0 | AW12: 2248 Habitantes | AX12: Metros Lineales intervenidos | AY12: Kilometros recuperados por Barrio | AZ12: Tramos viales inaugurados | BA12: Tramites de recibo final y terminacion, cierres de actas de vecindad, pqrs y pendientes en campo | BC12: No
A13: =+A12+1 -> 12 | B13: Obras Públicas | C13: CD-12-2020-2429 | D13: Línea Económica_Ciudad Dinámica | E13: Trasporte | F13: Barrios a la obra | G13: BAO_VII_2429_M12 | H13: Varias | I13: La Playa - Los Olivos I - Los Olivos II - El Pueblo - La Pradera | J13: - | K13: 10°58'6.7'' N 74°46'52.8'' O | N13: Postcontractual | O13: Liquidado | P13: =+AO13+AT13 -> 8.1375728e+09 | Q13: 1 | R13: 1 | S13: =+R13-Q13 -> 0 | T13: {=+_xlfn.IFS($P13<=10000000000,IF(S13>-0.05,"Verde",IF(S13<=-0.1,"Rojo","Amarillo")),$P13>10000000000,IF(S13>-0.03,"Verde",IF(S13<=-0.07,"Rojo","Amarillo")))} -> Verde | U13: 44305 | V13: 44334 | W13: 44442 | X13: 44561 | Y13: 44772 | Z13: =+IF(AND(O13="En_Ejecución",OR(T13="Rojo",T13="Amarillo")),IF(($Y13-(TODAY())<15),"Rojo",IF(($Y13-TODAY())>=45,"Verde","Amarillo")),O13) -> Liquidado | AA13: =+IF(AND(Z13="Amarillo",T13="Rojo"),"En_Seguimiento",IF(AND(Z13="Rojo",T13="Amarillo"),"En_Seguimiento",IF(AND(Z13="Rojo",T13="Rojo"),"En_Seguimiento",IF(AND(Z13="Suspendido",T13="Amarillo"),"En_Seguimiento",IF(AND(Z13="Suspendido",T13="Rojo"),"En_Seguimiento","-"))))) -> - | AB13: No | AD13: 44772 | AE13: EDU-367-2021 | AF13: CONSORCIO AZUL | AG13: CARLOS ALBERTO ROZO NADER (50%) AZUL CONSTRUCCIÓN Y MINERIA S.A.S. (50%) | AH13: Carlos Alberto Rozo Nader | AI13: EDU-388-2021 | AJ13: CONSORCIO INTERVIAS BARRANQUILLA | AK13: COMPAÑÍA DE INTERVENTORIAS Y CONSULTORIAS DE LA COSTA S.A.S. (59%) ROCCIA S.A.S. (30%) CGB (10%) INEXIA S.A.S. (1%) | AL13: CARLOS MASS GUERRERO | AM13: 7765796823 | AN13: 0 | AO13: =AM13+AN13 -> 7765796823 | AP13: 7526252083 | AQ13: 6925540108 | AR13: 0 | AS13: 0 | AT13: 3.7177594e+08 | AU13: 0 | AV13: 0 | AW13: 1408 Habitantes | AX13: Metros Lineales intervenidos | AY13: Kilometros recuperados por Barrio | AZ13: Tramos viales inaugurados | BA13: ACTIVIDADES FINALIZADAS | BC13: No
A14: =+A13+1 -> 13 | B14: Obras Públicas | C14: CD-12-2024-0002 | D14: Línea Económica_Ciudad Dinámica | E14: Trasporte | F14: Barrios a la obra | G14: BAO_VIII_0002_M1 | H14: =IFERROR(_xlfn.XLOOKUP(I14,[2]Listas!$C$2:$C$202,[2]Listas!$B$2:$B$202),"-") -> VARIAS | I14: VARIOS | J14: - | K14: =CONCATENATE(CONCATENATE( ABS(TRUNC(L14)),"°", TRUNC((ABS(L14)-ABS(TRUNC(L14)))*60),"'", ROUND((((ABS(L14)-ABS(TRUNC(L14)))*60)-TRUNC((ABS(L14)-ABS(TRUNC(L14)))*60))*60,0),"""", IF(L14<0,"O","E") ),", ",CONCATENATE( ABS(TRUNC(M14)),"°", TRUNC((ABS(M14)-ABS(TRUNC(M14)))*60),"'", ROUND((((ABS(M14)-ABS(TRUNC(M14)))*60)-TRUNC((ABS(M14)-ABS(TRUNC(M14)))*60))*60,0),"""", IF(M14<0,"S","N") )) -> 0°0'0"E, 0°0'0"N | L14: 0 | M14: 0 | N14: Contractual | O14: En_Ejecución | P14: =AO14+AT14 -> 5.5806512e+08 | Q14: 0.9268 | R14: 0.6111 | S14: =+R14-Q14 -> -0.3157 | T14: {=+_xlfn.IFS($P14<=10000000000,IF(S14>-0.05,"Verde",IF(S14<=-0.1,"Rojo","Amarillo")),$P14>10000000000,IF(S14>-0.03,"Verde",IF(S14<=-0.07,"Rojo","Amarillo")))} -> Rojo | U14: 45373 | V14: 45391 | W14: 45314 | X14: 45930 | Y14: 45930 | Z14: =+IF(AND(O14="En_Ejecución",OR(T14="Rojo",T14="Amarillo")),IF(($Y14-(TODAY())<15),"Rojo",IF(($Y14-TODAY())>=45,"Verde","Amarillo")),O14) -> Rojo | AA14: =+IF(AND(Z14="Amarillo",T14="Rojo"),"En_Seguimiento",IF(AND(Z14="Rojo",T14="Amarillo"),"En_Seguimiento",IF(AND(Z14="Rojo",T14="Rojo"),"En_Seguimiento",IF(AND(Z14="Suspendido",T14="Amarillo"),"En_Seguimiento",IF(AND(Z14="Suspendido",T14="Rojo"),"En_Seguimiento","-"))))) -> En_Seguimiento | AB14: No | AC14: - | AD14: 45930 | AE14: SA-EDU-021-2024 | AF14: CONSORCIO VIAS BAREM | AG14: BARMAR CONSTRUCCIONES S.A.S (NIT 901.234.686-5) 90% EMIRO CARLOS BARGUIL CUBILLOS (CC 78.034.207) 10% | AH14: EMIRO CARLOS BARGUIL CUBILLOS | AI14: CD-12-2024-0002 | AJ14: CONSORCIO DS | AK14: SESAC S.A (NIT 800.064.761-3) 90% DEIGMA S.A.S (NIT 900.498.688-9) 10% | AL14: ALEJANDRO ALBA QUINTERO | AM14: 5.5806512e+08 | AN14: 0 | AO14: =AM14+AN14 -> 5.5806512e+08 | AP14: 0 | AQ14: 0 | AR14: 0 | AS14: 0 | AT14: =AR14+AS14 -> 0 | AU14: 0 | AV14: 0 | AW14: NO APLICA | AX14: Metros Lineales intervenidos | AY14: Kilometros recuperados por Barrio | AZ14: Tramos viales inaugurados | BA14: Valor estimado por metro lineal del tramo, se realizan actividades de socializaciones en campo con la comunidad y levantamiento de actas de vecindad | BB14: - | BC14: No
A15: =+A14+1 -> 14 | B15: Obras Públicas | C15: CD-12-2024-0002 | D15: Línea Económica_Ciudad Dinámica | E15: Trasporte | F15: Barrios a la obra | G15: BAO_VIII_0002_M2 | H15: =IFERROR(_xlfn.XLOOKUP(I15,[2]Listas!$C$2:$C$202,[2]Listas!$B$2:$B$202),"-") -> VARIAS | I15: VARIOS | J15: - | K15: =CONCATENATE(CONCATENATE( ABS(TRUNC(L15)),"°", TRUNC((ABS(L15)-ABS(TRUNC(L15)))*60),"'", ROUND((((ABS(L15)-ABS(TRUNC(L15)))*60)-TRUNC((ABS(L15)-ABS(TRUNC(L15)))*60))*60,0),"""", IF(L15<0,"O","E") ),", ",CONCATENATE( ABS(TRUNC(M15)),"°", TRUNC((ABS(M15)-ABS(TRUNC(M15)))*60),"'", ROUND((((ABS(M15)-ABS(TRUNC(M15)))*60)-TRUNC((ABS(M15)-ABS(TRUNC(M15)))*60))*60,0),"""", IF(M15<0,"S","N") )) -> 0°0'0"E, 0°0'0"N | L15: 0 | M15: 0 | N15: Contractual | O15: En_Ejecución | P15: =AO15+AT15 -> 3.5143717e+08 | Q15: 0.9268 | R15: 0.4959 | S15: 0 | T15: {=+_xlfn.IFS($P15<=10000000000,IF(S15>-0.05,"Verde",IF(S15<=-0.1,"Rojo","Amarillo")),$P15>10000000000,IF(S15>-0.03,"Verde",IF(S15<=-0.07,"Rojo","Amarillo")))} -> Verde | U15: 45373 | V15: 45391 | W15: 45314 | X15: 45930 | Y15: 45930 | Z15: =+IF(AND(O15="En_Ejecución",OR(T15="Rojo",T15="Amarillo")),IF(($Y15-(TODAY())<15),"Rojo",IF(($Y15-TODAY())>=45,"Verde","Amarillo")),O15) -> En_Ejecución | AA15: - | AB15: No | AC15: - | AD15: 45930 | AE15: SA-EDU-007-2024 | AF15: CONSORCIO SAN CHARBEL EDU | AG15: COTES & COTES S.A.S (NIT 900.336.724-1) 70% REDES VIALES Y CONSTRUCCIONES S.A.S (NIT 900.606.651-6) 10% FUNDACIÓN OCEANIA 2030 (NIT 901.378.017-6) 10% CONSTRUCCIONES ELITE 2000 S.A.S (NIT 901.636.617-2) 10% | AH15: CARLOS KARLO COTES MADERA | AI15: CD-12-2024-0002 | AJ15: CONSORCIO DS | AK15: SESAC S.A (NIT 800.064.761-3) 90% DEIGMA S.A.S (NIT 900.498.688-9) 10% | AL15: ALEJANDRO ALBA QUINTERO | AM15: 3.5143717e+08 | AN15: 0 | AO15: =AM15+AN15 -> 3.5143717e+08 | AP15: 0 | AQ15: 0 | AR15: 0 | AS15: 0 | AT15: 0 | AU15: 0 | AV15: 0 | AW15: NO APLICA | AX15: Metros Lineales intervenidos | AY15: Kilometros recuperados por Barrio | AZ15: Tramos viales inaugurados | BA15: Valor estimado por metro lineal del tramo, se realizan actividades de socializaciones en campo con la comunidad y levantamiento de actas de vecindad | BB15: - | BC15: No
A16: =+A15+1 -> 15 | B16: Obras Públicas | C16: CD-12-2024-0002 | D16: Línea Económica_Ciudad Dinámica | E16: Trasporte | F16: Barrios a la obra | G16: BAO_VIII_0002_M3 | H16: =IFERROR(_xlfn.XLOOKUP(I16,[2]Listas!$C$2:$C$202,[2]Listas!$B$2:$B$202),"-") -> VARIAS | I16: VARIOS | J16: - | K16: =CONCATENATE(CONCATENATE( ABS(TRUNC(L16)),"°", TRUNC((ABS(L16)-ABS(TRUNC(L16)))*60),"'", ROUND((((ABS(L16)-ABS(TRUNC(L16)))*60)-TRUNC((ABS(L16)-ABS(TRUNC(L16)))*60))*60,0),"""", IF(L16<0,"O","E") ),", ",CONCATENATE( ABS(TRUNC(M16)),"°", TRUNC((ABS(M16)-ABS(TRUNC(M16)))*60),"'", ROUND((((ABS(M16)-ABS(TRUNC(M16)))*60)-TRUNC((ABS(M16)-ABS(TRUNC(M16)))*60))*60,0),"""", IF(M16<0,"S","N") )) -> 0°0'0"E, 0°0'0"N | L16: 0 | M16: 0 | N16: Contractual | O16: En_Ejecución | P16: =AO16+AT16 -> 4.254862e+08 | Q16: 0.9268 | R16: 0.3998 | S16: =+R16-Q16 -> -0.527 | T16: {=+_xlfn.IFS($P16<=10000000000,IF(S16>-0.05,"Verde",IF(S16<=-0.1,"Rojo","Amarillo")),$P16>10000000000,IF(S16>-0.03,"Verde",IF(S16<=-0.07,"Rojo","Amarillo")))} -> Rojo | U16: 45373 | V16: 45391 | W16: 45314 | X16: 45930 | Y16: 45930 | Z16: =+IF(AND(O16="En_Ejecución",OR(T16="Rojo",T16="Amarillo")),IF(($Y16-(TODAY())<15),"Rojo",IF(($Y16-TODAY())>=45,"Verde","Amarillo")),O16) -> Rojo | AA16: =+IF(AND(Z16="Amarillo",T16="Rojo"),"En_Seguimiento",IF(AND(Z16="Rojo",T16="Amarillo"),"En_Seguimiento",IF(AND(Z16="Rojo",T16="Rojo"),"En_Seguimiento",IF(AND(Z16="Suspendido",T16="Amarillo"),"En_Seguimiento",IF(AND(Z16="Suspendido",T16="Rojo"),"En_Seguimiento","-"))))) -> En_Seguimiento | AB16: No | AC16: - | AD16: 45930 | AE16: SA-EDU-008-2024 | AF16: CONSORCIO VIAS URBANAS 2024 | AG16: PLANETA PROYECTOS Y OBRAS S.A.S (NIT 901.020.571-8) 90% R&D INGENIERIA Y ARQUITECTURA S.A.S (NIT 900.554.914-9) 10% | AH16: CARLOS JOSÉ MARTÍNEZ HERNÁNDEZ | AI16: CD-12-2024-0002 | AJ16: CONSORCIO DS | AK16: SESAC S.A (NIT 800.064.761-3) 90% DEIGMA S.A.S (NIT 900.498.688-9) 10% | AL16: ALEJANDRO ALBA QUINTERO | AM16: 4.254862e+08 | AN16: 0 | AO16: =AM16+AN16 -> 4.254862e+08 | AP16: 0 | AQ16: 0 | AR16: 0 | AS16: 0 | AT16: =AR16+AS16 -> 0 | AU16: 0 | AV16: 0 | AW16: NO APLICA | AX16: Metros Lineales intervenidos | AY16: Kilometros recuperados por Barrio | AZ16: Tramos viales inaugurados | BA16: Valor estimado por metro lineal del tramo, se realizan actividades de socializaciones en campo con la comunidad y levantamiento de actas de vecindad | BB16: - | BC16: No
A17: =+A16+1 -> 16 | B17: Obras Públicas | C17: CD-12-2024-0002 | D17: Línea Económica_Ciudad Dinámica | E17: Trasporte | F17: Barrios a la obra | G17: BAO_VIII_0002_M4 | H17: =IFERROR(_xlfn.XLOOKUP(I17,[2]Listas!$C$2:$C$202,[2]Listas!$B$2:$B$202),"-") -> VARIAS | I17: VARIOS | J17: - | K17: =CONCATENATE(CONCATENATE( ABS(TRUNC(L17)),"°", TRUNC((ABS(L17)-ABS(TRUNC(L17)))*60),"'", ROUND((((ABS(L17)-ABS(TRUNC(L17)))*60)-TRUNC((ABS(L17)-ABS(TRUNC(L17)))*60))*60,0),"""", IF(L17<0,"O","E") ),", ",CONCATENATE( ABS(TRUNC(M17)),"°", TRUNC((ABS(M17)-ABS(TRUNC(M17)))*60),"'", ROUND((((ABS(M17)-ABS(TRUNC(M17)))*60)-TRUNC((ABS(M17)-ABS(TRUNC(M17)))*60))*60,0),"""", IF(M17<0,"S","N") )) -> 0°0'0"E, 0°0'0"N | L17: 0 | M17: 0 | N17: Contractual | O17: En_Ejecución | P17: =AO17+AT17 -> 6806556121 | Q17: 0.8925 | R17: 0.9718 | S17: =+R17-Q17 -> 0.0793 | T17: {=+_xlfn.IFS($P17<=10000000000,IF(S17>-0.05,"Verde",IF(S17<=-0.1,"Rojo","Amarillo")),$P17>10000000000,IF(S17>-0.03,"Verde",IF(S17<=-0.07,"Rojo","Amarillo")))} -> Verde | U17: 45373 | V17: 45391 | W17: 45314 | X17: 45930 | Y17: 45930 | Z17: =+IF(AND(O17="En_Ejecución",OR(T17="Rojo",T17="Amarillo")),IF(($Y17-(TODAY())<15),"Rojo",IF(($Y17-TODAY())>=45,"Verde","Amarillo")),O17) -> En_Ejecución | AA17: =+IF(AND(Z17="Amarillo",T17="Rojo"),"En_Seguimiento",IF(AND(Z17="Rojo",T17="Amarillo"),"En_Seguimiento",IF(AND(Z17="Rojo",T17="Rojo"),"En_Seguimiento",IF(AND(Z17="Suspendido",T17="Amarillo"),"En_Seguimiento",IF(AND(Z17="Suspendido",T17="Rojo"),"En_Seguimiento","-"))))) -> - | AB17: No | AC17: - | AD17: 45930 | AE17: SA-EDU-009-2024 | AF17: CONSORCIO G3 PAVIMENTAR BARRANQUILLA 24 | AG17: CONSTRUCCIONES Y DISEÑOS STEVENSON HERMANOS S.A.S Y/O CONDIS S.A.S (NIT 802.017.107-3) 45% MOVICONTRUCCIONES S.A.S (NIT 900.068.501-6) 45% CONSTRUCCIONES E INTERVENTORIA LEGAL S.A.S (NIT 900.606.675-8) 10% | AH17: IVAN ENRIQUE STEVENSON DEL VECCHIO | AI17: CD-12-2024-0002 | AJ17: CONSORCIO DS | AK17: SESAC S.A (NIT 800.064.761-3) 90% DEIGMA S.A.S (NIT 900.498.688-9) 10% | AL17: ALEJANDRO ALBA QUINTERO | AM17: 6806556121 | AN17: 0 | AO17: =AM17+AN17 -> 6806556121 | AP17: 0 | AQ17: 0 | AR17: 0 | AS17: 0 | AT17: =AR17+AS17 -> 0 | AU17: 0 | AV17: 0 | AW17: NO APLICA | AX17: Metros Lineales intervenidos | AY17: Kilometros recuperados por Barrio | AZ17: Tramos viales inaugurados | BA17: Valor estimado por metro lineal del tramo, se realizan actividades de socializaciones en campo con la comunidad y levantamiento de actas de vecindad | BB17: - | BC17: No
A18: =+A17+1 -> 17 | B18: Obras Públicas | C18: CD-12-2024-0002 | D18: Línea Económica_Ciudad Dinámica | E18: Trasporte | F18: Barrios a la obra | G18: BAO_VIII_0002_M5 | H18: =IFERROR(_xlfn.XLOOKUP(I18,[2]Listas!$C$2:$C$202,[2]Listas!$B$2:$B$202),"-") -> VARIAS | I18: VARIOS | J18: - | K18: =CONCATENATE(CONCATENATE( ABS(TRUNC(L18)),"°", TRUNC((ABS(L18)-ABS(TRUNC(L18)))*60),"'", ROUND((((ABS(L18)-ABS(TRUNC(L18)))*60)-TRUNC((ABS(L18)-ABS(TRUNC(L18)))*60))*60,0),"""", IF(L18<0,"O","E") ),", ",CONCATENATE( ABS(TRUNC(M18)),"°", TRUNC((ABS(M18)-ABS(TRUNC(M18)))*60),"'", ROUND((((ABS(M18)-ABS(TRUNC(M18)))*60)-TRUNC((ABS(M18)-ABS(TRUNC(M18)))*60))*60,0),"""", IF(M18<0,"S","N") )) -> 0°0'0"E, 0°0'0"N | L18: 0 | M18: 0 | N18: Contractual | O18: En_Ejecución | P18: =AO18+AT18 -> 215591272 | Q18: 0.841 | R18: 0.5995 | S18: =+R18-Q18 -> -0.2415 | T18: {=+_xlfn.IFS($P18<=10000000000,IF(S18>-0.05,"Verde",IF(S18<=-0.1,"Rojo","Amarillo")),$P18>10000000000,IF(S18>-0.03,"Verde",IF(S18<=-0.07,"Rojo","Amarillo")))} -> Rojo | U18: 45373 | V18: 45391 | W18: 45314 | X18: 45930 | Y18: 45930 | Z18: =+IF(AND(O18="En_Ejecución",OR(T18="Rojo",T18="Amarillo")),IF(($Y18-(TODAY())<15),"Rojo",IF(($Y18-TODAY())>=45,"Verde","Amarillo")),O18) -> Rojo | AA18: =+IF(AND(Z18="Amarillo",T18="Rojo"),"En_Seguimiento",IF(AND(Z18="Rojo",T18="Amarillo"),"En_Seguimiento",IF(AND(Z18="Rojo",T18="Rojo"),"En_Seguimiento",IF(AND(Z18="Suspendido",T18="Amarillo"),"En_Seguimiento",IF(AND(Z18="Suspendido",T18="Rojo"),"En_Seguimiento","-"))))) -> En_Seguimiento | AB18: No | AC18: - | AD18: 45930 | AE18: SA-EDU-010-2024 | AF18: CONSORCIO EDUBAR 2024 | AG18: OBRAS INTERVENTORIAS Y SUMINISTROS S.A.S (NIT 900.974.081-0) 90% INGENIERIA RYD S.A.S (NIT 901.499.915-4) 10% | AH18: CARMELO FAILLACE SAID | AI18: CD-12-2024-0002 | AJ18: CONSORCIO DS | AK18: SESAC S.A (NIT 800.064.761-3) 90% DEIGMA S.A.S (NIT 900.498.688-9) 10% | AL18: ALEJANDRO ALBA QUINTERO | AM18: 215591272 | AN18: 0 | AO18: =AM18+AN18 -> 215591272 | AP18: 0 | AQ18: 0 | AR18: 0 | AS18: 0 | AT18: =AR18+AS18 -> 0 | AU18: 0 | AV18: 0 | AW18: NO APLICA | AX18: Metros Lineales intervenidos | AY18: Kilometros recuperados por Barrio | AZ18: Tramos viales inaugurados | BA18: Se realizaron actividades de pavimentacion en concreto reforzado, andenes y bordillos. | BB18: - | BC18: No
A19: =+A18+1 -> 18 | B19: Obras Públicas | C19: CD-12-2024-0002 | D19: Línea Económica_Ciudad Dinámica | E19: Trasporte | F19: Barrios a la obra | G19: BAO_VIII_0002_M6 | H19: =IFERROR(_xlfn.XLOOKUP(I19,[2]Listas!$C$2:$C$202,[2]Listas!$B$2:$B$202),"-") -> VARIAS | I19: VARIOS | J19: - | K19: =CONCATENATE(CONCATENATE( ABS(TRUNC(L19)),"°", TRUNC((ABS(L19)-ABS(TRUNC(L19)))*60),"'", ROUND((((ABS(L19)-ABS(TRUNC(L19)))*60)-TRUNC((ABS(L19)-ABS(TRUNC(L19)))*60))*60,0),"""", IF(L19<0,"O","E") ),", ",CONCATENATE( ABS(TRUNC(M19)),"°", TRUNC((ABS(M19)-ABS(TRUNC(M19)))*60),"'", ROUND((((ABS(M19)-ABS(TRUNC(M19)))*60)-TRUNC((ABS(M19)-ABS(TRUNC(M19)))*60))*60,0),"""", IF(M19<0,"S","N") )) -> 0°0'0"E, 0°0'0"N | L19: 0 | M19: 0 | N19: Contractual | O19: En_Ejecución | P19: =AO19+AT19 -> 9018274387 | Q19: 0.8659 | R19: 0.8081 | S19: =+R19-Q19 -> -0.0578 | T19: {=+_xlfn.IFS($P19<=10000000000,IF(S19>-0.05,"Verde",IF(S19<=-0.1,"Rojo","Amarillo")),$P19>10000000000,IF(S19>-0.03,"Verde",IF(S19<=-0.07,"Rojo","Amarillo")))} -> Amarillo | U19: 45373 | V19: 45391 | W19: 45314 | X19: 45930 | Y19: 45930 | Z19: =+IF(AND(O19="En_Ejecución",OR(T19="Rojo",T19="Amarillo")),IF(($Y19-(TODAY())<15),"Rojo",IF(($Y19-TODAY())>=45,"Verde","Amarillo")),O19) -> Rojo | AA19: =+IF(AND(Z19="Amarillo",T19="Rojo"),"En_Seguimiento",IF(AND(Z19="Rojo",T19="Amarillo"),"En_Seguimiento",IF(AND(Z19="Rojo",T19="Rojo"),"En_Seguimiento",IF(AND(Z19="Suspendido",T19="Amarillo"),"En_Seguimiento",IF(AND(Z19="Suspendido",T19="Rojo"),"En_Seguimiento","-"))))) -> En_Seguimiento | AB19: No | AC19: - | AD19: 45930 | AE19: SA-EDU-023-2024 | AF19: CONSORCIO VIAS QUILLA | AG19: SOSDOM S.A.S (NIT 829.001.805-4) 50% RE-INGENIERIA S.A.S (NIT 900.206.366-0) 50% | AH19: SANTIAGO ANDRES DOMINGUEZ CAÑA | AI19: CD-12-2024-0002 | AJ19: PROYECTOS E INTERVENTORIAS S.A.S PI S.A.S | AK19: PROYECTOS E INTERVENTORIAS S.A.S PI S.A.S | AL19: WILSON GIOVANNI URREA URREA | AM19: 9018274387 | AN19: 0 | AO19: =AM19+AN19 -> 9018274387 | AP19: 0 | AQ19: 0 | AR19: 0 | AS19: 0 | AT19: =AR19+AS19 -> 0 | AU19: 0 | AV19: 0 | AW19: NO APLICA | AX19: Metros Lineales intervenidos | AY19: Kilometros recuperados por Barrio | AZ19: - | BA19: Se realizan actividades de socializaciones en campo con la comunidad | BB19: - | BC19: No
A20: =+A19+1 -> 19 | B20: Obras Públicas | C20: CD-12-2024-0002 | D20: Línea Económica_Ciudad Dinámica | E20: Trasporte | F20: Barrios a la obra | G20: BAO_VIII_0002_M7 | H20: =IFERROR(_xlfn.XLOOKUP(I20,[2]Listas!$C$2:$C$202,[2]Listas!$B$2:$B$202),"-") -> VARIAS | I20: VARIOS | J20: - | K20: =CONCATENATE(CONCATENATE( ABS(TRUNC(L20)),"°", TRUNC((ABS(L20)-ABS(TRUNC(L20)))*60),"'", ROUND((((ABS(L20)-ABS(TRUNC(L20)))*60)-TRUNC((ABS(L20)-ABS(TRUNC(L20)))*60))*60,0),"""", IF(L20<0,"O","E") ),", ",CONCATENATE( ABS(TRUNC(M20)),"°", TRUNC((ABS(M20)-ABS(TRUNC(M20)))*60),"'", ROUND((((ABS(M20)-ABS(TRUNC(M20)))*60)-TRUNC((ABS(M20)-ABS(TRUNC(M20)))*60))*60,0),"""", IF(M20<0,"S","N") )) -> 0°0'0"E, 0°0'0"N | L20: 0 | M20: 0 | N20: Contractual | O20: En_Ejecución | P20: =AO20+AT20 -> 9186635876 | Q20: 1 | R20: 0.6363 | S20: =+R20-Q20 -> -0.3637 | T20: {=+_xlfn.IFS($P20<=10000000000,IF(S20>-0.05,"Verde",IF(S20<=-0.1,"Rojo","Amarillo")),$P20>10000000000,IF(S20>-0.03,"Verde",IF(S20<=-0.07,"Rojo","Amarillo")))} -> Rojo | U20: 45373 | V20: 45391 | W20: 45314 | X20: 45930 | Y20: 45930 | Z20: =+IF(AND(O20="En_Ejecución",OR(T20="Rojo",T20="Amarillo")),IF(($Y20-(TODAY())<15),"Rojo",IF(($Y20-TODAY())>=45,"Verde","Amarillo")),O20) -> Rojo | AA20: =+IF(AND(Z20="Amarillo",T20="Rojo"),"En_Seguimiento",IF(AND(Z20="Rojo",T20="Amarillo"),"En_Seguimiento",IF(AND(Z20="Rojo",T20="Rojo"),"En_Seguimiento",IF(AND(Z20="Suspendido",T20="Amarillo"),"En_Seguimiento",IF(AND(Z20="Suspendido",T20="Rojo"),"En_Seguimiento","-"))))) -> En_Seguimiento | AB20: No | AC20: - | AD20: 45930 | AE20: SA-EDU-004-2024 | AF20: CONSORCIO COMPETITIVIDAD BARRANQUILLA | AG20: ESDRAS MD INGENIERIA S.A.S (NIT 900.816.446-2) 40% ALVARO HERNANDO CALDERON TORO (CC 16.625.689) 60% | AH20: ALVARO HERNANDO CALDERON TORO | AI20: CD-12-2024-0002 | AJ20: PROYECTOS E INTERVENTORIAS S.A.S PI S.A.S | AK20: PROYECTOS E INTERVENTORIAS S.A.S PI S.A.S | AL20: WILSON GIOVANNI URREA URREA | AM20: 9186635876 | AN20: 0 | AO20: =AM20+AN20 -> 9186635876 | AP20: 0 | AQ20: 0 | AR20: 0 | AS20: 0 | AT20: =AR20+AS20 -> 0 | AU20: 0 | AV20: 0 | AW20: NO APLICA | AX20: Espacio Publico recuperado | AY20: Area recuperada para vehiculos | AZ20: - | BA20: - | BB20: - | BC20: No
A21: =+A20+1 -> 20 | B21: Obras Públicas | C21: CD-12-2024-0002 | D21: Línea Económica_Ciudad Dinámica | E21: Trasporte | F21: Barrios a la obra | G21: BAO_VIII_0002_M8 | H21: =IFERROR(_xlfn.XLOOKUP(I21,[2]Listas!$C$2:$C$202,[2]Listas!$B$2:$B$202),"-") -> VARIAS | I21: VARIOS | J21: - | K21: =CONCATENATE(CONCATENATE( ABS(TRUNC(L21)),"°", TRUNC((ABS(L21)-ABS(TRUNC(L21)))*60),"'", ROUND((((ABS(L21)-ABS(TRUNC(L21)))*60)-TRUNC((ABS(L21)-ABS(TRUNC(L21)))*60))*60,0),"""", IF(L21<0,"O","E") ),", ",CONCATENATE( ABS(TRUNC(M21)),"°", TRUNC((ABS(M21)-ABS(TRUNC(M21)))*60),"'", ROUND((((ABS(M21)-ABS(TRUNC(M21)))*60)-TRUNC((ABS(M21)-ABS(TRUNC(M21)))*60))*60,0),"""", IF(M21<0,"S","N") )) -> 0°0'0"E, 0°0'0"N | L21: 0 | M21: 0 | N21: Contractual | O21: En_Ejecución | P21: =AO21+AT21 -> 12557965286 | Q21: 1 | R21: 0.8063 | S21: =+R21-Q21 -> -0.1937 | T21: {=+_xlfn.IFS($P21<=10000000000,IF(S21>-0.05,"Verde",IF(S21<=-0.1,"Rojo","Amarillo")),$P21>10000000000,IF(S21>-0.03,"Verde",IF(S21<=-0.07,"Rojo","Amarillo")))} -> Rojo | U21: 45373 | V21: 45391 | W21: 45314 | X21: 45930 | Y21: 45930 | Z21: =+IF(AND(O21="En_Ejecución",OR(T21="Rojo",T21="Amarillo")),IF(($Y21-(TODAY())<15),"Rojo",IF(($Y21-TODAY())>=45,"Verde","Amarillo")),O21) -> Rojo | AA21: =+IF(AND(Z21="Amarillo",T21="Rojo"),"En_Seguimiento",IF(AND(Z21="Rojo",T21="Amarillo"),"En_Seguimiento",IF(AND(Z21="Rojo",T21="Rojo"),"En_Seguimiento",IF(AND(Z21="Suspendido",T21="Amarillo"),"En_Seguimiento",IF(AND(Z21="Suspendido",T21="Rojo"),"En_Seguimiento","-"))))) -> En_Seguimiento | AB21: No | AC21: - | AD21: 45930 | AE21: SA-EDU-011-2024 | AF21: CONSORCIO DP 2024 | AG21: DONADO ARCE Y CIA S.A.S (NIT 890.111.275-4) 90% PACANO S.A.S (NIT 900.565.619-8) 10% | AH21: ROBERTO CARLO DONADO ARCE | AI21: CD-12-2024-0002 | AJ21: PROYECTOS E INTERVENTORIAS S.A.S PI S.A.S | AK21: PROYECTOS E INTERVENTORIAS S.A.S PI S.A.S | AL21: WILSON GIOVANNI URREA URREA | AM21: 12557965286 | AN21: 0 | AO21: =AM21+AN21 -> 12557965286 | AP21: 0 | AQ21: 0 | AR21: 0 | AS21: 0 | AT21: =AR21+AS21 -> 0 | AU21: 0 | AV21: 0 | AW21: Se Beneficia el sector de la salud, zonas educativas y puntos comerciales | AX21: Espacio Publico recuperado | AY21: Area recuperada para vehiculos | AZ21: - | BA21: Se realizan actividades de socializaciones en campo con la comunidad | BB21: - | BC21: No
A22: =+A21+1 -> 21 | B22: Obras Públicas | C22: CD-12-2024-0002 | D22: Línea Económica_Ciudad Dinámica | E22: Trasporte | F22: Barrios a la obra | G22: BAO_VIII_0002_M9 | H22: =IFERROR(_xlfn.XLOOKUP(I22,[2]Listas!$C$2:$C$202,[2]Listas!$B$2:$B$202),"-") -> VARIAS | I22: VARIOS | J22: - | K22: =CONCATENATE(CONCATENATE( ABS(TRUNC(L22)),"°", TRUNC((ABS(L22)-ABS(TRUNC(L22)))*60),"'", ROUND((((ABS(L22)-ABS(TRUNC(L22)))*60)-TRUNC((ABS(L22)-ABS(TRUNC(L22)))*60))*60,0),"""", IF(L22<0,"O","E") ),", ",CONCATENATE( ABS(TRUNC(M22)),"°", TRUNC((ABS(M22)-ABS(TRUNC(M22)))*60),"'", ROUND((((ABS(M22)-ABS(TRUNC(M22)))*60)-TRUNC((ABS(M22)-ABS(TRUNC(M22)))*60))*60,0),"""", IF(M22<0,"S","N") )) -> 0°0'0"E, 0°0'0"N | L22: 0 | M22: 0 | N22: Contractual | O22: En_Ejecución | P22: =AO22+AT22 -> 12058626643 | Q22: 0.8451 | R22: 0.7444 | S22: =+R22-Q22 -> -0.1007 | T22: {=+_xlfn.IFS($P22<=10000000000,IF(S22>-0.05,"Verde",IF(S22<=-0.1,"Rojo","Amarillo")),$P22>10000000000,IF(S22>-0.03,"Verde",IF(S22<=-0.07,"Rojo","Amarillo")))} -> Rojo | U22: 45373 | V22: 45391 | W22: 45314 | X22: 45930 | Y22: 45930 | Z22: =+IF(AND(O22="En_Ejecución",OR(T22="Rojo",T22="Amarillo")),IF(($Y22-(TODAY())<15),"Rojo",IF(($Y22-TODAY())>=45,"Verde","Amarillo")),O22) -> Rojo | AA22: =+IF(AND(Z22="Amarillo",T22="Rojo"),"En_Seguimiento",IF(AND(Z22="Rojo",T22="Amarillo"),"En_Seguimiento",IF(AND(Z22="Rojo",T22="Rojo"),"En_Seguimiento",IF(AND(Z22="Suspendido",T22="Amarillo"),"En_Seguimiento",IF(AND(Z22="Suspendido",T22="Rojo"),"En_Seguimiento","-"))))) -> En_Seguimiento | AB22: No | AC22: - | AD22: 45930 | AE22: SA-EDU-005-2024 | AF22: CONSORCIO DESARROLLO VIAL BARRANQUILLA | AG22: CONGLOMERADOTECNICO COLOMBIANO S.A.S (NIT 802.005.436-1) 90% JMD INGENIERIA DE PROYECTOS S.A.S (NIT 900.436.384-1) 10% | AI22: CD-12-2024-0002 | AJ22: PROYECTOS E INTERVENTORIAS S.A.S PI S.A.S | AK22: PROYECTOS E INTERVENTORIAS S.A.S PI S.A.S | AL22: WILSON GIOVANNI URREA URREA | AM22: 12058626643 | AN22: 0 | AO22: =AM22+AN22 -> 12058626643 | AP22: 0 | AQ22: 0 | AR22: 0 | AS22: 0 | AT22: =AR22+AS22 -> 0 | AU22: 0 | AV22: 0 | AW22: Se Beneficia el sector de la salud, zonas educativas y puntos comerciales | AX22: Espacio Publico recuperado | AY22: Area recuperada para vehiculos | AZ22: - | BA22: Se realizan actividades de socializaciones en campo con la comunidad | BB22: - | BC22: No
A23: =+A22+1 -> 22 | B23: Obras Públicas | C23: LP-026-2024 | D23: Línea Económica_Ciudad Dinámica | E23: Trasporte | F23: Barrios a la obra | G23: BAO_IX_VN_M1 | H23: =IFERROR(_xlfn.XLOOKUP(I23,[2]Listas!$C$2:$C$202,[2]Listas!$B$2:$B$202),"-") -> VARIAS | I23: VARIOS | J23: - | K23: =CONCATENATE(CONCATENATE( ABS(TRUNC(L23)),"°", TRUNC((ABS(L23)-ABS(TRUNC(L23)))*60),"'", ROUND((((ABS(L23)-ABS(TRUNC(L23)))*60)-TRUNC((ABS(L23)-ABS(TRUNC(L23)))*60))*60,0),"""", IF(L23<0,"O","E") ),", ",CONCATENATE( ABS(TRUNC(M23)),"°", TRUNC((ABS(M23)-ABS(TRUNC(M23)))*60),"'", ROUND((((ABS(M23)-ABS(TRUNC(M23)))*60)-TRUNC((ABS(M23)-ABS(TRUNC(M23)))*60))*60,0),"""", IF(M23<0,"S","N") )) -> 0°0'0"E, 0°0'0"N | L23: 0 | M23: 0 | N23: Contractual | O23: En_Ejecución | P23: =+AO23+AT23 -> 52085450531 | Q23: 0 | R23: 0.2471 | S23: =+R23-Q23 -> 0.2471 | T23: {=+_xlfn.IFS($P23<=10000000000,IF(S23>-0.05,"Verde",IF(S23<=-0.1,"Rojo","Amarillo")),$P23>10000000000,IF(S23>-0.03,"Verde",IF(S23<=-0.07,"Rojo","Amarillo")))} -> Verde | U23: 45707 | V23: 45744 | W23: 45789 | X23: 46335 | Y23: 46335 | Z23: =+IF(AND(O23="En_Ejecución",OR(T23="Rojo",T23="Amarillo")),IF(($Y23-(TODAY())<15),"Rojo",IF(($Y23-TODAY())>=45,"Verde","Amarillo")),O23) -> En_Ejecución | AA23: =+IF(AND(Z23="Amarillo",T23="Rojo"),"En_Seguimiento",IF(AND(Z23="Rojo",T23="Amarillo"),"En_Seguimiento",IF(AND(Z23="Rojo",T23="Rojo"),"En_Seguimiento",IF(AND(Z23="Suspendido",T23="Amarillo"),"En_Seguimiento",IF(AND(Z23="Suspendido",T23="Rojo"),"En_Seguimiento","-"))))) -> - | AB23: No | AC23: - | AD23: 46335 | AE23: LP-026-2024 LOTE 1 | AF23: CONSORCIO VIAS URBANAS BQ | AG23: CONVIAS: 90% (NIT 802.008.095-5) ENGENIERIA S.A.S (NIT 900.595.646-5) 10% | AH23: LUIS FRANCISCO OVALLE LLINAS | AI23: CD-12-2025-3646 | AJ23: CONSORCIO DS | AK23: N/A | AL23: N/A | AM23: 52085450531 | AO23: =AM23+AN23 -> 52085450531 | AP23: 10057307073 | AW23: NO APLICA | AX23: Km por Intervenir: 16.83 Km Intervenidos: 1.17 | AY23: Área por Intervenir: 10.13 Área Intervenida: 5.69 | AZ23: - | BA23: - | BB23: - | BC23: No
A24: =+A23+1 -> 23 | B24: Obras Públicas | C24: LP-026-2024 | D24: Línea Económica_Ciudad Dinámica | E24: Trasporte | F24: Barrios a la obra | G24: BAO_IX_VN_M2 | H24: =IFERROR(_xlfn.XLOOKUP(I24,[2]Listas!$C$2:$C$202,[2]Listas!$B$2:$B$202),"-") -> VARIAS | I24: VARIOS | J24: - | K24: =CONCATENATE(CONCATENATE( ABS(TRUNC(L24)),"°", TRUNC((ABS(L24)-ABS(TRUNC(L24)))*60),"'", ROUND((((ABS(L24)-ABS(TRUNC(L24)))*60)-TRUNC((ABS(L24)-ABS(TRUNC(L24)))*60))*60,0),"""", IF(L24<0,"O","E") ),", ",CONCATENATE( ABS(TRUNC(M24)),"°", TRUNC((ABS(M24)-ABS(TRUNC(M24)))*60),"'", ROUND((((ABS(M24)-ABS(TRUNC(M24)))*60)-TRUNC((ABS(M24)-ABS(TRUNC(M24)))*60))*60,0),"""", IF(M24<0,"S","N") )) -> 0°0'0"E, 0°0'0"N | L24: 0 | M24: 0 | N24: Contractual | O24: En_Ejecución | P24: =+AO24+AT24 -> 52033303778 | Q24: 0 | R24: 0.0742 | S24: =+R24-Q24 -> 0.0742 | T24: {=+_xlfn.IFS($P24<=10000000000,IF(S24>-0.05,"Verde",IF(S24<=-0.1,"Rojo","Amarillo")),$P24>10000000000,IF(S24>-0.03,"Verde",IF(S24<=-0.07,"Rojo","Amarillo")))} -> Verde | U24: 45707 | V24: 45744 | W24: 45784 | X24: 46335 | Y24: 46335 | Z24: =+IF(AND(O24="En_Ejecución",OR(T24="Rojo",T24="Amarillo")),IF(($Y24-(TODAY())<15),"Rojo",IF(($Y24-TODAY())>=45,"Verde","Amarillo")),O24) -> En_Ejecución | AA24: =+IF(AND(Z24="Amarillo",T24="Rojo"),"En_Seguimiento",IF(AND(Z24="Rojo",T24="Amarillo"),"En_Seguimiento",IF(AND(Z24="Rojo",T24="Rojo"),"En_Seguimiento",IF(AND(Z24="Suspendido",T24="Amarillo"),"En_Seguimiento",IF(AND(Z24="Suspendido",T24="Rojo"),"En_Seguimiento","-"))))) -> - | AB24: No | AC24: - | AD24: 46335 | AE24: LP-026-2024 LOTE 2 | AF24: UT VIAL URBANO BARRANQUILLA | AG24: PEZ VELA INGENIERÍA SAS: 99% (NIT. 901.376.745-0) CFD INGENIERÍA SAS (NIT. 900.556.186- 2) 1% | AH24: CARLOS FRANCISCO DIAZGRANADOS | AI24: CD-12-2025-3646 | AJ24: CONSORCIO DS | AK24: N/A | AL24: N/A | AM24: 52033303778 | AO24: =AM24+AN24 -> 52033303778 | AP24: 0 | AW24: NO APLICA | AX24: Km por Intervenir: 15.94 Km Intervenidos: 0.21 | AY24: Área por Intervenir: 6.99 Área Intervenida: 2.79 | AZ24: - | BA24: - | BB24: - | BC24: No
A25: =+A24+1 -> 24 | B25: Obras Públicas | C25: LP-026-2024 | D25: Línea Económica_Ciudad Dinámica | E25: Trasporte | F25: Barrios a la obra | G25: BAO_IX_VN_M3 | H25: =IFERROR(_xlfn.XLOOKUP(I25,[2]Listas!$C$2:$C$202,[2]Listas!$B$2:$B$202),"-") -> VARIAS | I25: VARIOS | J25: - | K25: =CONCATENATE(CONCATENATE( ABS(TRUNC(L25)),"°", TRUNC((ABS(L25)-ABS(TRUNC(L25)))*60),"'", ROUND((((ABS(L25)-ABS(TRUNC(L25)))*60)-TRUNC((ABS(L25)-ABS(TRUNC(L25)))*60))*60,0),"""", IF(L25<0,"O","E") ),", ",CONCATENATE( ABS(TRUNC(M25)),"°", TRUNC((ABS(M25)-ABS(TRUNC(M25)))*60),"'", ROUND((((ABS(M25)-ABS(TRUNC(M25)))*60)-TRUNC((ABS(M25)-ABS(TRUNC(M25)))*60))*60,0),"""", IF(M25<0,"S","N") )) -> 0°0'0"E, 0°0'0"N | L25: 0 | M25: 0 | N25: Contractual | O25: En_Ejecución | P25: =+AO25+AT25 -> 52104102820 | Q25: 0 | R25: 0.2117 | S25: =+R25-Q25 -> 0.2117 | T25: {=+_xlfn.IFS($P25<=10000000000,IF(S25>-0.05,"Verde",IF(S25<=-0.1,"Rojo","Amarillo")),$P25>10000000000,IF(S25>-0.03,"Verde",IF(S25<=-0.07,"Rojo","Amarillo")))} -> Verde | U25: 45707 | V25: 45744 | W25: 45785 | X25: 46335 | Y25: 46335 | Z25: =+IF(AND(O25="En_Ejecución",OR(T25="Rojo",T25="Amarillo")),IF(($Y25-(TODAY())<15),"Rojo",IF(($Y25-TODAY())>=45,"Verde","Amarillo")),O25) -> En_Ejecución | AA25: =+IF(AND(Z25="Amarillo",T25="Rojo"),"En_Seguimiento",IF(AND(Z25="Rojo",T25="Amarillo"),"En_Seguimiento",IF(AND(Z25="Rojo",T25="Rojo"),"En_Seguimiento",IF(AND(Z25="Suspendido",T25="Amarillo"),"En_Seguimiento",IF(AND(Z25="Suspendido",T25="Rojo"),"En_Seguimiento","-"))))) -> - | AB25: No | AC25: - | AD25: 46335 | AE25: LP-026-2024 LOTE 3 | AF25: UT PAVIMENTOS 2025 | AG25: JS INGENIERIA Y CONSTRUCCIONES SAS: 50% (NIT. 830.504.499-6) J.A. & ASOCIADOS SAS: 50% (NIT. 890.116.998-3) | AH25: JOSE JULIAN SAADE CURE | AI25: CD-12-2025-3646 | AJ25: CONSORCIO DS | AK25: N/A | AL25: N/A | AM25: 52104102820 | AO25: =AM25+AN25 -> 52104102820 | AP25: 5977371358 | AW25: NO APLICA | AX25: Km por Intervenir: 14.97 Km Intervenidos: 0.86 | AY25: Área por Intervenir: 8.97 Área Intervenida: 4.35 | AZ25: - | BA25: - | BB25: - | BC25: No
A26: =+A25+1 -> 25 | B26: Obras Públicas | C26: LP-026-2024 | D26: Línea Económica_Ciudad Dinámica | E26: Trasporte | F26: Barrios a la obra | G26: BAO_IX_VN_M4 | H26: =IFERROR(_xlfn.XLOOKUP(I26,[2]Listas!$C$2:$C$202,[2]Listas!$B$2:$B$202),"-") -> VARIAS | I26: VARIOS | J26: - | K26: =CONCATENATE(CONCATENATE( ABS(TRUNC(L26)),"°", TRUNC((ABS(L26)-ABS(TRUNC(L26)))*60),"'", ROUND((((ABS(L26)-ABS(TRUNC(L26)))*60)-TRUNC((ABS(L26)-ABS(TRUNC(L26)))*60))*60,0),"""", IF(L26<0,"O","E") ),", ",CONCATENATE( ABS(TRUNC(M26)),"°", TRUNC((ABS(M26)-ABS(TRUNC(M26)))*60),"'", ROUND((((ABS(M26)-ABS(TRUNC(M26)))*60)-TRUNC((ABS(M26)-ABS(TRUNC(M26)))*60))*60,0),"""", IF(M26<0,"S","N") )) -> 0°0'0"E, 0°0'0"N | L26: 0 | M26: 0 | N26: Contractual | O26: En_Ejecución | P26: =+AO26+AT26 -> 53500043499 | Q26: 0 | R26: 0.1172 | S26: =+R26-Q26 -> 0.1172 | T26: {=+_xlfn.IFS($P26<=10000000000,IF(S26>-0.05,"Verde",IF(S26<=-0.1,"Rojo","Amarillo")),$P26>10000000000,IF(S26>-0.03,"Verde",IF(S26<=-0.07,"Rojo","Amarillo")))} -> Verde | U26: 45707 | V26: 45744 | W26: 45782 | X26: 46331 | Y26: 46331 | Z26: =+IF(AND(O26="En_Ejecución",OR(T26="Rojo",T26="Amarillo")),IF(($Y26-(TODAY())<15),"Rojo",IF(($Y26-TODAY())>=45,"Verde","Amarillo")),O26) -> En_Ejecución | AA26: =+IF(AND(Z26="Amarillo",T26="Rojo"),"En_Seguimiento",IF(AND(Z26="Rojo",T26="Amarillo"),"En_Seguimiento",IF(AND(Z26="Rojo",T26="Rojo"),"En_Seguimiento",IF(AND(Z26="Suspendido",T26="Amarillo"),"En_Seguimiento",IF(AND(Z26="Suspendido",T26="Rojo"),"En_Seguimiento","-"))))) -> - | AB26: No | AC26: - | AD26: 46335 | AE26: LP-026-2024 LOTE 4 | AF26: CONSORCIO VIAS BARRANQUILLA 2025 | AG26: MOTA - ENGIL COLOMBIA S.A.S: 89,99% (NIT. 900.411.315-3); COLOMBIA ME S.A.S: 10% (NIT 901.532.801-4 ); MOTA-ENGIL ENGENHARIA E CONSTRUCAO S.A. SUCURSAL COLOMBIA: 0,01% (NIT. 900.447.078-8) | AH26: NUNO TELMO CIPRIANO VIANA ABRANCHES | AI26: CD-12-2025-3646 | AJ26: CONSORCIO DS | AK26: N/A | AL26: N/A | AM26: 53500043499 | AO26: =AM26+AN26 -> 53500043499 | AP26: 5000036700 | AW26: NO APLICA | AX26: Km por Intervenir: 14.32 Km Intervenidos: 0.69 | AY26: Área por Intervenir: 8.55 Área Intervenida: 2.31 | AZ26: - | BA26: - | BB26: - | BC26: No
A27: =+A26+1 -> 26 | B27: Obras Públicas | C27: LP-026-2024 | D27: Línea Económica_Ciudad Dinámica | E27: Trasporte | F27: Barrios a la obra | G27: BAO_IX_VN_M5 | H27: =IFERROR(_xlfn.XLOOKUP(I27,[2]Listas!$C$2:$C$202,[2]Listas!$B$2:$B$202),"-") -> VARIAS | I27: VARIOS | J27: - | K27: =CONCATENATE(CONCATENATE( ABS(TRUNC(L27)),"°", TRUNC((ABS(L27)-ABS(TRUNC(L27)))*60),"'", ROUND((((ABS(L27)-ABS(TRUNC(L27)))*60)-TRUNC((ABS(L27)-ABS(TRUNC(L27)))*60))*60,0),"""", IF(L27<0,"O","E") ),", ",CONCATENATE( ABS(TRUNC(M27)),"°", TRUNC((ABS(M27)-ABS(TRUNC(M27)))*60),"'", ROUND((((ABS(M27)-ABS(TRUNC(M27)))*60)-TRUNC((ABS(M27)-ABS(TRUNC(M27)))*60))*60,0),"""", IF(M27<0,"S","N") )) -> 0°0'0"E, 0°0'0"N | L27: 0 | M27: 0 | N27: Contractual | O27: En_Ejecución | P27: =+AO27+AT27 -> 52033303778 | Q27: 0 | R27: 0.3258 | S27: =+R27-Q27 -> 0.3258 | T27: {=+_xlfn.IFS($P27<=10000000000,IF(S27>-0.05,"Verde",IF(S27<=-0.1,"Rojo","Amarillo")),$P27>10000000000,IF(S27>-0.03,"Verde",IF(S27<=-0.07,"Rojo","Amarillo")))} -> Verde | U27: 45707 | V27: 45744 | W27: 45784 | X27: 46335 | Y27: 46335 | Z27: =+IF(AND(O27="En_Ejecución",OR(T27="Rojo",T27="Amarillo")),IF(($Y27-(TODAY())<15),"Rojo",IF(($Y27-TODAY())>=45,"Verde","Amarillo")),O27) -> En_Ejecución | AA27: =+IF(AND(Z27="Amarillo",T27="Rojo"),"En_Seguimiento",IF(AND(Z27="Rojo",T27="Amarillo"),"En_Seguimiento",IF(AND(Z27="Rojo",T27="Rojo"),"En_Seguimiento",IF(AND(Z27="Suspendido",T27="Amarillo"),"En_Seguimiento",IF(AND(Z27="Suspendido",T27="Rojo"),"En_Seguimiento","-"))))) -> - | AB27: No | AC27: - | AD27: 46335 | AE27: LP-026-2024 LOTE 5 | AF27: UT VIAL URBANO BARRANQUILLA | AG27: PEZ VELA INGENIERÍA SAS: 99% (NIT. 901.376.745-0) CFD INGENIERÍA SAS (NIT. 900.556.186- 2) 1% | AH27: CARLOS FRANCISCO DIAZGRANADOS | AI27: CD-12-2025-3646 | AJ27: CONSORCIO DS | AK27: N/A | AL27: N/A | AM27: 52033303778 | AO27: =AM27+AN27 -> 52033303778 | AP27: 0 | AW27: NO APLICA | AX27: Km por Intervenir: 20.20 Km Intervenidos: 0.57 | AY27: Área por Intervenir: 8.16 Área Intervenida: 2.63 | AZ27: - | BA27: - | BB27: - | BC27: No
A28: =+A27+1 -> 27 | B28: Obras Públicas | C28: N/A | D28: Línea Económica_Ciudad Dinámica | E28: Cultura | F28: Conchas Acústicas | G28: Concha Acústica CONIDEC | H28: =IFERROR(_xlfn.XLOOKUP(I28,[2]Listas!$C$2:$C$201,[2]Listas!$B$2:$B$201),"-") -> METROPOLITANA | I28: CIUDADELA 20 DE JULIO | J28: C 49 K 5B Sur | K28: 10,927544 N. -74,810228W | L28: -74.810228 | M28: 10.927544 | N28: Postcontractual | O28: Terminado | P28: =+AO28+AT28 -> 1569896099 | Q28: 1 | R28: 1 | S28: =+R28-Q28 -> 0 | T28: {=+_xlfn.IFS($P28<=10000000000,IF(S28>-0.05,"Verde",IF(S28<=-0.1,"Rojo","Amarillo")),$P28>10000000000,IF(S28>-0.03,"Verde",IF(S28<=-0.07,"Rojo","Amarillo")))} -> Verde | W28: 44868 | X28: 44926 | Y28: 45371 | Z28: =+IF(AND(O28="En_Ejecución",OR(T28="Rojo",T28="Amarillo")),IF(($Y28-(TODAY())<15),"Rojo",IF(($Y28-TODAY())>=45,"Verde","Amarillo")),O28) -> Terminado | AA28: =+IF(AND(Z28="Amarillo",T28="Rojo"),"En_Seguimiento",IF(AND(Z28="Rojo",T28="Amarillo"),"En_Seguimiento",IF(AND(Z28="Rojo",T28="Rojo"),"En_Seguimiento",IF(AND(Z28="Suspendido",T28="Amarillo"),"En_Seguimiento",IF(AND(Z28="Suspendido",T28="Rojo"),"En_Seguimiento","-"))))) -> - | AB28: No | AC28: - | AD28: 45371 | AE28: SA-020-2022 | AF28: CONSORCIO CEDINPRO | AG28: Turpial Ingeniería S.A.S.(70%) Central De Ingeniería y Proyectos S.A.S. (30%) | AH28: Cristian David Jimenez Yejas | AI28: N/A | AJ28: N/A | AK28: N/A | AL28: N/A | AM28: 993605126 | AN28: 576290973 | AO28: =AM28+AN28 -> 1569896099 | AP28: 984692194 | AQ28: 984692194 | AR28: 0 | AS28: 0 | AT28: =AR28+AS28 -> 0 | AU28: 0 | AV28: 0 | AW28: - | BA28: Instalación de láminas de alucobond para paneles acústicos Suministro e instalación de barandas Suministro e Instalación de Divisiones de baños en acero. Instalación de piedra muñeca en tarima. Pintura | BB28: Pendiente arreglo de observaciones, detalles y no conformidades establecidas en el acta de terminación. | BC28: No
A29: =+A28+1 -> 28 | B29: Obras Públicas | C29: N/A | D29: Línea Económica_Ciudad Dinámica | E29: Desarrollo_urbano | F29: Malecón de Sur Oriente | G29: Gran Malecón de Sur Oriente - Losa Canal | H29: =IFERROR(_xlfn.XLOOKUP(I29,[2]Listas!$C$2:$C$201,[2]Listas!$B$2:$B$201),"-") -> - | I29: - | J29: Arroyo rebolo de la 30 a la 8 | K29: 10°57'33.9"N 74°47'04.3"W | L29: -74.784453 | M29: 10.959417 | N29: Contractual | O29: En_Ejecución | P29: =+AO29+AT29 -> 9.7297212e+10 | Q29: 0.4117 | R29: 0.2551 | S29: =+R29-Q29 -> -0.1566 | T29: {=+_xlfn.IFS($P29<=10000000000,IF(S29>-0.05,"Verde",IF(S29<=-0.1,"Rojo","Amarillo")),$P29>10000000000,IF(S29>-0.03,"Verde",IF(S29<=-0.07,"Rojo","Amarillo")))} -> Rojo | U29: 45363 | V29: 45377 | W29: 45391 | X29: 45657 | Y29: 45657 | Z29: =+IF(AND(O29="En_Ejecución",OR(T29="Rojo",T29="Amarillo")),IF(($Y29-(TODAY())<15),"Rojo",IF(($Y29-TODAY())>=45,"Verde","Amarillo")),O29) -> Rojo | AA29: =+IF(AND(Z29="Amarillo",T29="Rojo"),"En_Seguimiento",IF(AND(Z29="Rojo",T29="Amarillo"),"En_Seguimiento",IF(AND(Z29="Rojo",T29="Rojo"),"En_Seguimiento",IF(AND(Z29="Suspendido",T29="Amarillo"),"En_Seguimiento",IF(AND(Z29="Suspendido",T29="Rojo"),"En_Seguimiento","-"))))) -> En_Seguimiento | AB29: No | AC29: - | AD29: 45657 | AE29: LP-002-2024 | AF29: CONSORCIO SAN FELIPE | AG29: COLOMBIA ME S.A.S. 99.99%; MOTA-ENGIL PERÚ S.A. SUCURSAL COLOMBIA 0.01% | AH29: Nuno Telmo Cipriano Viana Abranches | AI29: CD-12-2024-2106 | AJ29: EDUBAR S.A. | AK29: N/A | AL29: ANGELLY CRIALES ANIBAL | AM29: 9.2664003e+10 | AN29: 0 | AO29: =AM29+AN29 -> 9.2664003e+10 | AP29: 23298960880 | AQ29: 23298960880 | AR29: 4.633209e+09 | AS29: 0 | AT29: =AR29+AS29 -> 4.633209e+09 | AU29: 7.9600395e+08 | AV29: 7.9600395e+08 | AW29: - | AX29: Kg de acero suministrado : 790.340 Kg | BA29: Se realizaron perforaciones de anclaje en muros. Se avanzó en el ajuste de los diseños estructurales. Se avanzó en el armado de vigas y galvanizado de las mismas. Se Instalaron las primeras 20 vigas de acero en el canal. | BC29: No
A30: =+A29+1 -> 29 | B30: Obras Públicas | C30: N/A | D30: Línea Económica_Ciudad Dinámica | E30: Desarrollo_urbano | F30: Malecón de Sur Oriente | G30: Gran Malecón de Sur Oriente - Losa Canal 2 | H30: =IFERROR(_xlfn.XLOOKUP(I30,[2]Listas!$C$2:$C$201,[2]Listas!$B$2:$B$201),"-") -> - | I30: - | N30: Contractual | O30: En_Ejecución | Z30: =+IF(AND(O30="En_Ejecución",OR(T30="Rojo",T30="Amarillo")),IF(($Y30-(TODAY())<15),"Rojo",IF(($Y30-TODAY())>=45,"Verde","Amarillo")),O30) -> En_Ejecución | AA30: =+IF(AND(Z30="Amarillo",T30="Rojo"),"En_Seguimiento",IF(AND(Z30="Rojo",T30="Amarillo"),"En_Seguimiento",IF(AND(Z30="Rojo",T30="Rojo"),"En_Seguimiento",IF(AND(Z30="Suspendido",T30="Amarillo"),"En_Seguimiento",IF(AND(Z30="Suspendido",T30="Rojo"),"En_Seguimiento","-"))))) -> - | AB30: No | AC30: - | AW30: -
A31: =+A30+1 -> 30 | B31: Obras Públicas | C31: NA | D31: Línea Económica_Ciudad Dinámica | E31: Desarrollo_urbano | F31: Plazas de Mercado | G31: MP - Mercado EPM | H31: =IFERROR(_xlfn.XLOOKUP(I31,[2]Listas!$C$2:$C$201,[2]Listas!$B$2:$B$201),"-") -> NORTE-CENTRO HISTORICO | I31: VILLANUEVA | J31: Cl 30 44 100 | K31: 10°59'0.05"N. 74°46'35.27"W | L31: -74.776464 | M31: 10.983347 | N31: Postcontractual | O31: Terminado | P31: =+AO31+AT31 -> 1.0517152e+10 | Q31: 1 | R31: 1 | S31: =+R31-Q31 -> 0 | T31: {=+_xlfn.IFS($P31<=10000000000,IF(S31>-0.05,"Verde",IF(S31<=-0.1,"Rojo","Amarillo")),$P31>10000000000,IF(S31>-0.03,"Verde",IF(S31<=-0.07,"Rojo","Amarillo")))} -> Verde | U31: 43005 | V31: 43006 | W31: 43075 | X31: 43957 | Y31: 45504 | Z31: =+IF(AND(O31="En_Ejecución",OR(T31="Rojo",T31="Amarillo")),IF(($Y31-(TODAY())<15),"Rojo",IF(($Y31-TODAY())>=45,"Verde","Amarillo")),O31) -> Terminado | AA31: =+IF(AND(Z31="Amarillo",T31="Rojo"),"En_Seguimiento",IF(AND(Z31="Rojo",T31="Amarillo"),"En_Seguimiento",IF(AND(Z31="Rojo",T31="Rojo"),"En_Seguimiento",IF(AND(Z31="Suspendido",T31="Amarillo"),"En_Seguimiento",IF(AND(Z31="Suspendido",T31="Rojo"),"En_Seguimiento","-"))))) -> - | AB31: No | AC31: - | AD31: 45504 | AE31: 012017-002333 | AF31: CONSORCIO BARRANQUILLA CAN 2017 | AG31: CONSULTORIA E IMÁGENES S.A.S. AGOPLAS S.A.S. | AH31: Jairo Contreras Rincon | AI31: 012017-002447 | AJ31: CONSORCIO BARRANQUILLA 2019 | AK31: GEINCIVILES S.A.S. (25%) VALLEJO H INGENIEROS (75%) | AL31: Fabian Vallejo | AM31: 9.9390905e+09 | AN31: 0 | AO31: =AM31+AN31 -> 9.9390905e+09 | AP31: 2.2935764e+10 | AQ31: 2.1498738e+10 | AR31: 465660685 | AS31: 112400855 | AT31: =AR31+AS31 -> 578061540 | AU31: 1.0638766e+09 | AV31: 9.5650587e+08 | AW31: - | AX31: Construccion de 415 locales | BA31: Se enrgizo definitivamente el mercado | BC31: No
A32: =+A31+1 -> 31 | B32: Obras Públicas | C32: NA | D32: Línea Económica_Ciudad Dinámica | E32: Desarrollo_urbano | F32: Plazas de Mercado | G32: MP - Mercado de Granos | H32: =IFERROR(_xlfn.XLOOKUP(I32,[2]Listas!$C$2:$C$201,[2]Listas!$B$2:$B$201),"-") -> NORTE-CENTRO HISTORICO | I32: CENTRO | J32: Cra 40 28 04 | K32: 10°58'40.07"N 74°46'30.88"W | L32: -74.775244 | M32: 10.977797 | N32: Contractual | O32: En_Ejecución | P32: =+AO32+AT32 -> 1.6864171e+10 | Q32: 0.94 | R32: 0.92 | S32: =+R32-Q32 -> -0.02 | T32: {=+_xlfn.IFS($P32<=10000000000,IF(S32>-0.05,"Verde",IF(S32<=-0.1,"Rojo","Amarillo")),$P32>10000000000,IF(S32>-0.03,"Verde",IF(S32<=-0.07,"Rojo","Amarillo")))} -> Verde | U32: 43005 | V32: 43006 | W32: 43075 | X32: 43957 | Y32: 45597 | Z32: =+IF(AND(O32="En_Ejecución",OR(T32="Rojo",T32="Amarillo")),IF(($Y32-(TODAY())<15),"Rojo",IF(($Y32-TODAY())>=45,"Verde","Amarillo")),O32) -> En_Ejecución | AA32: =+IF(AND(Z32="Amarillo",T32="Rojo"),"En_Seguimiento",IF(AND(Z32="Rojo",T32="Amarillo"),"En_Seguimiento",IF(AND(Z32="Rojo",T32="Rojo"),"En_Seguimiento",IF(AND(Z32="Suspendido",T32="Amarillo"),"En_Seguimiento",IF(AND(Z32="Suspendido",T32="Rojo"),"En_Seguimiento","-"))))) -> - | AB32: No | AC32: - | AD32: 45597 | AE32: 012017-002333 | AF32: CONSORCIO BARRANQUILLA CAN 2017 | AG32: CONSULTORIA E IMÁGENES S.A.S. AGOPLAS S.A.S. | AH32: Jairo Contreras Rincon | AI32: 012017-002447 | AJ32: CONSORCIO BARRANQUILLA 2019 | AK32: GEINCIVILES S.A.S. (25%) VALLEJO H INGENIEROS (75%) | AL32: Fabian Vallejo | AM32: 9.5919899e+09 | AN32: 6694119966 | AO32: =AM32+AN32 -> 1.628611e+10 | AP32: 2.3904346e+10 | AQ32: 2.3323511e+10 | AR32: 465660685 | AS32: 112400855 | AT32: =AR32+AS32 -> 578061540 | AU32: 1.0638766e+09 | AV32: 9.5650587e+08 | AW32: - | AX32: Construccion de 131 locales | BA32: INSTALACION DE ESTRUCTURA METALICA, INSTALACION DE CORREAS, RELLENO LOCALES EXTERNOS, CONFORMACION DEL ESPACIO PUBLICO | BB32: pendiente reubicacion de locatarios externos para culminacion de la instalacion de la estructura metalica | BC32: Si
A33: =+A32+1 -> 32 | B33: Obras Públicas | C33: NA | D33: Línea Social_Ciudad Segura y Solidaria | E33: Seguridad | F33: CAI | G33: CAI Santa Maria | H33: =IFERROR(_xlfn.XLOOKUP(I33,[2]Listas!$C$2:$C$201,[2]Listas!$B$2:$B$201),"-") -> METROPOLITANA | I33: SANTA MARIA | J33: Cra. 1 sur No. 91 esquina | K33: 10°56'3.44"N 74°49'31.83"W | L33: -74.825508 | M33: 10.934289 | N33: Postcontractual | O33: Entregado | P33: =+AO33+AT33 -> 6.5358959e+08 | Q33: 1 | R33: 1 | S33: =+R33-Q33 -> 0 | T33: {=+_xlfn.IFS($P33<=10000000000,IF(S33>-0.05,"Verde",IF(S33<=-0.1,"Rojo","Amarillo")),$P33>10000000000,IF(S33>-0.03,"Verde",IF(S33<=-0.07,"Rojo","Amarillo")))} -> Verde | U33: 44439 | V33: 44441 | W33: 44525 | X33: 44561 | Y33: 45461 | Z33: =+IF(AND(O33="En_Ejecución",OR(T33="Rojo",T33="Amarillo")),IF(($Y33-(TODAY())<15),"Rojo",IF(($Y33-TODAY())>=45,"Verde","Amarillo")),O33) -> Entregado | AA33: =+IF(AND(Z33="Amarillo",T33="Rojo"),"En_Seguimiento",IF(AND(Z33="Rojo",T33="Amarillo"),"En_Seguimiento",IF(AND(Z33="Rojo",T33="Rojo"),"En_Seguimiento",IF(AND(Z33="Suspendido",T33="Amarillo"),"En_Seguimiento",IF(AND(Z33="Suspendido",T33="Rojo"),"En_Seguimiento","-"))))) -> - | AB33: No | AC33: - | AD33: 45461 | AE33: LP-006-2021 | AF33: CONSTRUCCIONES DANFEL SAS | AG33: NA | AH33: Eduardo Santos | AI33: CM-002-2021 | AJ33: CONSORCIO MEDIA LUNA | AK33: INGECINCO LTDA, ( 50%) y JUAN ANDRES CASTRO HERNANDEZ ( 50%) | AL33: Alvaro Rodriguez Perez | AM33: 382600000 | AN33: 1.8108425e+08 | AO33: =AM33+AN33 -> 5.6368425e+08 | AP33: 2.5302237e+08 | AQ33: 2.5302237e+08 | AR33: 45589070 | AS33: 44316263 | AT33: =AR33+AS33 -> 89905333 | AU33: 30327678 | AV33: 30327678 | AW33: - | BA33: CAI terminado e Inagurado | BC33: No
A34: =+A33+1 -> 33 | B34: Obras Públicas | C34: NA | D34: Línea Social_Ciudad Segura y Solidaria | E34: Seguridad | F34: CAI | G34: CAI La Paz | H34: =IFERROR(_xlfn.XLOOKUP(I34,[2]Listas!$C$2:$C$201,[2]Listas!$B$2:$B$201),"-") -> SUROCCIDENTE | I34: LA PAZ | J34: Cra. 13 No. 106 esquina | K34: 10°57'57.86"N. 74°50'4.54"W | L34: -74.834594 | M34: 10.966061 | N34: Postcontractual | O34: Entregado | P34: =+AO34+AT34 -> 7.5623118e+08 | Q34: 1 | R34: 1 | S34: =+R34-Q34 -> 0 | T34: {=+_xlfn.IFS($P34<=10000000000,IF(S34>-0.05,"Verde",IF(S34<=-0.1,"Rojo","Amarillo")),$P34>10000000000,IF(S34>-0.03,"Verde",IF(S34<=-0.07,"Rojo","Amarillo")))} -> Verde | U34: 44439 | V34: 44441 | W34: 44525 | X34: 44561 | Y34: 45461 | Z34: =+IF(AND(O34="En_Ejecución",OR(T34="Rojo",T34="Amarillo")),IF(($Y34-(TODAY())<15),"Rojo",IF(($Y34-TODAY())>=45,"Verde","Amarillo")),O34) -> Entregado | AA34: =+IF(AND(Z34="Amarillo",T34="Rojo"),"En_Seguimiento",IF(AND(Z34="Rojo",T34="Amarillo"),"En_Seguimiento",IF(AND(Z34="Rojo",T34="Rojo"),"En_Seguimiento",IF(AND(Z34="Suspendido",T34="Amarillo"),"En_Seguimiento",IF(AND(Z34="Suspendido",T34="Rojo"),"En_Seguimiento","-"))))) -> - | AB34: No | AC34: - | AD34: 45461 | AE34: LP-006-2021 | AF34: CONSTRUCCIONES DANFEL SAS | AG34: NA | AH34: Eduardo Santos | AI34: CM-002-2021 | AJ34: CONSORCIO MEDIA LUNA | AK34: INGECINCO LTDA, ( 50%) y JUAN ANDRES CASTRO HERNANDEZ ( 50%) | AL34: Alvaro Rodriguez Perez | AM34: 409200000 | AN34: 2.5087524e+08 | AO34: =AM34+AN34 -> 6.6007524e+08 | AP34: 2.7061357e+08 | AQ34: 2.7061357e+08 | AR34: 48758618 | AS34: 47397320 | AT34: =AR34+AS34 -> 96155939 | AU34: 32436189 | AV34: 32436189 | AW34: - | BA34: pañetes y pintura, obra gris | BC34: No
A35: =+A34+1 -> 34 | B35: Obras Públicas | C35: NA | D35: Línea Social_Ciudad Segura y Solidaria | E35: Seguridad | F35: CAI | G35: CAI Santo Domingo | H35: =IFERROR(_xlfn.XLOOKUP(I35,[2]Listas!$C$2:$C$201,[2]Listas!$B$2:$B$201),"-") -> METROPOLITANA | I35: SANTO DOMINGO DE GUZMAN | J35: Cra. 2 No. 62 esquina | K35: 10°56'10.02"N. 74°48'57.74"W | L35: -74.816039 | M35: 10.936117 | N35: Postcontractual | O35: Entregado | P35: =+AO35+AT35 -> 7.603197e+08 | Q35: 1 | R35: 1 | S35: =+R35-Q35 -> 0 | T35: {=+_xlfn.IFS($P35<=10000000000,IF(S35>-0.05,"Verde",IF(S35<=-0.1,"Rojo","Amarillo")),$P35>10000000000,IF(S35>-0.03,"Verde",IF(S35<=-0.07,"Rojo","Amarillo")))} -> Verde | U35: 44439 | V35: 44441 | W35: 44525 | X35: 44561 | Y35: 45461 | Z35: =+IF(AND(O35="En_Ejecución",OR(T35="Rojo",T35="Amarillo")),IF(($Y35-(TODAY())<15),"Rojo",IF(($Y35-TODAY())>=45,"Verde","Amarillo")),O35) -> Entregado | AA35: =+IF(AND(Z35="Amarillo",T35="Rojo"),"En_Seguimiento",IF(AND(Z35="Rojo",T35="Amarillo"),"En_Seguimiento",IF(AND(Z35="Rojo",T35="Rojo"),"En_Seguimiento",IF(AND(Z35="Suspendido",T35="Amarillo"),"En_Seguimiento",IF(AND(Z35="Suspendido",T35="Rojo"),"En_Seguimiento","-"))))) -> - | AB35: No | AC35: - | AD35: 45461 | AE35: LP-006-2021 | AF35: CONSTRUCCIONES DANFEL SAS | AG35: NA | AH35: Eduardo Santos | AI35: CM-002-2021 | AJ35: CONSORCIO MEDIA LUNA | AK35: INGECINCO LTDA, ( 50%) y JUAN ANDRES CASTRO HERNANDEZ ( 50%) | AL35: Alvaro Rodriguez Perez | AM35: 460325367 | AN35: 1.9182469e+08 | AO35: =AM35+AN35 -> 6.5215006e+08 | AP35: 3.0442398e+08 | AQ35: 3.0442398e+08 | AR35: 54850511 | AS35: 53319132 | AT35: =AR35+AS35 -> 1.0816964e+08 | AU35: 36488760 | AV35: 36488760 | AW35: - | BA35: Cai Terminado e Inagurado | BC35: No
A36: =+A35+1 -> 35 | B36: Obras Públicas | C36: NA | D36: Línea Económica_Ciudad Dinámica | E36: Trasporte | F36: Malla Vial | G36: Intercambiador_Alameda_CRA43 | H36: =IFERROR(_xlfn.XLOOKUP(I36,[2]Listas!$C$2:$C$201,[2]Listas!$B$2:$B$201),"-") -> NORTE-CENTRO HISTORICO | I36: ALAMEDA DEL RIO | L36: -74.833777 | M36: 11.027738 | N36: Contractual | O36: En_Ejecución | P36: =+AO36+AT36 -> 59906133530 | Q36: 0.135 | R36: 0.089 | S36: =+R36-Q36 -> -0.046 | T36: {=+_xlfn.IFS($P36<=10000000000,IF(S36>-0.05,"Verde",IF(S36<=-0.1,"Rojo","Amarillo")),$P36>10000000000,IF(S36>-0.03,"Verde",IF(S36<=-0.07,"Rojo","Amarillo")))} -> Amarillo | W36: 45391 | X36: 46121 | Y36: 46121 | Z36: =+IF(AND(O36="En_Ejecución",OR(T36="Rojo",T36="Amarillo")),IF(($Y36-(TODAY())<15),"Rojo",IF(($Y36-TODAY())>=45,"Verde","Amarillo")),O36) -> Verde | AA36: =+IF(AND(Z36="Amarillo",T36="Rojo"),"En_Seguimiento",IF(AND(Z36="Rojo",T36="Amarillo"),"En_Seguimiento",IF(AND(Z36="Rojo",T36="Rojo"),"En_Seguimiento",IF(AND(Z36="Suspendido",T36="Amarillo"),"En_Seguimiento",IF(AND(Z36="Suspendido",T36="Rojo"),"En_Seguimiento","-"))))) -> - | AB36: No | AC36: - | AD36: 45657 | AM36: 59906133530 | AN36: 0 | AO36: =AN36+AM36 -> 59906133530 | AP36: 0 | AQ36: 0 | AR36: 0 | AS36: 0 | AT36: =AR36+AS36 -> 0 | AU36: 0 | AV36: 0 | AW36: - | BC36: No
A37: =+A36+1 -> 36 | B37: Gerencia de Ciudad | C37: NA | D37: Línea Social_Ciudad Segura y Solidaria | E37: Seguridad | F37: Estaciones | G37: Seguridad_2025_Estación El Bosque | H37: Suroccidente | I37: El Bosque | J37: Cordialidad #calle 60B -110 | K37: 10°56'52.67"N. 74°48'57.29"O | L37: -74815838 | M37: 10947916
A38: =+A37+1 -> 37 | B38: Gerencia de Ciudad | C38: NA | D38: Línea Social_Ciudad Segura y Solidaria | E38: Seguridad | F38: Estaciones | G38: Seguridad_2025_Estación Caribe Verde | H38: Suroccidente | I38: Caribe Verde | J38: Avenida Caribe Verde 120 #11 d 02 | K38: 10°57'25.09"N. 74°50'38.85"O | L38: -74844167 | M38: 10957133
A39: =+A38+1 -> 38 | B39: Gerencia de Ciudad | C39: NA | D39: Línea Social_Ciudad Segura y Solidaria | E39: Seguridad | F39: Estaciones | G39: Seguridad_2025_Estación Riomar | H39: Riomar | I39: Altos de Riomar | J39: Calle 94 Cra 56 esquina | K39: 11° 0'51.60"N. 74°49'19.37"O | L39: -74822025 | M39: 11014343
A40: =+A39+1 -> 39 | B40: Gerencia de Ciudad | C40: NA | D40: Línea Social_Ciudad Segura y Solidaria | E40: Seguridad | F40: Estaciones | G40: Seguridad_2025_Estación Rebolo | H40: Suroriente | I40: Montes/Rebolo | J40: Cra 26 # 24-71 | K40: 10°57'50.99"N. 74°46'46.68"O | L40: -74779594 | M40: 10964234
A41: =+A40+1 -> 40 | B41: Gerencia de Ciudad | C41: NA | D41: Línea Social_Ciudad Segura y Solidaria | E41: Seguridad | F41: CAI | G41: Seguridad_2025_CAI La Victoria | H41: Suroriente | I41: La Victoria | J41: Av. Murillo cra 10e | K41: 10°57'9.02"N. 74°47'53.04"O | L41: -74798215 | M41: 10952332
A42: =+A41+1 -> 41 | B42: Gerencia de Ciudad | C42: NA | D42: Línea Social_Ciudad Segura y Solidaria | E42: Seguridad | F42: CAI | G42: Seguridad_2025_CAI La Alboraya | H42: Suroriente | I42: La Alboraya | J42: Calle 41b # 8-52 | K42: 10°56'47.93"N. 74°47'48.20"O | L42: -74796735 | M42: 10946749
A43: =+A42+1 -> 42 | B43: Gerencia de Ciudad | C43: NA | D43: Línea Social_Ciudad Segura y Solidaria | E43: Seguridad | F43: CAI | G43: Seguridad_2025_CAI El Limon | H43: Suroriente | I43: El Limon | J43: Calle 33c # 05-5D | K43: 10°56'29.09"N. 74°47'12.11"O | L43: -74786668 | M43: 10941457
A44: =+A43+1 -> 43 | B44: Gerencia de Ciudad | C44: NA | D44: Línea Social_Ciudad Segura y Solidaria | E44: Seguridad | F44: Mantenimeinto y adecuacion | G44: Seguridad_2025_Escuela calle 17 | H44: Suroriente | I44: Simon Bolivar | J44: Calle 17 # 7d | K44: 10°56'47.47"N. 74°46'23.60"O | L44: -74773234 | M44: 10946679
A45: =+A44+1 -> 44 | B45: Gerencia de Ciudad | C45: NA | D45: Línea Social_Ciudad Segura y Solidaria | E45: Seguridad | F45: Mantenimeinto y adecuacion | G45: Seguridad_2025_Red de apoyo (CAD)
A46: =+A45+1 -> 45 | B46: Gerencia de Ciudad | C46: NA | D46: Línea Social_Ciudad Segura y Solidaria | E46: Seguridad | F46: Mantenimeinto y adecuacion | G46: Seguridad_2025_Centro Local de Analisis Criminar (CELAC)
A47: =+A46+1 -> 46 | B47: Gerencia de Ciudad | C47: NA | D47: Línea Social_Ciudad Segura y Solidaria | E47: Seguridad | F47: Mantenimeinto y adecuacion | G47: Seguridad_2025_Interpol
A48: =+A47+1 -> 47 | B48: Gerencia de Ciudad | C48: NA | D48: Línea Social_Ciudad Segura y Solidaria | E48: Seguridad | F48: Mantenimeinto y adecuacion | G48: Seguridad_2025_Celdas en la Estacion Norte
A49: =+A48+1 -> 48 | B49: Gerencia de Ciudad | C49: NA | D49: Línea Económica_Ciudad Dinámica | E49: Cultura | F49: Edificaciones culturales | G49: Museo de Arte Moderno de Barranquilla (MAMBAQ) | H49: Norte_Centro_Histórico | I49: Barrio Abajo | J49: Cl 36 46 66 | K49: 10°59'12.86"N 74°46'41.32"W | L49: -74.778144 | M49: 10.986906 | N49: Contractual | O49: En_Ejecución | P49: =+AO49+AT49 -> 18804848036 | Q49: 0.7058 | R49: 0.6849 | S49: =+R49-Q49 -> -0.0209 | T49: {=+_xlfn.IFS($P49<=10000000000,IF(S49>-0.05,"Verde",IF(S49<=-0.1,"Rojo","Amarillo")),$P49>10000000000,IF(S49>-0.03,"Verde",IF(S49<=-0.07,"Rojo","Amarillo")))} -> Verde | W49: 45505 | X49: 45657 | Y49: 45976 | Z49: =+IF(AND(O49="En_Ejecución",OR(T49="Rojo",T49="Amarillo")),IF(($Y49-(TODAY())<15),"Rojo",IF(($Y49-TODAY())>=45,"Verde","Amarillo")),O49) -> En_Ejecución | AD49: 0 | AE49: LP-010-2024 | AF49: CONSORCIO MUSEO DE ARTE 010 | AH49: Jairo Contreras Rincon | AI49: CD-52-2024-3636 | AJ49: EDUBAR S.A. | AM49: 17404848036 | AN49: 0 | AO49: =AM49+AN49 -> 17404848036 | AP49: 9.0363728e+09 | AQ49: 9.0363728e+09 | AR49: 1400000000 | AS49: 0 | AT49: =AR49+AS49 -> 1400000000 | AU49: 6.7996818e+08 | AV49: 6.7996818e+08 | BA49: Levantamiento de actas de vecindad y revisión de estudios y diseños. | BB49: Levantamiento de actas de vecindad y revisión de estudios y diseños. | BC49: No
A50: =+A49+1 -> 49 | B50: EDUBAR | C50: CD-12-2020-2435 | D50: Línea Ambiental_Ciudad Ambiental y Sostenible | E50: EcoTurismo | F50: EcoParque Mallonquín | G50: Ecoparque Mallorquin-2435 - UF-1 | H50: Riomar | I50: La Playa | K50: 11°01'51"N 74°50'35"W | L50: -74.845851 | M50: 11.031815 | N50: Postcontractual | O50: Terminado | P50: =+AO50+AT50 -> 87873793990 | Q50: 1 | R50: 1 | S50: =+R50-Q50 -> 0 | T50: {=+_xlfn.IFS($P50<=10000000000,IF(S50>-0.05,"Verde",IF(S50<=-0.1,"Rojo","Amarillo")),$P50>10000000000,IF(S50>-0.03,"Verde",IF(S50<=-0.07,"Rojo","Amarillo")))} -> Verde | U50: 44377 | V50: 44398 | W50: 44440 | X50: 44561 | Y50: 45378 | Z50: =+IF(AND(O50="En_Ejecución",OR(T50="Rojo",T50="Amarillo")),IF(($Y50-(TODAY())<15),"Rojo",IF(($Y50-TODAY())>=45,"Verde","Amarillo")),O50) -> Terminado | AA50: =+IF(AND(Z50="Amarillo",T50="Rojo"),"En_Seguimiento",IF(AND(Z50="Rojo",T50="Amarillo"),"En_Seguimiento",IF(AND(Z50="Rojo",T50="Rojo"),"En_Seguimiento",IF(AND(Z50="Suspendido",T50="Amarillo"),"En_Seguimiento",IF(AND(Z50="Suspendido",T50="Rojo"),"En_Seguimiento","-"))))) -> - | AD50: 45378 | AE50: EDU-561-2021 | AF50: CONSORCIO JCO MALLORQUÍN | AG50: JACUR S.A.S 75% & OBRACI CONSTRUCCIONES S.A.S 25% | AH50: Adalberto Vivero Coronel | AI50: EDU-566-2021 | AJ50: CONSORCIO UF1 MALLORQUÍN | AK50: INGENIERÍA DE PROYECTOS S.A.S 60% & INP SERVICIOS S.A.S 40% | AL50: PEDRO ANTONIO GUTIERREZ VISBAL | AM50: 82464264620 | AN50: 0 | AO50: =AM50+AN50 -> 82464264620 | AP50: 8.2327509e+10 | AQ50: 7.3910048e+10 | AR50: 3974629750 | AS50: 1434899620 | AT50: =AR50+AS50 -> 5409529370 | AU50: 4.6938415e+09 | AV50: 4.5938415e+09 | AW50: Se estima que influye directamente en el barrios las Flores con un número de 7.900 habitantes aproximadamente y en el Corregimiento La Playa con el número de 12.648 habitantes. | AX50: uso sostenible por parte de la población y el fortalecimiento del ecoturismo. | AY50: Impacto en la población potencializando la vocación turistica del sector y el sentido de pertenencia hacia la cienaga y el ma | AZ50: Desarrollar una zona de esparcimiento público y de encuentro con la naturaleza. | BA50: proceso de liquidación | BC50: Si
A51: =+A50+1 -> 50 | B51: EDUBAR | C51: Contrato Específico No. 2210698 Derivado del Pacto Funcional Atlántico - CONTRATO DE MANDATO N.º 221009 – Suscrito entre EL DNP Y ENTERRITORIO | D51: Línea Ambiental_Ciudad Ambiental y Sostenible | E51: EcoTurismo | F51: EcoParque Mallonquín | G51: Ecoparque Mallorquin-0698 - UF-2 | H51: Riomar | I51: La Playa | K51: 11°02'07.5"N 74°50'18.8"W | L51: -74.838556 | M51: 11.035417 | N51: Postcontractual | O51: Terminado | P51: =+AO51+AT51 -> 116179263051 | Q51: 1 | R51: 1 | S51: =+R51-Q51 -> 0 | T51: {=+_xlfn.IFS($P51<=10000000000,IF(S51>-0.05,"Verde",IF(S51<=-0.1,"Rojo","Amarillo")),$P51>10000000000,IF(S51>-0.03,"Verde",IF(S51<=-0.07,"Rojo","Amarillo")))} -> Verde | U51: 44609 | V51: 44622 | W51: 44697 | X51: 45001 | Y51: 45596 | Z51: =+IF(AND(O51="En_Ejecución",OR(T51="Rojo",T51="Amarillo")),IF(($Y51-(TODAY())<15),"Rojo",IF(($Y51-TODAY())>=45,"Verde","Amarillo")),O51) -> Terminado | AA51: =+IF(AND(Z51="Amarillo",T51="Rojo"),"En_Seguimiento",IF(AND(Z51="Rojo",T51="Amarillo"),"En_Seguimiento",IF(AND(Z51="Rojo",T51="Rojo"),"En_Seguimiento",IF(AND(Z51="Suspendido",T51="Amarillo"),"En_Seguimiento",IF(AND(Z51="Suspendido",T51="Rojo"),"En_Seguimiento","-"))))) -> - | AD51: 45596 | AE51: EDU-267-2022 | AF51: TICOM | AH51: Jose Maria Vecino Villarreal | AI51: EDU-279-2022 | AJ51: CONSORCIO ECOPARQUES | AK51: HM INGENIERA S.A.S INGENIERIA MASTER S.A.S. INGENIERIA MATRIZ S.A.S. | AL51: LILIANA MARGARITA ARAOS BERARDINELLI | AM51: 113014745304 | AN51: 0 | AO51: =AM51+AN51 -> 113014745304 | AP51: 1.0171103e+11 | AQ51: 1.0171103e+11 | AR51: 2656000579 | AS51: 508517168 | AT51: =AR51+AS51 -> 3164517747 | AU51: 2.848066e+09 | AV51: 2.848066e+09 | AW51: Se estima que influye directamente en el barrios las Flores con un número de 7.900 habitantes aproximadamente y en el Corregimiento La Playa con el número de 12.648 habitantes. | AX51: uso sostenible por parte de la población y el fortalecimiento del ecoturismo. | AY51: Impacto en la población potencializando la vocación turistica del sector y el sentido de pertenencia hacia la cienaga y el ma | AZ51: Desarrollar una zona de esparcimiento público y de encuentro con la naturaleza. | BA51: proceso de liquidación | BC51: Si
A52: =+A51+1 -> 51 | B52: EDUBAR | C52: CD-12-2020-2435 | D52: Línea Ambiental_Ciudad Ambiental y Sostenible | E52: EcoTurismo | F52: Tren Turistico | G52: Ecoparque Mallorquin-2435 - Tren Tajamar | H52: Riomar | I52: Las Flores | K52: 11°02'42"N 74°49'37"W | L52: -74.829962 | M52: 11.0457 | N52: Postcontractual | O52: Terminado | P52: =+AO52+AT52 -> 5.1953168e+10 | Q52: 1 | R52: 1 | S52: =+R52-Q52 -> 0 | T52: {=+_xlfn.IFS($P52<=10000000000,IF(S52>-0.05,"Verde",IF(S52<=-0.1,"Rojo","Amarillo")),$P52>10000000000,IF(S52>-0.03,"Verde",IF(S52<=-0.07,"Rojo","Amarillo")))} -> Verde | U52: 44434 | V52: 44494 | W52: 44529 | X52: 44561 | Y52: 45565 | Z52: =+IF(AND(O52="En_Ejecución",OR(T52="Rojo",T52="Amarillo")),IF(($Y52-(TODAY())<15),"Rojo",IF(($Y52-TODAY())>=45,"Verde","Amarillo")),O52) -> Terminado | AA52: =+IF(AND(Z52="Amarillo",T52="Rojo"),"En_Seguimiento",IF(AND(Z52="Rojo",T52="Amarillo"),"En_Seguimiento",IF(AND(Z52="Rojo",T52="Rojo"),"En_Seguimiento",IF(AND(Z52="Suspendido",T52="Amarillo"),"En_Seguimiento",IF(AND(Z52="Suspendido",T52="Rojo"),"En_Seguimiento","-"))))) -> - | AD52: 45565 | AE52: EDU-783-2021 | AF52: CONSORCIO TREN MALLORQUÍN | AG52: AMBIENTALES Y CONSTRUCCIÓN S.A.S 50% & INGECON S.A. 50% | AH52: Andres Felipe Sorzano | AI52: EDU-784-2021 | AJ52: CONSORCIO MALLORQUÍN | AK52: TNM LIMITED 50% & BLANCA LILLYAM TABARES 50% | AL52: BLANCA LILLYAM TABARES | AM52: 34080465796 | AN52: 1.3111924e+10 | AO52: =AM52+AN52 -> 4.719239e+10 | AP52: 4.4244542e+10 | AQ52: 4.119826e+10 | AR52: 1526326725 | AS52: 3234450940 | AT52: =AR52+AS52 -> 4760777665 | AU52: 4387474665 | AV52: 3.2558989e+09 | AW52: 8000 personas beneficiadas directamente en el Barrio de Las Flores | AX52: mejoramiento de la vía actual, incluir un sendero peatonal y cicloruta | AY52: recuperación de los vagones y su riel con dos estaciones para la recogida de pasajeros | AZ52: Pontencializar la vocación turistica del sector. | BA52: proceso de liquidación | BB52: En proceso de liquidación. | BC52: Si
A53: =+A52+1 -> 52 | B53: EDUBAR | C53: CD-12-2021-4477 | D53: Línea Ambiental_Ciudad Ambiental y Sostenible | E53: EcoTurismo | F53: Recuperación Playas de Puerto Mocho | G53: Playa de Puerto Mocho (Playa 2) | H53: Riomar | I53: Las Flores | K53: 11°03'16"N 74°50'26"W | L53: -74.844958 | M53: 11.060215 | N53: Postcontractual | O53: Terminado | P53: =+AO53+AT53 -> 25046584645 | Q53: 1 | R53: 1 | S53: =+R53-Q53 -> 0 | T53: {=+_xlfn.IFS($P53<=10000000000,IF(S53>-0.05,"Verde",IF(S53<=-0.1,"Rojo","Amarillo")),$P53>10000000000,IF(S53>-0.03,"Verde",IF(S53<=-0.07,"Rojo","Amarillo")))} -> Verde | U53: 44630 | V53: 44655 | W53: 44795 | X53: 44926 | Y53: 45596 | Z53: =+IF(AND(O53="En_Ejecución",OR(T53="Rojo",T53="Amarillo")),IF(($Y53-(TODAY())<15),"Rojo",IF(($Y53-TODAY())>=45,"Verde","Amarillo")),O53) -> Terminado | AA53: =+IF(AND(Z53="Amarillo",T53="Rojo"),"En_Seguimiento",IF(AND(Z53="Rojo",T53="Amarillo"),"En_Seguimiento",IF(AND(Z53="Rojo",T53="Rojo"),"En_Seguimiento",IF(AND(Z53="Suspendido",T53="Amarillo"),"En_Seguimiento",IF(AND(Z53="Suspendido",T53="Rojo"),"En_Seguimiento","-"))))) -> - | AD53: 45596 | AE53: EDU-275-2022 | AF53: UNION TEMPORAL PUERTO MAR | AG53: SEACOR S.A.S. E.S.P. (51%) ESI DE COLOMBIA S.A.S (40%) VIÑAS RUSSI (9%) | AH53: Rafi Farh Carbonell | AI53: EDU-343-2022 | AJ53: CONSORCIO CAYNEXIA | AK53: CAYENA CONSULTORES E INTERVENTORES S.A.S. (80%) INEXIA S.A.S. (20%) | AL53: LUIS BAUTISTA CARVAJAL | AM53: 23091329705 | AO53: =AM53+AN53 -> 23091329705 | AP53: 2.7252198e+10 | AQ53: 2.7252198e+10 | AR53: 1673561307 | AS53: 281693633 | AT53: =AR53+AS53 -> 1955254940 | AU53: 1794573057 | AV53: 1.4642435e+09 | AW53: 8000 personas beneficiadas directamente en el Barrio de Las Flores | AX53: recuperar el valor natural de la playa y generar nuevos atractivos que posibiliten la reactivación del turismo sostenible y responsable. | AY53: Desarrollar estrategias integrales, que permitan consolidar el entorno creando conexiones e interacciones con nuevos equipamientos como el Ecoparque Ciénaga de mallorquín y potenciando la accesibilidad a través del tren turístico las Flores. | AZ53: rehabilitar la playa y convertirla en un espacio de intercambio cultural y social, con diferentes usos, que favorezcan la economía del sector y que revitalicen el borde costero del atlántico y lo integren con la ciudad. | BA53: proceso de liquidación | BC53: Si
A54: =+A53+1 -> 53 | B54: EDUBAR | C54: CD-12-2021-4477 | D54: Línea Ambiental_Ciudad Ambiental y Sostenible | E54: EcoTurismo | F54: Recuperación Playas de Puerto Mocho | G54: Playa de Puerto Mocho - Adición No.1 (playa 1) | H54: Riomar | I54: Las Flores | K54: 11°03'16"N 74°50'26"W | N54: Postcontractual | O54: Terminado | P54: 1.5877909e+10 | Q54: 1 | R54: 1 | S54: =+R54-Q54 -> 0 | T54: {=+_xlfn.IFS($P54<=10000000000,IF(S54>-0.05,"Verde",IF(S54<=-0.1,"Rojo","Amarillo")),$P54>10000000000,IF(S54>-0.03,"Verde",IF(S54<=-0.07,"Rojo","Amarillo")))} -> Verde | U54: 44630 | V54: 44655 | W54: 45405 | X54: 45504 | Y54: 45596 | Z54: =+IF(AND(O54="En_Ejecución",OR(T54="Rojo",T54="Amarillo")),IF(($Y54-(TODAY())<15),"Rojo",IF(($Y54-TODAY())>=45,"Verde","Amarillo")),O54) -> Terminado | AA54: =+IF(AND(Z54="Amarillo",T54="Rojo"),"En_Seguimiento",IF(AND(Z54="Rojo",T54="Amarillo"),"En_Seguimiento",IF(AND(Z54="Rojo",T54="Rojo"),"En_Seguimiento",IF(AND(Z54="Suspendido",T54="Amarillo"),"En_Seguimiento",IF(AND(Z54="Suspendido",T54="Rojo"),"En_Seguimiento","-"))))) -> - | AD54: 45596 | AE54: EDU-275-2022 | AF54: UNION TEMPORAL PUERTO MAR | AG54: SEACOR S.A.S. E.S.P. (51%) ESI DE COLOMBIA S.A.S (40%) VIÑAS RUSSI (9%) | AH54: Rafi Farh Carbonell | AI54: EDU-343-2022 | AJ54: CONSORCIO CAYNEXIA | AK54: CAYENA CONSULTORES E INTERVENTORES S.A.S. (80%) INEXIA S.A.S. (20%) | AL54: LUIS BAUTISTA CARVAJAL | AN54: 15009346085 | AO54: =AM54+AN54 -> 15009346085 | AS54: 8.6856277e+08 | AT54: =AR54+AS54 -> 8.6856277e+08 | AW54: 8000 personas beneficiadas directamente en el Barrio de Las Flores | AX54: recuperar el valor natural de la playa y generar nuevos atractivos que posibiliten la reactivación del turismo sostenible y responsable. | AY54: Desarrollar estrategias integrales, que permitan consolidar el entorno creando conexiones e interacciones con nuevos equipamientos como el Ecoparque Ciénaga de mallorquín y potenciando la accesibilidad a través del tren turístico las Flores. | AZ54: rehabilitar la playa y convertirla en un espacio de intercambio cultural y social, con diferentes usos, que favorezcan la economía del sector y que revitalicen el borde costero del atlántico y lo integren con la ciudad. | BC54: Si
A55: =+A54+1 -> 54 | B55: EDUBAR | C55: CD-57-2021-2989 | D55: Línea Económica_Ciudad Dinámica | E55: Desarrollo_urbano | F55: Plazas de Mercado | G55: MP-2989 - Mercado Tajamar | H55: Riomar | I55: Las Flores | J55: calle 106 con 111 | K55: 11°02'42"N 74°49'37"W | L55: -74.826944 | M55: 11.045 | N55: Postcontractual | O55: Entregado | P55: 12636583690 | Q55: 1 | R55: 1 | S55: =+R55-Q55 -> 0 | T55: {=+_xlfn.IFS($P55<=10000000000,IF(S55>-0.05,"Verde",IF(S55<=-0.1,"Rojo","Amarillo")),$P55>10000000000,IF(S55>-0.03,"Verde",IF(S55<=-0.07,"Rojo","Amarillo")))} -> Verde | U55: 44511 | V55: 44557 | W55: 44643 | X55: 44926 | Y55: 45540 | Z55: =+IF(AND(O55="En_Ejecución",OR(T55="Rojo",T55="Amarillo")),IF(($Y55-(TODAY())<15),"Rojo",IF(($Y55-TODAY())>=45,"Verde","Amarillo")),O55) -> Entregado | AA55: =+IF(AND(Z55="Amarillo",T55="Rojo"),"En_Seguimiento",IF(AND(Z55="Rojo",T55="Amarillo"),"En_Seguimiento",IF(AND(Z55="Rojo",T55="Rojo"),"En_Seguimiento",IF(AND(Z55="Suspendido",T55="Amarillo"),"En_Seguimiento",IF(AND(Z55="Suspendido",T55="Rojo"),"En_Seguimiento","-"))))) -> - | AD55: 45540 | AE55: EDU-868-2021 | AF55: CONSORCIO MERCADOS BARRANQUILLA 2022 | AG55: AE INGENIEROS CIVILES SAS (99%) CABV CONSULTORIA Y CONSTRUCCIONES SAS (1%) | AH55: Antonio Escorcia | AI55: EDU-264-2022 | AJ55: CONSORCIO MP BARRANQUILLA | AK55: ECOVIAS S.A.S (70%) ALPHA GRUPO CONSULTOR E INTERVENTOR S.A.S (30%) | AL55: LUIGGI PUGLIESE MERCADO | AM55: 12636583690 | AN55: 0 | AO55: =AM55+AN55 -> 12636583690 | AP55: 8.0675437e+10 | AQ55: 8.0502233e+10 | AR55: 2506709098 | AS55: 2372520475 | AT55: =AR55+AS55 -> 4879229573 | AU55: 4.5208727e+09 | AV55: 3.2329775e+09 | AW55: 8000 personas beneficiadas en el Barrio de Las Flores | AX55: liberacion de areas de espacio publico( vias, andenes) | AY55: mejoramiento de infraestructura publica | AZ55: impulso economico mediante incremento de turistas en la zona | BC55: Si
A56: =+A55+1 -> 55 | B56: EDUBAR | C56: CD-57-2021-2989 | D56: Línea Económica_Ciudad Dinámica | E56: Desarrollo_urbano | F56: Plazas de Mercado | G56: MP-2989 - Mercado Sredni | H56: Norte_Centro_Histórico | I56: Centro | J56: calle 38 con 43 | K56: 10°58'54"N 74°46'48"W | L56: -74.781064 | M56: 10.981995 | N56: Postcontractual | O56: Entregado | P56: 7709538000 | Q56: 1 | R56: 1 | S56: =+R56-Q56 -> 0 | T56: {=+_xlfn.IFS($P56<=10000000000,IF(S56>-0.05,"Verde",IF(S56<=-0.1,"Rojo","Amarillo")),$P56>10000000000,IF(S56>-0.03,"Verde",IF(S56<=-0.07,"Rojo","Amarillo")))} -> Verde | U56: 44511 | V56: 44557 | W56: 44643 | X56: 44926 | Y56: 45343 | Z56: =+IF(AND(O56="En_Ejecución",OR(T56="Rojo",T56="Amarillo")),IF(($Y56-(TODAY())<15),"Rojo",IF(($Y56-TODAY())>=45,"Verde","Amarillo")),O56) -> Entregado | AA56: =+IF(AND(Z56="Amarillo",T56="Rojo"),"En_Seguimiento",IF(AND(Z56="Rojo",T56="Amarillo"),"En_Seguimiento",IF(AND(Z56="Rojo",T56="Rojo"),"En_Seguimiento",IF(AND(Z56="Suspendido",T56="Amarillo"),"En_Seguimiento",IF(AND(Z56="Suspendido",T56="Rojo"),"En_Seguimiento","-"))))) -> - | AD56: 45343 | AE56: EDU-868-2021 | AF56: CONSORCIO MERCADOS BARRANQUILLA 2022 | AG56: AE INGENIEROS CIVILES SAS (99%) CABV CONSULTORIA Y CONSTRUCCIONES SAS (1%) | AH56: Antonio Escorcia | AI56: EDU-264-2022 | AJ56: CONSORCIO MP BARRANQUILLA | AK56: ECOVIAS S.A.S (70%) ALPHA GRUPO CONSULTOR E INTERVENTOR S.A.S (30%) | AL56: LUIGGI PUGLIESE MERCADO | AM56: 7709538000 | AN56: 0 | AO56: =AM56+AN56 -> 7709538000 | AP56: 8.0675437e+10 | AQ56: 8.0502233e+10 | AR56: 2506709098 | AS56: 2372520475 | AT56: =AR56+AS56 -> 4879229573 | AU56: 4.5208727e+09 | AV56: 3.2329775e+09 | AW56: 155 vendedores que ocupaban el espacio publico | AX56: liberacion de areas de espacio publico( vias, andenes) | AY56: dignificacion de labor de trabajo | AZ56: mejoramiento de sanidad en espacio publico | BC56: No
A57: =+A56+1 -> 56 | B57: EDUBAR | C57: CD-57-2021-2989 | D57: Línea Económica_Ciudad Dinámica | E57: Desarrollo_urbano | F57: Plazas de Mercado | G57: MP-2989 - Mercado Del Rio | H57: Norte_Centro_Histórico | I57: La Loma | K57: 10°59'35.0"N 74°46'11.9"W | L57: -74.769972 | M57: 10.993056 | N57: Contractual | O57: En_Ejecución | P57: 2.9920188e+10 | Q57: 0.99 | R57: 0.9302 | S57: =+R57-Q57 -> -0.0598 | T57: {=+_xlfn.IFS($P57<=10000000000,IF(S57>-0.05,"Verde",IF(S57<=-0.1,"Rojo","Amarillo")),$P57>10000000000,IF(S57>-0.03,"Verde",IF(S57<=-0.07,"Rojo","Amarillo")))} -> Amarillo | U57: 44511 | V57: 44557 | W57: 44643 | X57: 44926 | Y57: 45991 | Z57: =+IF(AND(O57="En_Ejecución",OR(T57="Rojo",T57="Amarillo")),IF(($Y57-(TODAY())<15),"Rojo",IF(($Y57-TODAY())>=45,"Verde","Amarillo")),O57) -> Amarillo | AA57: =+IF(AND(Z57="Amarillo",T57="Rojo"),"En_Seguimiento",IF(AND(Z57="Rojo",T57="Amarillo"),"En_Seguimiento",IF(AND(Z57="Rojo",T57="Rojo"),"En_Seguimiento",IF(AND(Z57="Suspendido",T57="Amarillo"),"En_Seguimiento",IF(AND(Z57="Suspendido",T57="Rojo"),"En_Seguimiento","-"))))) -> - | AD57: 45991 | AE57: EDU-868-2021 | AF57: CONSORCIO MERCADOS BARRANQUILLA 2022 | AG57: AE INGENIEROS CIVILES SAS (99%) CABV CONSULTORIA Y CONSTRUCCIONES SAS (1%) | AH57: Antonio Escorcia | AI57: EDU-264-2022 | AJ57: CONSORCIO MP BARRANQUILLA | AK57: ECOVIAS S.A.S (70%) ALPHA GRUPO CONSULTOR E INTERVENTOR S.A.S (30%) | AL57: LUIGGI PUGLIESE MERCADO | AM57: 2.9920188e+10 | AN57: 0 | AO57: =AM57+AN57 -> 2.9920188e+10 | AP57: 8.0675437e+10 | AQ57: 8.0502233e+10 | AR57: 2506709098 | AS57: 2372520475 | AT57: =AR57+AS57 -> 4879229573 | AU57: 4.5208727e+09 | AV57: 3.2329775e+09 | AW57: 341 vendedores que ocupan el espacio publico actualemente seran ubicados en el proyecto | AX57: liberacion de areas de espacio publico( vias, andenes) | AY57: dignificacion de labor de trabajo | AZ57: mejoramiento de sanidad en espacio publico | BC57: Si
A58: =+A57+1 -> 57 | B58: EDUBAR | C58: CD-57-2021-2989 | D58: Línea Económica_Ciudad Dinámica | E58: Desarrollo_urbano | F58: Plazas de Mercado | G58: MP-2989 - Mercado La Magola | H58: Norte_Centro_Histórico | I58: Centro | J58: cra 42B entre calles 31 y 33 | K58: 10°58'46"N 74°46'32"W | L58: -74.775379 | M58: 10.979354 | N58: Postcontractual | O58: Entregado | P58: 1050450000 | Q58: 1 | R58: 1 | S58: =+R58-Q58 -> 0 | T58: {=+_xlfn.IFS($P58<=10000000000,IF(S58>-0.05,"Verde",IF(S58<=-0.1,"Rojo","Amarillo")),$P58>10000000000,IF(S58>-0.03,"Verde",IF(S58<=-0.07,"Rojo","Amarillo")))} -> Verde | U58: 44511 | V58: 44557 | W58: 44643 | X58: 44926 | Y58: 45473 | Z58: =+IF(AND(O58="En_Ejecución",OR(T58="Rojo",T58="Amarillo")),IF(($Y58-(TODAY())<15),"Rojo",IF(($Y58-TODAY())>=45,"Verde","Amarillo")),O58) -> Entregado | AA58: =+IF(AND(Z58="Amarillo",T58="Rojo"),"En_Seguimiento",IF(AND(Z58="Rojo",T58="Amarillo"),"En_Seguimiento",IF(AND(Z58="Rojo",T58="Rojo"),"En_Seguimiento",IF(AND(Z58="Suspendido",T58="Amarillo"),"En_Seguimiento",IF(AND(Z58="Suspendido",T58="Rojo"),"En_Seguimiento","-"))))) -> - | AD58: 45473 | AE58: EDU-868-2021 | AF58: CONSORCIO MERCADOS BARRANQUILLA 2022 | AG58: AE INGENIEROS CIVILES SAS (99%) CABV CONSULTORIA Y CONSTRUCCIONES SAS (1%) | AH58: Antonio Escorcia | AI58: EDU-264-2022 | AJ58: CONSORCIO MP BARRANQUILLA | AK58: ECOVIAS S.A.S (70%) ALPHA GRUPO CONSULTOR E INTERVENTOR S.A.S (30%) | AL58: LUIGGI PUGLIESE MERCADO | AM58: 1050450000 | AN58: 0 | AO58: =AM58+AN58 -> 1050450000 | AP58: 8.0675437e+10 | AQ58: 8.0502233e+10 | AR58: 2506709098 | AS58: 2372520475 | AT58: =AR58+AS58 -> 4879229573 | AU58: 4.5208727e+09 | AV58: 3.2329775e+09 | AW58: 328 locales mejorados | AX58: Mejoramiento de cubierta | AY58: mejoramiento de zonas de circulacion | AZ58: dignificacion de labor de trabajo | BC58: No
A59: =+A58+1 -> 58 | B59: EDUBAR | C59: CD-57-2021-2989 | D59: Línea Económica_Ciudad Dinámica | E59: Desarrollo_urbano | F59: Plazas de Mercado | G59: MP-2989 - Parqueadero Multiproposito Barlovento | H59: Norte_Centro_Histórico | I59: Barlovento | J59: C 9A 46A 115 | K59: 10°59'11"N 74°46'32"W | L59: -74.775877 | M59: 10.986525 | N59: Postcontractual | O59: Entregado | P59: 2797245954 | Q59: 1 | R59: 1 | S59: =+R59-Q59 -> 0 | T59: {=+_xlfn.IFS($P59<=10000000000,IF(S59>-0.05,"Verde",IF(S59<=-0.1,"Rojo","Amarillo")),$P59>10000000000,IF(S59>-0.03,"Verde",IF(S59<=-0.07,"Rojo","Amarillo")))} -> Verde | U59: 44511 | V59: 44557 | W59: 44643 | X59: 44926 | Y59: 45473 | Z59: =+IF(AND(O59="En_Ejecución",OR(T59="Rojo",T59="Amarillo")),IF(($Y59-(TODAY())<15),"Rojo",IF(($Y59-TODAY())>=45,"Verde","Amarillo")),O59) -> Entregado | AA59: =+IF(AND(Z59="Amarillo",T59="Rojo"),"En_Seguimiento",IF(AND(Z59="Rojo",T59="Amarillo"),"En_Seguimiento",IF(AND(Z59="Rojo",T59="Rojo"),"En_Seguimiento",IF(AND(Z59="Suspendido",T59="Amarillo"),"En_Seguimiento",IF(AND(Z59="Suspendido",T59="Rojo"),"En_Seguimiento","-"))))) -> - | AD59: 45473 | AE59: EDU-868-2021 | AF59: CONSORCIO MERCADOS BARRANQUILLA 2022 | AG59: AE INGENIEROS CIVILES SAS (99%) CABV CONSULTORIA Y CONSTRUCCIONES SAS (1%) | AH59: Antonio Escorcia | AI59: EDU-264-2022 | AJ59: CONSORCIO MP BARRANQUILLA | AK59: ECOVIAS S.A.S (70%) ALPHA GRUPO CONSULTOR E INTERVENTOR S.A.S (30%) | AL59: LUIGGI PUGLIESE MERCADO | AM59: 2797245954 | AN59: 0 | AO59: =AM59+AN59 -> 2797245954 | AP59: 8.0675437e+10 | AQ59: 8.0502233e+10 | AR59: 2506709098 | AS59: 2372520475 | AT59: =AR59+AS59 -> 4879229573 | AU59: 4.5208727e+09 | AV59: 3.2329775e+09 | AW59: 16 refresquerias y 6 restaurantes en los cuales se les mejoro su infraestructura | AX59: mejoramiento de cocinas | AY59: dignificacion de labor de trabajo | BC59: No
A60: =+A59+1 -> 59 | B60: EDUBAR | C60: CD-57-2021-2989 | D60: Línea Económica_Ciudad Dinámica | E60: Desarrollo_urbano | F60: Plazas de Mercado | G60: MP-2989 - Mercado Gran Bazar | H60: Norte_Centro_Histórico | I60: Barranquillita | J60: C 9 41N 52 | K60: 10°58'45"N 74°46'20"W | L60: -74.772587 | M60: 10.978692 | N60: Postcontractual | O60: Entregado | P60: 3.6506105e+10 | Q60: 1 | R60: 1 | S60: =+R60-Q60 -> 0 | T60: {=+_xlfn.IFS($P60<=10000000000,IF(S60>-0.05,"Verde",IF(S60<=-0.1,"Rojo","Amarillo")),$P60>10000000000,IF(S60>-0.03,"Verde",IF(S60<=-0.07,"Rojo","Amarillo")))} -> Verde | U60: 44511 | V60: 44557 | W60: 44627 | X60: 44926 | Y60: 45214 | Z60: =+IF(AND(O60="En_Ejecución",OR(T60="Rojo",T60="Amarillo")),IF(($Y60-(TODAY())<15),"Rojo",IF(($Y60-TODAY())>=45,"Verde","Amarillo")),O60) -> Entregado | AA60: =+IF(AND(Z60="Amarillo",T60="Rojo"),"En_Seguimiento",IF(AND(Z60="Rojo",T60="Amarillo"),"En_Seguimiento",IF(AND(Z60="Rojo",T60="Rojo"),"En_Seguimiento",IF(AND(Z60="Suspendido",T60="Amarillo"),"En_Seguimiento",IF(AND(Z60="Suspendido",T60="Rojo"),"En_Seguimiento","-"))))) -> - | AD60: 45214 | AE60: EDU-846-2021 | AF60: CONSORCIO GRAN BAZAR 2021 | AG60: RYD CONSTRUCTORES S.A.S (40%) PROYECTOS Y GESTION DEL DESARROLLO (40%) CONSTRUCTORA JEMUR (20%) | AH60: Reynaldo Yali Diaz | AI60: EDU-225-2022 | AJ60: CONSORCIO INTERBAZAR | AK60: ANTLIA-AC S.A.S (60%) JANIO PARDO CONSULTORIA Y CONSTRUCCIONES (40%) | AL60: ALCIDEZ JOSE LANDINETH | AM60: 3.6506105e+10 | AN60: 0 | AO60: =AM60+AN60 -> 3.6506105e+10 | AP60: 3.6506105e+10 | AQ60: 3.365632e+10 | AR60: 1549714271 | AS60: 197575700 | AT60: =AR60+AS60 -> 1747289971 | AU60: 1.74729e+09 | AV60: 1.6152499e+09 | AW60: 752 vendedores que ocupaban el espacio publico | AX60: liberacion de areas de espacio publico( vias, andenes) | AY60: dignificacion de labor de trabajo | AZ60: mejoramiento de sanidad en espacio publico | BC60: No
A61: =+A60+1 -> 60 | B61: EDUBAR | C61: CD-57-2021-2989 | D61: Línea Económica_Ciudad Dinámica | E61: Desarrollo_urbano | F61: Plazas de Mercado | G61: MP-2989-Mercado de EPM | H61: Norte_Centro_Histórico | I61: Barranquillita | J61: C 30 44 100 | K61: 10°59'07"N 74°46'22"W | N61: Postcontractual | O61: Entregado | P61: 1080269844 | Q61: 1 | R61: 1 | S61: =+R61-Q61 -> 0 | T61: {=+_xlfn.IFS($P61<=10000000000,IF(S61>-0.05,"Verde",IF(S61<=-0.1,"Rojo","Amarillo")),$P61>10000000000,IF(S61>-0.03,"Verde",IF(S61<=-0.07,"Rojo","Amarillo")))} -> Verde | U61: 44511 | V61: 44557 | W61: 44643 | X61: 44906 | Y61: 45644 | Z61: =+IF(AND(O61="En_Ejecución",OR(T61="Rojo",T61="Amarillo")),IF(($Y61-(TODAY())<15),"Rojo",IF(($Y61-TODAY())>=45,"Verde","Amarillo")),O61) -> Entregado | AA61: =+IF(AND(Z61="Amarillo",T61="Rojo"),"En_Seguimiento",IF(AND(Z61="Rojo",T61="Amarillo"),"En_Seguimiento",IF(AND(Z61="Rojo",T61="Rojo"),"En_Seguimiento",IF(AND(Z61="Suspendido",T61="Amarillo"),"En_Seguimiento",IF(AND(Z61="Suspendido",T61="Rojo"),"En_Seguimiento","-"))))) -> - | AD61: 45611 | AE61: EDU-868-2021 | AF61: CONSORCIO MERCADOS BARRANQUILLA 2022 | AG61: AE INGENIEROS CIVILES SAS (99%) CABV CONSULTORIA Y CONSTRUCCIONES SAS (1%) | AH61: Antonio Escorcia | AI61: EDU-264-2022 | AJ61: CONSORCIO MP BARRANQUILLA | AK61: ECOVIAS S.A.S (70%) ALPHA GRUPO CONSULTOR E INTERVENTOR S.A.S (30%) | AL61: LUIGGI PUGLIESE MERCADO | AM61: 1080269844 | AN61: 0 | AO61: =AM61+AN61 -> 1080269844 | AP61: 8.0675437e+10 | AQ61: 8.0502233e+10 | AR61: 2506709098 | AS61: 2372520475 | AT61: =AR61+AS61 -> 4879229573 | AU61: 4.5208727e+09 | AV61: 3.2329775e+09 | BC61: No
A62: =+A61+1 -> 61 | B62: EDUBAR | C62: CD-57-2021-2989 | D62: Línea Económica_Ciudad Dinámica | E62: Desarrollo_urbano | F62: Plazas de Mercado | G62: MP-2989-Mercado El Playon | H62: Norte_Centro_Histórico | I62: Barranquillita | J62: C 30 41A 44 | K62: 10°58'49"N 74°46'23"W | N62: Contractual | O62: En_Ejecución | P62: 30652617135 | Q62: 0.557 | R62: 0.557 | S62: =+R62-Q62 -> 0 | T62: {=+_xlfn.IFS($P62<=10000000000,IF(S62>-0.05,"Verde",IF(S62<=-0.1,"Rojo","Amarillo")),$P62>10000000000,IF(S62>-0.03,"Verde",IF(S62<=-0.07,"Rojo","Amarillo")))} -> Verde | U62: 44511 | V62: 44557 | W62: 44643 | X62: 44906 | Y62: 45991 | Z62: =+IF(AND(O62="En_Ejecución",OR(T62="Rojo",T62="Amarillo")),IF(($Y62-(TODAY())<15),"Rojo",IF(($Y62-TODAY())>=45,"Verde","Amarillo")),O62) -> En_Ejecución | AA62: =+IF(AND(Z62="Amarillo",T62="Rojo"),"En_Seguimiento",IF(AND(Z62="Rojo",T62="Amarillo"),"En_Seguimiento",IF(AND(Z62="Rojo",T62="Rojo"),"En_Seguimiento",IF(AND(Z62="Suspendido",T62="Amarillo"),"En_Seguimiento",IF(AND(Z62="Suspendido",T62="Rojo"),"En_Seguimiento","-"))))) -> - | AD62: 45991 | AE62: EDU-868-2021 | AF62: CONSORCIO MERCADOS BARRANQUILLA 2022 | AG62: AE INGENIEROS CIVILES SAS (99%) CABV CONSULTORIA Y CONSTRUCCIONES SAS (1%) | AH62: Antonio Escorcia | AI62: EDU-264-2022 | AJ62: CONSORCIO MP BARRANQUILLA | AK62: ECOVIAS S.A.S (70%) ALPHA GRUPO CONSULTOR E INTERVENTOR S.A.S (30%) | AL62: LUIGGI PUGLIESE MERCADO | AM62: 30652617135 | AN62: 0 | AO62: =AM62+AN62 -> 30652617135 | AP62: 8.0675437e+10 | AQ62: 8.0502233e+10 | AR62: 2506709098 | AS62: 2372520475 | AT62: =AR62+AS62 -> 4879229573 | AU62: 4.5208727e+09 | AV62: 3.2329775e+09 | BB62: ETAPA 1 -EJECUCCION AL 100%, ETAPA 2 -100%, ETAPA 3 - 15,72%, AMPLIACION 1 Y 2- 68% AMPLIACION (1 Y 2) - 55% | BC62: No
A63: =+A62+1 -> 62 | B63: EDUBAR | C63: CD-57-2020-2438 | D63: Línea Económica_Ciudad Dinámica | E63: Desarrollo_urbano | F63: Tranformación de Entornos Urbanos | G63: TEU-2438 - Carrera 53 | H63: Norte_Centro_Histórico | I63: Riomar | J63: carrera 53 entre calles 80 a la 87 | K63: 11°00'20"N 74°48'42"W | L63: -74.811667 | M63: 11.005556 | N63: Contractual | O63: Suspendido | P63: 9.2541684e+09 | Q63: 1 | R63: 0.9978 | S63: =+R63-Q63 -> -0.0022 | T63: {=+_xlfn.IFS($P63<=10000000000,IF(S63>-0.05,"Verde",IF(S63<=-0.1,"Rojo","Amarillo")),$P63>10000000000,IF(S63>-0.03,"Verde",IF(S63<=-0.07,"Rojo","Amarillo")))} -> Verde | U63: 44561 | V63: 44651 | W63: 44706 | X63: 44926 | Y63: 45473 | Z63: =+IF(AND(O63="En_Ejecución",OR(T63="Rojo",T63="Amarillo")),IF(($Y63-(TODAY())<15),"Rojo",IF(($Y63-TODAY())>=45,"Verde","Amarillo")),O63) -> Suspendido | AA63: =+IF(AND(Z63="Amarillo",T63="Rojo"),"En_Seguimiento",IF(AND(Z63="Rojo",T63="Amarillo"),"En_Seguimiento",IF(AND(Z63="Rojo",T63="Rojo"),"En_Seguimiento",IF(AND(Z63="Suspendido",T63="Amarillo"),"En_Seguimiento",IF(AND(Z63="Suspendido",T63="Rojo"),"En_Seguimiento","-"))))) -> - | AD63: 45473 | AE63: EDU-272-2022 | AF63: UNION TEMPORAL CONTRUCCION URBANA | AG63: CONSTRUCTOR DE OBRAS E INGENIERIA- COVEIN (70 %) CONSTRUCCION YACAMAN S.A.S -(30%) | AH63: Guillermo Cuello Gieseken | AI63: EDU-273-2022 | AJ63: CONSORCIO INTER TRANSFORMANDO BQ | AK63: HG INGENIERIA Y DESARROLLO S.A.S -(85%) COMPAÑIA DE INTERVENTORIAS Y CONSULTORIAS DE LA COSTA S.A.S (5%). TECNOLOGIAS Y CONSULTORIAS AMBIENTALES Y DE GESTION S.A.S (10%) | AL63: MARIA DEL JESUS CASTAÑEDA | AM63: 9.2541684e+09 | AN63: 0 | AO63: =AM63+AN63 -> 9.2541684e+09 | AP63: 25196782528 | AQ63: 23908722669 | AR63: 1226742000 | AS63: 270858875 | AT63: =AR63+AS63 -> 1497600875 | AU63: 1126553602 | AV63: 995962806 | AW63: Zona Norte de la ciudad de Barranquilla | AX63: mejoramiento de malla vial y espacio publico | AY63: segreracion de vehiculos y peatones | AZ63: regularizacion de zonas de estacionamiento | BC63: Si
A64: =+A63+1 -> 63 | B64: EDUBAR | C64: CD-57-2020-2438 | D64: Línea Económica_Ciudad Dinámica | E64: Desarrollo_urbano | F64: Tranformación de Entornos Urbanos | G64: TEU-2438 - Malecon UF3 | H64: Norte_Centro_Histórico | I64: Centro | J64: Gran Malecon del Rio UF3 | K64: 11°00'55"N 74°47'19"W | L64: -74.788611 | M64: 11.015278 | N64: Postcontractual | O64: Entregado | P64: 13100000000 | Q64: 1 | R64: 1 | S64: =+R64-Q64 -> 0 | T64: {=+_xlfn.IFS($P64<=10000000000,IF(S64>-0.05,"Verde",IF(S64<=-0.1,"Rojo","Amarillo")),$P64>10000000000,IF(S64>-0.03,"Verde",IF(S64<=-0.07,"Rojo","Amarillo")))} -> Verde | U64: 44561 | V64: 44651 | W64: 44706 | X64: 44926 | Y64: 45473 | Z64: =+IF(AND(O64="En_Ejecución",OR(T64="Rojo",T64="Amarillo")),IF(($Y64-(TODAY())<15),"Rojo",IF(($Y64-TODAY())>=45,"Verde","Amarillo")),O64) -> Entregado | AA64: =+IF(AND(Z64="Amarillo",T64="Rojo"),"En_Seguimiento",IF(AND(Z64="Rojo",T64="Amarillo"),"En_Seguimiento",IF(AND(Z64="Rojo",T64="Rojo"),"En_Seguimiento",IF(AND(Z64="Suspendido",T64="Amarillo"),"En_Seguimiento",IF(AND(Z64="Suspendido",T64="Rojo"),"En_Seguimiento","-"))))) -> - | AD64: 45473 | AE64: EDU-272-2022 | AF64: UNION TEMPORAL CONTRUCCION URBANA | AG64: CONSTRUCTOR DE OBRAS E INGENIERIA- COVEIN (70 %) CONSTRUCCION YACAMAN S.A.S -(30%) | AH64: Guillermo Cuello Gieseken | AI64: EDU-273-2022 | AJ64: CONSORCIO INTER TRANSFORMANDO BQ | AK64: HG INGENIERIA Y DESARROLLO S.A.S -(85%) COMPAÑIA DE INTERVENTORIAS Y CONSULTORIAS DE LA COSTA S.A.S (5%). TECNOLOGIAS Y CONSULTORIAS AMBIENTALES Y DE GESTION S.A.S (10%) | AL64: MARIA DEL JESUS CASTAÑEDA | AM64: 13100000000 | AN64: 0 | AO64: =AM64+AN64 -> 13100000000 | AP64: 25196782528 | AQ64: 23908722669 | AR64: 1226742000 | AS64: 270858875 | AT64: =AR64+AS64 -> 1497600875 | AU64: 1126553602 | AV64: 995962806 | AW64: Poblacion total de Barranquilla | AX64: 26000 m2 de espacios construidos para disfrute de la ciudadania | AY64: zonas deportivas | AZ64: zonas de biosaludables y jardines infantiles | BC64: No
A65: =+A64+1 -> 64 | B65: EDUBAR | C65: CD-57-2020-2438 | D65: Línea Económica_Ciudad Dinámica | E65: Desarrollo_urbano | F65: Tranformación de Entornos Urbanos | G65: TEU-2438 - Centro Urbano Comunitario Barlovento | H65: Norte_Centro_Histórico | I65: Barlovento | J65: Carrera 50 con calle 9A | K65: 10°59'15"N 74°46'32"W | L65: -74.776109 | M65: 10.987964 | N65: Postcontractual | O65: Entregado | P65: 5.4369555e+08 | Q65: 1 | R65: 1 | S65: =+R65-Q65 -> 0 | T65: {=+_xlfn.IFS($P65<=10000000000,IF(S65>-0.05,"Verde",IF(S65<=-0.1,"Rojo","Amarillo")),$P65>10000000000,IF(S65>-0.03,"Verde",IF(S65<=-0.07,"Rojo","Amarillo")))} -> Verde | U65: 44561 | V65: 44651 | W65: 44706 | X65: 44926 | Y65: 45473 | Z65: =+IF(AND(O65="En_Ejecución",OR(T65="Rojo",T65="Amarillo")),IF(($Y65-(TODAY())<15),"Rojo",IF(($Y65-TODAY())>=45,"Verde","Amarillo")),O65) -> Entregado | AA65: =+IF(AND(Z65="Amarillo",T65="Rojo"),"En_Seguimiento",IF(AND(Z65="Rojo",T65="Amarillo"),"En_Seguimiento",IF(AND(Z65="Rojo",T65="Rojo"),"En_Seguimiento",IF(AND(Z65="Suspendido",T65="Amarillo"),"En_Seguimiento",IF(AND(Z65="Suspendido",T65="Rojo"),"En_Seguimiento","-"))))) -> - | AD65: 45392 | AE65: EDU-272-2022 | AF65: UNION TEMPORAL CONTRUCCION URBANA | AG65: CONSTRUCTOR DE OBRAS E INGENIERIA- COVEIN (70 %) CONSTRUCCION YACAMAN S.A.S -(30%) | AH65: Guillermo Cuello Gieseken | AI65: EDU-273-2022 | AJ65: CONSORCIO INTER TRANSFORMANDO BQ | AK65: HG INGENIERIA Y DESARROLLO S.A.S -(85%) COMPAÑIA DE INTERVENTORIAS Y CONSULTORIAS DE LA COSTA S.A.S (5%). TECNOLOGIAS Y CONSULTORIAS AMBIENTALES Y DE GESTION S.A.S (10%) | AL65: MARIA DEL JESUS CASTAÑEDA | AM65: 5.4369555e+08 | AN65: 0 | AO65: =AM65+AN65 -> 5.4369555e+08 | AP65: 25196782528 | AQ65: 23908722669 | AR65: 1226742000 | AS65: 270858875 | AT65: =AR65+AS65 -> 1497600875 | AU65: 1126553602 | AV65: 995962806 | AW65: 2,932 poblacion del barrio Barlovento | AX65: entrega de 500 desayunos a la comunidad | AY65: zona de reunion para la comunidad | BC65: No
A66: =+A65+1 -> 65 | B66: EDUBAR | C66: CD-57-2020-2438 | D66: Línea Económica_Ciudad Dinámica | E66: Desarrollo_urbano | F66: Tranformación de Entornos Urbanos | G66: TEU-2438 - Plaza de Pescado | H66: Norte_Centro_Histórico | I66: Centro | J66: Carrea 42 # 7-39 | K66: 10°58'45"N 74°46'16"W | L66: -74.771111 | M66: 10.979167 | N66: Postcontractual | O66: Entregado | P66: 9.3774704e+08 | Q66: 1 | R66: 1 | S66: =+R66-Q66 -> 0 | T66: {=+_xlfn.IFS($P66<=10000000000,IF(S66>-0.05,"Verde",IF(S66<=-0.1,"Rojo","Amarillo")),$P66>10000000000,IF(S66>-0.03,"Verde",IF(S66<=-0.07,"Rojo","Amarillo")))} -> Verde | U66: 44561 | V66: 44651 | W66: 44706 | X66: 44926 | Y66: 45473 | Z66: =+IF(AND(O66="En_Ejecución",OR(T66="Rojo",T66="Amarillo")),IF(($Y66-(TODAY())<15),"Rojo",IF(($Y66-TODAY())>=45,"Verde","Amarillo")),O66) -> Entregado | AA66: =+IF(AND(Z66="Amarillo",T66="Rojo"),"En_Seguimiento",IF(AND(Z66="Rojo",T66="Amarillo"),"En_Seguimiento",IF(AND(Z66="Rojo",T66="Rojo"),"En_Seguimiento",IF(AND(Z66="Suspendido",T66="Amarillo"),"En_Seguimiento",IF(AND(Z66="Suspendido",T66="Rojo"),"En_Seguimiento","-"))))) -> - | AD66: 45473 | AE66: EDU-272-2022 | AF66: UNION TEMPORAL CONTRUCCION URBANA | AG66: CONSTRUCTOR DE OBRAS E INGENIERIA- COVEIN (70 %) CONSTRUCCION YACAMAN S.A.S -(30%) | AH66: Guillermo Cuello Gieseken | AI66: EDU-273-2022 | AJ66: CONSORCIO INTER TRANSFORMANDO BQ | AK66: HG INGENIERIA Y DESARROLLO S.A.S -(85%) COMPAÑIA DE INTERVENTORIAS Y CONSULTORIAS DE LA COSTA S.A.S (5%). TECNOLOGIAS Y CONSULTORIAS AMBIENTALES Y DE GESTION S.A.S (10%) | AL66: MARIA DEL JESUS CASTAÑEDA | AM66: 9.3774704e+08 | AN66: 0 | AO66: =AM66+AN66 -> 9.3774704e+08 | AP66: 25196782528 | AQ66: 23908722669 | AR66: 1226742000 | AS66: 270858875 | AT66: =AR66+AS66 -> 1497600875 | AU66: 1126553602 | AV66: 995962806 | AW66: 467 puestos de trabajo | AX66: mejoramiento en cubierta para la zona de picadores, las cuales alberga 116 puestos de trabajo | AY66: mejoramiento de cubierta en zona de venta, la cual beneficia 351 puestos de trabajo | AZ66: mejoramiento de sanidad del mercado | BC66: Si
A67: =+A66+1 -> 66 | B67: EDUBAR | C67: CD-57-2020-2438 | D67: Línea Económica_Ciudad Dinámica | E67: Desarrollo_urbano | F67: Tranformación de Entornos Urbanos | G67: TEU-2438 - Callejon de Robertico | H67: Norte_Centro_Histórico | I67: Centro | J67: Calle 30 # 42-15 | K67: 10°58'47"N 74°46'32"W | L67: -74.776636 | M67: 10.979342 | N67: Postcontractual | O67: Entregado | P67: 1.6785979e+08 | Q67: 1 | R67: 1 | S67: =+R67-Q67 -> 0 | T67: {=+_xlfn.IFS($P67<=10000000000,IF(S67>-0.05,"Verde",IF(S67<=-0.1,"Rojo","Amarillo")),$P67>10000000000,IF(S67>-0.03,"Verde",IF(S67<=-0.07,"Rojo","Amarillo")))} -> Verde | U67: 44561 | V67: 44651 | W67: 44706 | X67: 44926 | Y67: 45473 | Z67: =+IF(AND(O67="En_Ejecución",OR(T67="Rojo",T67="Amarillo")),IF(($Y67-(TODAY())<15),"Rojo",IF(($Y67-TODAY())>=45,"Verde","Amarillo")),O67) -> Entregado | AA67: =+IF(AND(Z67="Amarillo",T67="Rojo"),"En_Seguimiento",IF(AND(Z67="Rojo",T67="Amarillo"),"En_Seguimiento",IF(AND(Z67="Rojo",T67="Rojo"),"En_Seguimiento",IF(AND(Z67="Suspendido",T67="Amarillo"),"En_Seguimiento",IF(AND(Z67="Suspendido",T67="Rojo"),"En_Seguimiento","-"))))) -> - | AD67: 45473 | AE67: EDU-272-2022 | AF67: UNION TEMPORAL CONTRUCCION URBANA | AG67: CONSTRUCTOR DE OBRAS E INGENIERIA- COVEIN (70 %) CONSTRUCCION YACAMAN S.A.S -(30%) | AH67: Guillermo Cuello Gieseken | AI67: EDU-273-2022 | AJ67: CONSORCIO INTER TRANSFORMANDO BQ | AK67: HG INGENIERIA Y DESARROLLO S.A.S -(85%) COMPAÑIA DE INTERVENTORIAS Y CONSULTORIAS DE LA COSTA S.A.S (5%). TECNOLOGIAS Y CONSULTORIAS AMBIENTALES Y DE GESTION S.A.S (10%) | AL67: MARIA DEL JESUS CASTAÑEDA | AM67: 1.6785979e+08 | AN67: 0 | AO67: =AM67+AN67 -> 1.6785979e+08 | AP67: 25196782528 | AQ67: 23908722669 | AR67: 1226742000 | AS67: 270858875 | AT67: =AR67+AS67 -> 1497600875 | AU67: 1126553602 | AV67: 995962806 | AW67: Centro de Barranquilla | AX67: mejoramiento de espacio publico | BC67: No
A68: =+A67+1 -> 67 | B68: EDUBAR | C68: CD-57-2020-2438 | D68: Línea Económica_Ciudad Dinámica | E68: Desarrollo_urbano | F68: Tranformación de Entornos Urbanos | G68: TEU-2438 - Callejon del Meao | H68: Norte_Centro_Histórico | I68: Centro | J68: cra 42B entre calles 31 y 33 | K68: 10°59'22"N 74°47'22"W | L68: -74.775834 | M68: 10.979962 | N68: Postcontractual | O68: Entregado | P68: 2.92209e+08 | Q68: 1 | R68: 1 | S68: =+R68-Q68 -> 0 | T68: {=+_xlfn.IFS($P68<=10000000000,IF(S68>-0.05,"Verde",IF(S68<=-0.1,"Rojo","Amarillo")),$P68>10000000000,IF(S68>-0.03,"Verde",IF(S68<=-0.07,"Rojo","Amarillo")))} -> Verde | U68: 44561 | V68: 44651 | W68: 44706 | X68: 44926 | Y68: 45473 | Z68: =+IF(AND(O68="En_Ejecución",OR(T68="Rojo",T68="Amarillo")),IF(($Y68-(TODAY())<15),"Rojo",IF(($Y68-TODAY())>=45,"Verde","Amarillo")),O68) -> Entregado | AA68: =+IF(AND(Z68="Amarillo",T68="Rojo"),"En_Seguimiento",IF(AND(Z68="Rojo",T68="Amarillo"),"En_Seguimiento",IF(AND(Z68="Rojo",T68="Rojo"),"En_Seguimiento",IF(AND(Z68="Suspendido",T68="Amarillo"),"En_Seguimiento",IF(AND(Z68="Suspendido",T68="Rojo"),"En_Seguimiento","-"))))) -> - | AD68: 45473 | AE68: EDU-272-2022 | AF68: UNION TEMPORAL CONTRUCCION URBANA | AG68: CONSTRUCTOR DE OBRAS E INGENIERIA- COVEIN (70 %) CONSTRUCCION YACAMAN S.A.S -(30%) | AH68: Guillermo Cuello Gieseken | AI68: EDU-273-2022 | AJ68: CONSORCIO INTER TRANSFORMANDO BQ | AK68: HG INGENIERIA Y DESARROLLO S.A.S -(85%) COMPAÑIA DE INTERVENTORIAS Y CONSULTORIAS DE LA COSTA S.A.S (5%). TECNOLOGIAS Y CONSULTORIAS AMBIENTALES Y DE GESTION S.A.S (10%) | AL68: MARIA DEL JESUS CASTAÑEDA | AM68: 2.92209e+08 | AN68: 0 | AO68: =AM68+AN68 -> 2.92209e+08 | AP68: 25196782528 | AQ68: 23908722669 | AR68: 1226742000 | AS68: 270858875 | AT68: =AR68+AS68 -> 1497600875 | AU68: 1126553602 | AV68: 995962806 | AW68: Centro de Barranquilla | AX68: mejoramiento de espacio publico | BC68: No
A69: =+A68+1 -> 68 | B69: EDUBAR | C69: CD-57-2020-2438 | D69: Línea Económica_Ciudad Dinámica | E69: Desarrollo_urbano | F69: Tranformación de Entornos Urbanos | G69: TEU-2438 - Centro urbano comunitario las Americas | H69: Norte_Centro_Histórico | I69: Las Americas | J69: Cra 3C # 52B- 141 | K69: 10°56'27"N 74°48'40"W | L69: -74.811111 | M69: 10.940833 | N69: Postcontractual | O69: Entregado | P69: 5.3441609e+08 | Q69: 1 | R69: 1 | S69: =+R69-Q69 -> 0 | T69: {=+_xlfn.IFS($P69<=10000000000,IF(S69>-0.05,"Verde",IF(S69<=-0.1,"Rojo","Amarillo")),$P69>10000000000,IF(S69>-0.03,"Verde",IF(S69<=-0.07,"Rojo","Amarillo")))} -> Verde | U69: 44561 | V69: 44651 | W69: 44706 | X69: 44926 | Y69: 45473 | Z69: =+IF(AND(O69="En_Ejecución",OR(T69="Rojo",T69="Amarillo")),IF(($Y69-(TODAY())<15),"Rojo",IF(($Y69-TODAY())>=45,"Verde","Amarillo")),O69) -> Entregado | AA69: =+IF(AND(Z69="Amarillo",T69="Rojo"),"En_Seguimiento",IF(AND(Z69="Rojo",T69="Amarillo"),"En_Seguimiento",IF(AND(Z69="Rojo",T69="Rojo"),"En_Seguimiento",IF(AND(Z69="Suspendido",T69="Amarillo"),"En_Seguimiento",IF(AND(Z69="Suspendido",T69="Rojo"),"En_Seguimiento","-"))))) -> - | AD69: 45358 | AE69: EDU-272-2022 | AF69: UNION TEMPORAL CONTRUCCION URBANA | AG69: CONSTRUCTOR DE OBRAS E INGENIERIA- COVEIN (70 %) CONSTRUCCION YACAMAN S.A.S -(30%) | AH69: Guillermo Cuello Gieseken | AI69: EDU-273-2022 | AJ69: CONSORCIO INTER TRANSFORMANDO BQ | AK69: HG INGENIERIA Y DESARROLLO S.A.S -(85%) COMPAÑIA DE INTERVENTORIAS Y CONSULTORIAS DE LA COSTA S.A.S (5%). TECNOLOGIAS Y CONSULTORIAS AMBIENTALES Y DE GESTION S.A.S (10%) | AL69: MARIA DEL JESUS CASTAÑEDA | AM69: 5.3441609e+08 | AN69: 0 | AO69: =AM69+AN69 -> 5.3441609e+08 | AP69: 25196782528 | AQ69: 23908722669 | AR69: 1226742000 | AS69: 270858875 | AT69: =AR69+AS69 -> 1497600875 | AU69: 1126553602 | AV69: 995962806 | AW69: 8,333 poblacion de barrio Las Americas | AX69: entrega de 500 desayunos a la comunidad | AY69: zona de reunion para la comunidad | BC69: No
A70: =+A69+1 -> 69 | B70: EDUBAR | C70: Contrato Específico No. 2210681 Derivado del Pacto Funcional Atlántico - CONTRATO DE MANDATO N.º 221009 – Suscrito entre EL DNP Y ENTERRITORIO | D70: Línea Económica_Ciudad Dinámica | E70: Agua_potable_y_saneamiento_básico | F70: Agua potable y saneamiento básico | G70: Recuperación Caños - Recuperación Integral Caño de la Ahuyama | H70: Suroriente | I70: Rebolo La Luz Villanueva Zona Franca La Chinita El Ferry | J70: - | K70: 10°58'11"N 74°45'54"W | L70: -74.77058 | M70: 10.96864 | N70: Contractual | O70: En_Ejecución | P70: 99979996094 | Q70: 0.8 | R70: 0.738 | S70: =+R70-Q70 -> -0.062 | T70: {=+_xlfn.IFS($P70<=10000000000,IF(S70>-0.05,"Verde",IF(S70<=-0.1,"Rojo","Amarillo")),$P70>10000000000,IF(S70>-0.03,"Verde",IF(S70<=-0.07,"Rojo","Amarillo")))} -> Amarillo | U70: 44606 | V70: 44627 | W70: 44692 | X70: 45016 | Y70: 45930 | Z70: =+IF(AND(O70="En_Ejecución",OR(T70="Rojo",T70="Amarillo")),IF(($Y70-(TODAY())<15),"Rojo",IF(($Y70-TODAY())>=45,"Verde","Amarillo")),O70) -> Rojo | AA70: =+IF(AND(Z70="Amarillo",T70="Rojo"),"En_Seguimiento",IF(AND(Z70="Rojo",T70="Amarillo"),"En_Seguimiento",IF(AND(Z70="Rojo",T70="Rojo"),"En_Seguimiento",IF(AND(Z70="Suspendido",T70="Amarillo"),"En_Seguimiento",IF(AND(Z70="Suspendido",T70="Rojo"),"En_Seguimiento","-"))))) -> En_Seguimiento | AD70: 45930 | AE70: EDU-270A-2022 | AF70: CONSORCIO DRAGADOS DE COLOMBIA | AG70: Conformación del Consorcio: - SOLUCIONES DE INFRAESTRUCTURA Y LOGÍSTICA S.A.A Nit. 900.745.398-9 50% de participación. - MOVICON CONSTRUCTORES S.A.S Nit. 890.404.359-2 participación:25% - CODIFA S.A.S NIt.802.002.415-1 participación: 25% | AH70: Fabiam Alvarado Paternina | AI70: EDU-277-2022 | AJ70: CONSORCIO INTERCAÑO LA AHUYAMA | AK70: - ROCCIA SAS Nit 900388860-8 participación: 70% - INEXIA SAS Nit 901357944-9 participación: 15% - ARIARI INGENIERIA LIMITADA Nit 822005713-8 participación: 15% | AL70: CARLOS ANDRES MASS GUERRERO | AM70: 93425142894 | AN70: 0 | AO70: =AM70+AN70 -> 93425142894 | AP70: 65554736477 | AQ70: 65554736477 | AR70: 6554853200 | AS70: 0 | AT70: =AR70+AS70 -> 6554853200 | AU70: 4.5274371e+09 | AV70: 4.5274371e+09 | AW70: El proyecto Recuperación Integral del caño de la Ahuyama beneficia directamente a los barrios la chinita, Rebolo y la Luz | AX70: Mitigar y reducir los factores contaminantes de las aguas, | AY70: Mitigar los riesgos de inundación en los barrios (la chinita, Rebolo y la Luz) y zonas que se encuentran ubicados a lo largo de caño y su área de influencia | BA70: Se esta adelantando un proceso de incumplimiento al contratista de la obra | BC70: Si
A71: =+A70+1 -> 70 | B71: EDUBAR | C71: CD-58-2021-4425 | D71: Línea Social_Ciudad Segura y Solidaria | E71: Recreación_y_Deporte | F71: Escenarios deportivos | G71: Escenarios - Pista de Ciclomontañismo | H71: Norte_Centro_Histórico | I71: - | J71: - | K71: 10°59'56.4"N 74°50'03.9"W | L71: -74.83488 | M71: 10.998346 | N71: Postcontractual | O71: Entregado | P71: 3.5618673e+10 | Q71: 1 | R71: 1 | S71: =+R71-Q71 -> 0 | T71: {=+_xlfn.IFS($P71<=10000000000,IF(S71>-0.05,"Verde",IF(S71<=-0.1,"Rojo","Amarillo")),$P71>10000000000,IF(S71>-0.03,"Verde",IF(S71<=-0.07,"Rojo","Amarillo")))} -> Verde | U71: 44573 | V71: 44623 | W71: 44721 | X71: 44926 | Y71: 45616 | Z71: =+IF(AND(O71="En_Ejecución",OR(T71="Rojo",T71="Amarillo")),IF(($Y71-(TODAY())<15),"Rojo",IF(($Y71-TODAY())>=45,"Verde","Amarillo")),O71) -> Entregado | AA71: =+IF(AND(Z71="Amarillo",T71="Rojo"),"En_Seguimiento",IF(AND(Z71="Rojo",T71="Amarillo"),"En_Seguimiento",IF(AND(Z71="Rojo",T71="Rojo"),"En_Seguimiento",IF(AND(Z71="Suspendido",T71="Amarillo"),"En_Seguimiento",IF(AND(Z71="Suspendido",T71="Rojo"),"En_Seguimiento","-"))))) -> - | AD71: 45616 | AE71: EDU-269-2022 | AF71: CONSORCIO SENDEROS 2021 | AG71: DONADO ARCE & CIA S.A.S. (80%) PACANO S.A.S. (20%) | AH71: Roberto Carlo Donado Arce | AI71: NA | AJ71: NA | AK71: NA | AL71: NA | AM71: 3.1980741e+10 | AN71: 3.6379327e+09 | AO71: =AM71+AN71 -> 3.5618673e+10 | AP71: 2.8779232e+10 | AQ71: 2.8779232e+10 | AR71: 0 | AS71: 0 | AT71: =AR71+AS71 -> 0 | AU71: 0 | AV71: 0 | BA71: Instalaciones electricas, Estuco, revestimiento fachada, cerramiento, mobiliario y cerramineto | BB71: RECLAMACIÓN POR MAYOR VALOR EN PRECIOS DE INSUMOS ($909.534.408,80)​ SE REQUIERE REVISAR ESTABILIDAD DEL TALUD CARRERA 43​ SE RETIRO DEL ALCANCE REDES DE TELECOMUNICACIONES, VOZ Y DATOS | BC71: Si
A72: =+A71+1 -> 71 | B72: EDUBAR | C72: CD-05-2022-3691 | D72: Línea Social_Ciudad Segura y Solidaria | E72: Educación | F72: Colegios | G72: InfraEducativa-3691 - IE Reuven [Construcción] | H72: Metropolitana | I72: Ciudadela 20 de Julio | J72: Cra 1B # 46G - 18 | K72: 10°55'52"N 74°48'16"W | L72: -74.804487 | M72: 10.931654 | N72: Contractual | O72: En_Ejecución | P72: 1374984440 | Q72: 1 | R72: 1 | S72: =+R72-Q72 -> 0 | T72: {=+_xlfn.IFS($P72<=10000000000,IF(S72>-0.05,"Verde",IF(S72<=-0.1,"Rojo","Amarillo")),$P72>10000000000,IF(S72>-0.03,"Verde",IF(S72<=-0.07,"Rojo","Amarillo")))} -> Verde | U72: 44831 | V72: 44862 | W72: 44901 | X72: 44926 | Y72: 45930 | Z72: =+IF(AND(O72="En_Ejecución",OR(T72="Rojo",T72="Amarillo")),IF(($Y72-(TODAY())<15),"Rojo",IF(($Y72-TODAY())>=45,"Verde","Amarillo")),O72) -> En_Ejecución | AA72: =+IF(AND(Z72="Amarillo",T72="Rojo"),"En_Seguimiento",IF(AND(Z72="Rojo",T72="Amarillo"),"En_Seguimiento",IF(AND(Z72="Rojo",T72="Rojo"),"En_Seguimiento",IF(AND(Z72="Suspendido",T72="Amarillo"),"En_Seguimiento",IF(AND(Z72="Suspendido",T72="Rojo"),"En_Seguimiento","-"))))) -> - | AD72: 45601 | AE72: EDU-345-2022 | AF72: CONSORCIO EDUCATIVO DISTRITAL | AG72: TURPIAL INGENIERIA S.A.S (65%) BF CONSTRUYE S.A.S (30%) IDC 21 S.A.S (5%) | AH72: Cristian David Jimenez Yejas | AI72: SA-EDU-0001-2022 | AJ72: CONSORCIO IE DISTRITO | AK72: CAYENA CONSULTORES E INTERVENTORES S.A.S (40%) HG INGENIERIA Y DESARROLLO S.A.S.(30%) HM INGENIERIA S.A.S (30%) | AL72: MARCELA PATRICIA BAQUERO APONTE | AM72: 1374984440 | AN72: 0 | AO72: =AM72+AN72 -> 1374984440 | AP72: 2.7569081e+10 | AQ72: 2.6728811e+10 | AR72: 79841522 | AT72: =AR72+AS72 -> 79841522 | AU72: 1.5520677e+09 | AV72: 1.5520677e+09 | AX72: Diseños ejecutados y aprobados por mes | AY72: Frentes iniciados por mes | AZ72: Frentes entregados por mes | BA72: FRENTE ENTREGADO | BC72: Si
A73: =+A72+1 -> 72 | B73: EDUBAR | C73: CD-05-2022-3691 | D73: Línea Social_Ciudad Segura y Solidaria | E73: Educación | F73: Colegios | G73: InfraEducativa-3691 - IE Jose Eusebio Caro [Construcción] | H73: Suroccidente | I73: Chiquinquirá | J73: Cra 33 # 45 - 125 | K73: 10°58'30"N 74°47'20"W | L73: -74.789017 | M73: 10.974971 | N73: Contractual | O73: En_Ejecución | P73: 2111537064 | Q73: 1 | R73: 1 | S73: =+R73-Q73 -> 0 | T73: {=+_xlfn.IFS($P73<=10000000000,IF(S73>-0.05,"Verde",IF(S73<=-0.1,"Rojo","Amarillo")),$P73>10000000000,IF(S73>-0.03,"Verde",IF(S73<=-0.07,"Rojo","Amarillo")))} -> Verde | U73: 44831 | V73: 44862 | W73: 44901 | X73: 44926 | Y73: 45930 | Z73: =+IF(AND(O73="En_Ejecución",OR(T73="Rojo",T73="Amarillo")),IF(($Y73-(TODAY())<15),"Rojo",IF(($Y73-TODAY())>=45,"Verde","Amarillo")),O73) -> En_Ejecución | AA73: =+IF(AND(Z73="Amarillo",T73="Rojo"),"En_Seguimiento",IF(AND(Z73="Rojo",T73="Amarillo"),"En_Seguimiento",IF(AND(Z73="Rojo",T73="Rojo"),"En_Seguimiento",IF(AND(Z73="Suspendido",T73="Amarillo"),"En_Seguimiento",IF(AND(Z73="Suspendido",T73="Rojo"),"En_Seguimiento","-"))))) -> - | AD73: 45684 | AE73: EDU-345-2022 | AF73: CONSORCIO EDUCATIVO DISTRITAL | AG73: TURPIAL INGENIERIA S.A.S (65%) BF CONSTRUYE S.A.S (30%) IDC 21 S.A.S (5%) | AH73: Cristian David Jimenez Yejas | AI73: SA-EDU-0001-2022 | AJ73: CONSORCIO IE DISTRITO | AK73: CAYENA CONSULTORES E INTERVENTORES S.A.S (40%) HG INGENIERIA Y DESARROLLO S.A.S.(30%) HM INGENIERIA S.A.S (30%) | AL73: MARCELA PATRICIA BAQUERO APONTE | AM73: 2111537064 | AN73: 0 | AO73: =AM73+AN73 -> 2111537064 | AP73: 2.7569081e+10 | AQ73: 2.6728811e+10 | AR73: 122611083 | AT73: =AR73+AS73 -> 122611083 | AU73: 1.5520677e+09 | AV73: 1.5520677e+09 | AW73: 1200 Estudiantes | AX73: Diseños ejecutados y aprobados por mes | AY73: Frentes iniciados por mes | AZ73: Frentes entregados por mes | BA73: FRENTE ENTREGADO | BC73: Si
A74: =+A73+1 -> 73 | B74: EDUBAR | C74: CD-05-2022-3691 | D74: Línea Social_Ciudad Segura y Solidaria | E74: Educación | F74: Colegios | G74: InfraEducativa-3691 - IE Juan Jose Rondon [Construcción] | H74: Suroccidente | I74: San Felipe | J74: Cra 25B # 68 - 20 | K74: 10°58'27"N 74°48'29"W | L74: -74.808127 | M74: 10.974588 | N74: Contractual | O74: En_Ejecución | P74: 3.9924321e+08 | Q74: 1 | R74: 1 | S74: =+R74-Q74 -> 0 | T74: {=+_xlfn.IFS($P74<=10000000000,IF(S74>-0.05,"Verde",IF(S74<=-0.1,"Rojo","Amarillo")),$P74>10000000000,IF(S74>-0.03,"Verde",IF(S74<=-0.07,"Rojo","Amarillo")))} -> Verde | U74: 44831 | V74: 44862 | W74: 44901 | X74: 44926 | Y74: 45930 | Z74: =+IF(AND(O74="En_Ejecución",OR(T74="Rojo",T74="Amarillo")),IF(($Y74-(TODAY())<15),"Rojo",IF(($Y74-TODAY())>=45,"Verde","Amarillo")),O74) -> En_Ejecución | AA74: =+IF(AND(Z74="Amarillo",T74="Rojo"),"En_Seguimiento",IF(AND(Z74="Rojo",T74="Amarillo"),"En_Seguimiento",IF(AND(Z74="Rojo",T74="Rojo"),"En_Seguimiento",IF(AND(Z74="Suspendido",T74="Amarillo"),"En_Seguimiento",IF(AND(Z74="Suspendido",T74="Rojo"),"En_Seguimiento","-"))))) -> - | AD74: 45495 | AE74: EDU-345-2022 | AF74: CONSORCIO EDUCATIVO DISTRITAL | AG74: TURPIAL INGENIERIA S.A.S (65%) BF CONSTRUYE S.A.S (30%) IDC 21 S.A.S (5%) | AH74: Cristian David Jimenez Yejas | AI74: SA-EDU-0001-2022 | AJ74: CONSORCIO IE DISTRITO | AK74: CAYENA CONSULTORES E INTERVENTORES S.A.S (40%) HG INGENIERIA Y DESARROLLO S.A.S.(30%) HM INGENIERIA S.A.S (30%) | AL74: MARCELA PATRICIA BAQUERO APONTE | AM74: 4.0501561e+08 | AN74: 0 | AO74: =AM74+AN74 -> 4.0501561e+08 | AP74: 2.7569081e+10 | AQ74: 2.6728811e+10 | AR74: 23518130 | AT74: =AR74+AS74 -> 23518130 | AU74: 1.5520677e+09 | AV74: 1.5520677e+09 | AW74: 693 Estudiantes | AX74: Diseños ejecutados y aprobados por mes | AY74: Frentes iniciados por mes | AZ74: Frentes entregados por mes | BA74: FRENTE ENTREGADO | BC74: Si
A75: =+A74+1 -> 74 | B75: EDUBAR | C75: CD-05-2022-3691 | D75: Línea Social_Ciudad Segura y Solidaria | E75: Educación | F75: Colegios | G75: InfraEducativa-3691 - IE Carrizal [Construcción] | H75: Metropolitana | I75: Carrizal | J75: Calle 50D 3 31A - 37 | K75: 10°57'47"N 74°48'05"W | L75: -74.808606 | M75: 10.937517 | N75: Contractual | O75: En_Ejecución | P75: 6.8433819e+09 | Q75: 1 | R75: 0.9407 | S75: =+R75-Q75 -> -0.0593 | T75: {=+_xlfn.IFS($P75<=10000000000,IF(S75>-0.05,"Verde",IF(S75<=-0.1,"Rojo","Amarillo")),$P75>10000000000,IF(S75>-0.03,"Verde",IF(S75<=-0.07,"Rojo","Amarillo")))} -> Amarillo | U75: 44831 | V75: 44862 | W75: 44901 | X75: 44926 | Y75: 45930 | Z75: =+IF(AND(O75="En_Ejecución",OR(T75="Rojo",T75="Amarillo")),IF(($Y75-(TODAY())<15),"Rojo",IF(($Y75-TODAY())>=45,"Verde","Amarillo")),O75) -> Rojo | AA75: =+IF(AND(Z75="Amarillo",T75="Rojo"),"En_Seguimiento",IF(AND(Z75="Rojo",T75="Amarillo"),"En_Seguimiento",IF(AND(Z75="Rojo",T75="Rojo"),"En_Seguimiento",IF(AND(Z75="Suspendido",T75="Amarillo"),"En_Seguimiento",IF(AND(Z75="Suspendido",T75="Rojo"),"En_Seguimiento","-"))))) -> En_Seguimiento | AD75: 45899 | AE75: EDU-345-2022 | AF75: CONSORCIO EDUCATIVO DISTRITAL | AG75: TURPIAL INGENIERIA S.A.S (65%) BF CONSTRUYE S.A.S (30%) IDC 21 S.A.S (5%) | AH75: Cristian David Jimenez Yejas | AI75: SA-EDU-0001-2022 | AJ75: CONSORCIO IE DISTRITO | AK75: CAYENA CONSULTORES E INTERVENTORES S.A.S (40%) HG INGENIERIA Y DESARROLLO S.A.S.(30%) HM INGENIERIA S.A.S (30%) | AL75: MARCELA PATRICIA BAQUERO APONTE | AM75: 6245181088 | AN75: 0 | AO75: =AM75+AN75 -> 6245181088 | AP75: 2.7569081e+10 | AQ75: 2.6728811e+10 | AR75: 362640293 | AT75: =AR75+AS75 -> 362640293 | AU75: 1.5520677e+09 | AV75: 1.5520677e+09 | AW75: 570 Estudiantes | AX75: Diseños ejecutados y aprobados por mes | AY75: Frentes iniciados por mes | AZ75: Frentes entregados por mes | BA75: Instalación de piso, levante de muro, excavación para cuneta, reparaciones en fachada | BC75: Si
A76: =+A75+1 -> 75 | B76: EDUBAR | C76: CD-05-2022-3691 | D76: Línea Social_Ciudad Segura y Solidaria | E76: Educación | F76: Colegios | G76: InfraEducativa-3691 - IE Mayor de Barranquilla [Construcción] | H76: Norte_Centro_Histórico | I76: Centro | J76: Calle 47 # 44 - 97 | K76: 10°59'08"N 74°47'12"W | L76: -74.786994 | M76: 10.985841 | N76: Contractual | O76: En_Ejecución | P76: 3559766405 | Q76: 1 | R76: 0.99 | S76: =+R76-Q76 -> -0.01 | T76: {=+_xlfn.IFS($P76<=10000000000,IF(S76>-0.05,"Verde",IF(S76<=-0.1,"Rojo","Amarillo")),$P76>10000000000,IF(S76>-0.03,"Verde",IF(S76<=-0.07,"Rojo","Amarillo")))} -> Verde | U76: 44831 | V76: 44862 | W76: 44901 | X76: 44926 | Y76: 45930 | Z76: =+IF(AND(O76="En_Ejecución",OR(T76="Rojo",T76="Amarillo")),IF(($Y76-(TODAY())<15),"Rojo",IF(($Y76-TODAY())>=45,"Verde","Amarillo")),O76) -> En_Ejecución | AA76: =+IF(AND(Z76="Amarillo",T76="Rojo"),"En_Seguimiento",IF(AND(Z76="Rojo",T76="Amarillo"),"En_Seguimiento",IF(AND(Z76="Rojo",T76="Rojo"),"En_Seguimiento",IF(AND(Z76="Suspendido",T76="Amarillo"),"En_Seguimiento",IF(AND(Z76="Suspendido",T76="Rojo"),"En_Seguimiento","-"))))) -> - | AD76: 45853 | AE76: EDU-345-2022 | AF76: CONSORCIO EDUCATIVO DISTRITAL | AG76: TURPIAL INGENIERIA S.A.S (65%) BF CONSTRUYE S.A.S (30%) IDC 21 S.A.S (5%) | AH76: Cristian David Jimenez Yejas | AI76: SA-EDU-0001-2022 | AJ76: CONSORCIO IE DISTRITO | AK76: CAYENA CONSULTORES E INTERVENTORES S.A.S (40%) HG INGENIERIA Y DESARROLLO S.A.S.(30%) HM INGENIERIA S.A.S (30%) | AL76: MARCELA PATRICIA BAQUERO APONTE | AM76: 3559766405 | AN76: 0 | AO76: =AM76+AN76 -> 3559766405 | AP76: 2.7569081e+10 | AQ76: 2.6728811e+10 | AR76: 206705733 | AT76: =AR76+AS76 -> 206705733 | AU76: 1.5520677e+09 | AV76: 1.5520677e+09 | AW76: 894 Estudiantes | AX76: Diseños ejecutados y aprobados por mes | AY76: Frentes iniciados por mes | AZ76: Frentes entregados por mes | BA76: Frente entregado con detalles | BC76: Si
A77: =+A76+1 -> 76 | B77: EDUBAR | C77: CD-05-2022-3691 | D77: Línea Social_Ciudad Segura y Solidaria | E77: Educación | F77: Colegios | G77: InfraEducativa-3691 - IE Jorge Nicolas Abello sede 2 [Cocina] | H77: Suroccidente | I77: San Felipe | J77: Calle 64 # 25 - Esq | K77: 10°58'26"N 74°48'19"W | L77: -74.805362 | M77: 10.97291 | N77: Contractual | O77: En_Ejecución | P77: 138325539 | Q77: 1 | R77: 1 | S77: =+R77-Q77 -> 0 | T77: {=+_xlfn.IFS($P77<=10000000000,IF(S77>-0.05,"Verde",IF(S77<=-0.1,"Rojo","Amarillo")),$P77>10000000000,IF(S77>-0.03,"Verde",IF(S77<=-0.07,"Rojo","Amarillo")))} -> Verde | U77: 44831 | V77: 44862 | W77: 44901 | X77: 44926 | Y77: 45930 | Z77: =+IF(AND(O77="En_Ejecución",OR(T77="Rojo",T77="Amarillo")),IF(($Y77-(TODAY())<15),"Rojo",IF(($Y77-TODAY())>=45,"Verde","Amarillo")),O77) -> En_Ejecución | AA77: =+IF(AND(Z77="Amarillo",T77="Rojo"),"En_Seguimiento",IF(AND(Z77="Rojo",T77="Amarillo"),"En_Seguimiento",IF(AND(Z77="Rojo",T77="Rojo"),"En_Seguimiento",IF(AND(Z77="Suspendido",T77="Amarillo"),"En_Seguimiento",IF(AND(Z77="Suspendido",T77="Rojo"),"En_Seguimiento","-"))))) -> - | AD77: 45499 | AE77: EDU-345-2022 | AF77: CONSORCIO EDUCATIVO DISTRITAL | AG77: TURPIAL INGENIERIA S.A.S (65%) BF CONSTRUYE S.A.S (30%) IDC 21 S.A.S (5%) | AH77: Cristian David Jimenez Yejas | AI77: SA-EDU-0001-2022 | AJ77: CONSORCIO IE DISTRITO | AK77: CAYENA CONSULTORES E INTERVENTORES S.A.S (40%) HG INGENIERIA Y DESARROLLO S.A.S.(30%) HM INGENIERIA S.A.S (30%) | AL77: MARCELA PATRICIA BAQUERO APONTE | AM77: 138325539 | AN77: 0 | AO77: =AM77+AN77 -> 138325539 | AP77: 2.7569081e+10 | AQ77: 2.6728811e+10 | AR77: 8032179 | AT77: =AR77+AS77 -> 8032179 | AU77: 1.5520677e+09 | AV77: 1.5520677e+09 | AW77: 447 Estudiantes | AX77: Diseños ejecutados y aprobados por mes | AY77: Frentes iniciados por mes | AZ77: Frentes entregados por mes | BA77: FRENTE ENTREGADO | BC77: No
A78: =+A77+1 -> 77 | B78: EDUBAR | C78: CD-05-2022-3691 | D78: Línea Social_Ciudad Segura y Solidaria | E78: Educación | F78: Colegios | G78: InfraEducativa-3691 - Ideth Sede 2 [Cocina] | H78: Suroccidente | I78: Nueva Granada | J78: Cra 28 # 63b - 87 | K78: 10°58'34"N 74°48'17"W | L78: -74.804781 | M78: 10.976457 | N78: Contractual | O78: En_Ejecución | P78: 301355388 | Q78: 1 | R78: 1 | S78: =+R78-Q78 -> 0 | T78: {=+_xlfn.IFS($P78<=10000000000,IF(S78>-0.05,"Verde",IF(S78<=-0.1,"Rojo","Amarillo")),$P78>10000000000,IF(S78>-0.03,"Verde",IF(S78<=-0.07,"Rojo","Amarillo")))} -> Verde | U78: 44831 | V78: 44862 | W78: 44901 | X78: 44926 | Y78: 45930 | Z78: =+IF(AND(O78="En_Ejecución",OR(T78="Rojo",T78="Amarillo")),IF(($Y78-(TODAY())<15),"Rojo",IF(($Y78-TODAY())>=45,"Verde","Amarillo")),O78) -> En_Ejecución | AA78: =+IF(AND(Z78="Amarillo",T78="Rojo"),"En_Seguimiento",IF(AND(Z78="Rojo",T78="Amarillo"),"En_Seguimiento",IF(AND(Z78="Rojo",T78="Rojo"),"En_Seguimiento",IF(AND(Z78="Suspendido",T78="Amarillo"),"En_Seguimiento",IF(AND(Z78="Suspendido",T78="Rojo"),"En_Seguimiento","-"))))) -> - | AD78: 45594 | AE78: EDU-345-2022 | AF78: CONSORCIO EDUCATIVO DISTRITAL | AG78: TURPIAL INGENIERIA S.A.S (65%) BF CONSTRUYE S.A.S (30%) IDC 21 S.A.S (5%) | AH78: Cristian David Jimenez Yejas | AI78: SA-EDU-0001-2022 | AJ78: CONSORCIO IE DISTRITO | AK78: CAYENA CONSULTORES E INTERVENTORES S.A.S (40%) HG INGENIERIA Y DESARROLLO S.A.S.(30%) HM INGENIERIA S.A.S (30%) | AL78: MARCELA PATRICIA BAQUERO APONTE | AM78: 301355388 | AN78: 0 | AO78: =AM78+AN78 -> 301355388 | AP78: 2.7569081e+10 | AQ78: 2.6728811e+10 | AR78: 17498869 | AT78: =AR78+AS78 -> 17498869 | AU78: 1.5520677e+09 | AV78: 1.5520677e+09 | AW78: 652 Estudiantes | AX78: Diseños ejecutados y aprobados por mes | AY78: Frentes iniciados por mes | AZ78: Frentes entregados por mes | BA78: FRENTE ENTREGADO | BC78: No
A79: =+A78+1 -> 78 | B79: EDUBAR | C79: CD-05-2022-3691 | D79: Línea Social_Ciudad Segura y Solidaria | E79: Educación | F79: Colegios | G79: InfraEducativa-3691 - IE Insteco Sede 2 [Cocina] | H79: Norte_Centro_Histórico | I79: Centro | J79: Cl 39 # 38 -63 | K79: 10°58'42"N 74°46'57"W | L79: -74.782329 | M79: 10.978455 | N79: Contractual | O79: En_Ejecución | P79: 245789393 | Q79: 1 | R79: 1 | S79: =+R79-Q79 -> 0 | T79: {=+_xlfn.IFS($P79<=10000000000,IF(S79>-0.05,"Verde",IF(S79<=-0.1,"Rojo","Amarillo")),$P79>10000000000,IF(S79>-0.03,"Verde",IF(S79<=-0.07,"Rojo","Amarillo")))} -> Verde | U79: 44831 | V79: 44862 | W79: 44901 | X79: 44926 | Y79: 45930 | Z79: =+IF(AND(O79="En_Ejecución",OR(T79="Rojo",T79="Amarillo")),IF(($Y79-(TODAY())<15),"Rojo",IF(($Y79-TODAY())>=45,"Verde","Amarillo")),O79) -> En_Ejecución | AA79: =+IF(AND(Z79="Amarillo",T79="Rojo"),"En_Seguimiento",IF(AND(Z79="Rojo",T79="Amarillo"),"En_Seguimiento",IF(AND(Z79="Rojo",T79="Rojo"),"En_Seguimiento",IF(AND(Z79="Suspendido",T79="Amarillo"),"En_Seguimiento",IF(AND(Z79="Suspendido",T79="Rojo"),"En_Seguimiento","-"))))) -> - | AD79: 45674 | AE79: EDU-345-2022 | AF79: CONSORCIO EDUCATIVO DISTRITAL | AG79: TURPIAL INGENIERIA S.A.S (65%) BF CONSTRUYE S.A.S (30%) IDC 21 S.A.S (5%) | AH79: Cristian David Jimenez Yejas | AI79: SA-EDU-0001-2022 | AJ79: CONSORCIO IE DISTRITO | AK79: CAYENA CONSULTORES E INTERVENTORES S.A.S (40%) HG INGENIERIA Y DESARROLLO S.A.S.(30%) HM INGENIERIA S.A.S (30%) | AL79: MARCELA PATRICIA BAQUERO APONTE | AM79: 245789393 | AN79: 0 | AO79: =AM79+AN79 -> 245789393 | AP79: 2.7569081e+10 | AQ79: 2.6728811e+10 | AR79: 14272306 | AT79: =AR79+AS79 -> 14272306 | AU79: 1.5520677e+09 | AV79: 1.5520677e+09 | AW79: 1120 Estudiantes | AX79: Diseños ejecutados y aprobados por mes | AY79: Frentes iniciados por mes | AZ79: Frentes entregados por mes | BA79: FRENTE ENTREGADO | BC79: No
A80: =+A79+1 -> 79 | B80: EDUBAR | C80: CD-05-2022-3691 | D80: Línea Social_Ciudad Segura y Solidaria | E80: Educación | F80: Colegios | G80: InfraEducativa-3691 - IE La Libertad [Cocina] | H80: Suroccidente | I80: La libertad | J80: Cra 26A # 74B - 139 | K80: 10°58'37"N 74°48'59"W | L80: -74.816548 | M80: 10.977098 | N80: Contractual | O80: En_Ejecución | P80: 2.7773008e+08 | Q80: 1 | R80: 1 | S80: =+R80-Q80 -> 0 | T80: {=+_xlfn.IFS($P80<=10000000000,IF(S80>-0.05,"Verde",IF(S80<=-0.1,"Rojo","Amarillo")),$P80>10000000000,IF(S80>-0.03,"Verde",IF(S80<=-0.07,"Rojo","Amarillo")))} -> Verde | U80: 44831 | V80: 44862 | W80: 44901 | X80: 44926 | Y80: 45930 | Z80: =+IF(AND(O80="En_Ejecución",OR(T80="Rojo",T80="Amarillo")),IF(($Y80-(TODAY())<15),"Rojo",IF(($Y80-TODAY())>=45,"Verde","Amarillo")),O80) -> En_Ejecución | AA80: =+IF(AND(Z80="Amarillo",T80="Rojo"),"En_Seguimiento",IF(AND(Z80="Rojo",T80="Amarillo"),"En_Seguimiento",IF(AND(Z80="Rojo",T80="Rojo"),"En_Seguimiento",IF(AND(Z80="Suspendido",T80="Amarillo"),"En_Seguimiento",IF(AND(Z80="Suspendido",T80="Rojo"),"En_Seguimiento","-"))))) -> - | AD80: 45772 | AE80: EDU-345-2022 | AF80: CONSORCIO EDUCATIVO DISTRITAL | AG80: TURPIAL INGENIERIA S.A.S (65%) BF CONSTRUYE S.A.S (30%) IDC 21 S.A.S (5%) | AH80: Cristian David Jimenez Yejas | AI80: SA-EDU-0001-2022 | AJ80: CONSORCIO IE DISTRITO | AK80: CAYENA CONSULTORES E INTERVENTORES S.A.S (40%) HG INGENIERIA Y DESARROLLO S.A.S.(30%) HM INGENIERIA S.A.S (30%) | AL80: MARCELA PATRICIA BAQUERO APONTE | AM80: 2.7773008e+08 | AN80: 0 | AO80: =AM80+AN80 -> 2.7773008e+08 | AP80: 2.7569081e+10 | AQ80: 2.6728811e+10 | AR80: 16127013 | AT80: =AR80+AS80 -> 16127013 | AU80: 1.5520677e+09 | AV80: 1.5520677e+09 | AW80: 1600 Estudiantes | AX80: Diseños ejecutados y aprobados por mes | AY80: Frentes iniciados por mes | AZ80: Frentes entregados por mes | BA80: FRENTE ENTREGADO | BC80: No
A81: =+A80+1 -> 80 | B81: EDUBAR | C81: CD-05-2022-3691 | D81: Línea Social_Ciudad Segura y Solidaria | E81: Educación | F81: Colegios | G81: InfraEducativa-3691 - IE Insteco Sede 1 [Cocina] | H81: Norte_Centro_Histórico | I81: Centro | J81: Cl 47 # 42 - 60 | K81: 10°58'59"N 74°47'14"W | L81: -74.787226 | M81: 10.983092 | N81: Contractual | O81: En_Ejecución | P81: 153482039 | Q81: 1 | R81: 0.33 | S81: =+R81-Q81 -> -0.67 | T81: {=+_xlfn.IFS($P81<=10000000000,IF(S81>-0.05,"Verde",IF(S81<=-0.1,"Rojo","Amarillo")),$P81>10000000000,IF(S81>-0.03,"Verde",IF(S81<=-0.07,"Rojo","Amarillo")))} -> Rojo | U81: 44831 | V81: 44862 | W81: 44901 | X81: 44926 | Y81: 45930 | Z81: =+IF(AND(O81="En_Ejecución",OR(T81="Rojo",T81="Amarillo")),IF(($Y81-(TODAY())<15),"Rojo",IF(($Y81-TODAY())>=45,"Verde","Amarillo")),O81) -> Rojo | AA81: =+IF(AND(Z81="Amarillo",T81="Rojo"),"En_Seguimiento",IF(AND(Z81="Rojo",T81="Amarillo"),"En_Seguimiento",IF(AND(Z81="Rojo",T81="Rojo"),"En_Seguimiento",IF(AND(Z81="Suspendido",T81="Amarillo"),"En_Seguimiento",IF(AND(Z81="Suspendido",T81="Rojo"),"En_Seguimiento","-"))))) -> En_Seguimiento | AD81: 45884 | AE81: EDU-345-2022 | AF81: CONSORCIO EDUCATIVO DISTRITAL | AG81: TURPIAL INGENIERIA S.A.S (65%) BF CONSTRUYE S.A.S (30%) IDC 21 S.A.S (5%) | AH81: Cristian David Jimenez Yejas | AI81: SA-EDU-0001-2022 | AJ81: CONSORCIO IE DISTRITO | AK81: CAYENA CONSULTORES E INTERVENTORES S.A.S (40%) HG INGENIERIA Y DESARROLLO S.A.S.(30%) HM INGENIERIA S.A.S (30%) | AL81: MARCELA PATRICIA BAQUERO APONTE | AM81: 153482039 | AN81: 0 | AO81: =AM81+AN81 -> 153482039 | AP81: 2.7569081e+10 | AQ81: 2.6728811e+10 | AR81: 8912275 | AT81: =AR81+AS81 -> 8912275 | AU81: 1.5520677e+09 | AV81: 1.5520677e+09 | AW81: 458 Estudiantes | AX81: Diseños ejecutados y aprobados por mes | AY81: Frentes iniciados por mes | AZ81: Frentes entregados por mes | BA81: Sin actividades | BC81: No
A82: =+A81+1 -> 81 | B82: EDUBAR | C82: CD-05-2022-3691 | D82: Línea Social_Ciudad Segura y Solidaria | E82: Educación | F82: Colegios | G82: InfraEducativa-3691 - IE Sonia Ahumada [Cocina] | H82: Suroccidente | I82: Siete de Agosto | J82: Cra 12A #94 - 75 | K82: 10°57'45"N 74°49'45"W | L82: -74.829292 | M82: 10.96283 | N82: Contractual | O82: En_Ejecución | P82: 151020467 | Q82: 1 | R82: 1 | S82: =+R82-Q82 -> 0 | T82: {=+_xlfn.IFS($P82<=10000000000,IF(S82>-0.05,"Verde",IF(S82<=-0.1,"Rojo","Amarillo")),$P82>10000000000,IF(S82>-0.03,"Verde",IF(S82<=-0.07,"Rojo","Amarillo")))} -> Verde | U82: 44831 | V82: 44862 | W82: 44901 | X82: 44926 | Y82: 45930 | Z82: =+IF(AND(O82="En_Ejecución",OR(T82="Rojo",T82="Amarillo")),IF(($Y82-(TODAY())<15),"Rojo",IF(($Y82-TODAY())>=45,"Verde","Amarillo")),O82) -> En_Ejecución | AA82: =+IF(AND(Z82="Amarillo",T82="Rojo"),"En_Seguimiento",IF(AND(Z82="Rojo",T82="Amarillo"),"En_Seguimiento",IF(AND(Z82="Rojo",T82="Rojo"),"En_Seguimiento",IF(AND(Z82="Suspendido",T82="Amarillo"),"En_Seguimiento",IF(AND(Z82="Suspendido",T82="Rojo"),"En_Seguimiento","-"))))) -> - | AD82: 45594 | AE82: EDU-345-2022 | AF82: CONSORCIO EDUCATIVO DISTRITAL | AG82: TURPIAL INGENIERIA S.A.S (65%) BF CONSTRUYE S.A.S (30%) IDC 21 S.A.S (5%) | AH82: Cristian David Jimenez Yejas | AI82: SA-EDU-0001-2022 | AJ82: CONSORCIO IE DISTRITO | AK82: CAYENA CONSULTORES E INTERVENTORES S.A.S (40%) HG INGENIERIA Y DESARROLLO S.A.S.(30%) HM INGENIERIA S.A.S (30%) | AM82: 151020467 | AN82: 0 | AO82: =AM82+AN82 -> 151020467 | AP82: 2.7569081e+10 | AQ82: 2.6728811e+10 | AR82: 8769338 | AT82: =AR82+AS82 -> 8769338 | AU82: 1.5520677e+09 | AV82: 1.5520677e+09 | AW82: 1187 Estudiantes | AX82: Diseños ejecutados y aprobados por mes | AY82: Frentes iniciados por mes | AZ82: Frentes entregados por mes | BA82: FRENTE ENTREGADO | BC82: No
A83: =+A82+1 -> 82 | B83: EDUBAR | C83: CD-05-2022-3691 | D83: Línea Social_Ciudad Segura y Solidaria | E83: Educación | F83: Colegios | G83: InfraEducativa-3691 - IE Nuestra Señora de las Nieves [Cocina] | H83: Suroriente | I83: Las nieves | J83: Cra 10 # 23 - 13 | K83: 10°57'8.96"N 74°48'17.20"O | L83: -74.776795 | M83: 10.9498 | N83: Contractual | O83: En_Ejecución | P83: 225259654 | Q83: 1 | R83: 1 | S83: =+R83-Q83 -> 0 | T83: {=+_xlfn.IFS($P83<=10000000000,IF(S83>-0.05,"Verde",IF(S83<=-0.1,"Rojo","Amarillo")),$P83>10000000000,IF(S83>-0.03,"Verde",IF(S83<=-0.07,"Rojo","Amarillo")))} -> Verde | U83: 44831 | V83: 44862 | W83: 44901 | X83: 44926 | Y83: 45930 | Z83: =+IF(AND(O83="En_Ejecución",OR(T83="Rojo",T83="Amarillo")),IF(($Y83-(TODAY())<15),"Rojo",IF(($Y83-TODAY())>=45,"Verde","Amarillo")),O83) -> En_Ejecución | AA83: =+IF(AND(Z83="Amarillo",T83="Rojo"),"En_Seguimiento",IF(AND(Z83="Rojo",T83="Amarillo"),"En_Seguimiento",IF(AND(Z83="Rojo",T83="Rojo"),"En_Seguimiento",IF(AND(Z83="Suspendido",T83="Amarillo"),"En_Seguimiento",IF(AND(Z83="Suspendido",T83="Rojo"),"En_Seguimiento","-"))))) -> - | AD83: 45594 | AE83: EDU-345-2022 | AF83: CONSORCIO EDUCATIVO DISTRITAL | AG83: TURPIAL INGENIERIA S.A.S (65%) BF CONSTRUYE S.A.S (30%) IDC 21 S.A.S (5%) | AH83: Cristian David Jimenez Yejas | AI83: SA-EDU-0001-2022 | AJ83: CONSORCIO IE DISTRITO | AK83: CAYENA CONSULTORES E INTERVENTORES S.A.S (40%) HG INGENIERIA Y DESARROLLO S.A.S.(30%) HM INGENIERIA S.A.S (30%) | AM83: 225259654 | AN83: 0 | AO83: =AM83+AN83 -> 225259654 | AP83: 2.7569081e+10 | AQ83: 2.6728811e+10 | AR83: 13080201 | AT83: =AR83+AS83 -> 13080201 | AU83: 1.5520677e+09 | AV83: 1.5520677e+09 | AW83: 1153 Estudiantes | AX83: Diseños ejecutados y aprobados por mes | AY83: Frentes iniciados por mes | AZ83: Frentes entregados por mes | BA83: FRENTE ENTREGADO | BC83: No
A84: =+A83+1 -> 83 | B84: EDUBAR | C84: CD-05-2022-3691 | D84: Línea Social_Ciudad Segura y Solidaria | E84: Educación | F84: Colegios | G84: InfraEducativa-3691 - IE Ciudadela Estudiantil [Cocina] | H84: Metropolitana | I84: Ciudadela 20 de Julio | J84: Cra 1A # 47 - 49 | K84: 10°55'52.40"N 74°48'27.93"O | L84: -74.807738 | M84: 10.931445 | N84: Contractual | O84: En_Ejecución | P84: 547819451 | Q84: 1 | R84: 1 | S84: =+R84-Q84 -> 0 | T84: {=+_xlfn.IFS($P84<=10000000000,IF(S84>-0.05,"Verde",IF(S84<=-0.1,"Rojo","Amarillo")),$P84>10000000000,IF(S84>-0.03,"Verde",IF(S84<=-0.07,"Rojo","Amarillo")))} -> Verde | U84: 44831 | V84: 44862 | W84: 44901 | X84: 44926 | Y84: 45930 | Z84: =+IF(AND(O84="En_Ejecución",OR(T84="Rojo",T84="Amarillo")),IF(($Y84-(TODAY())<15),"Rojo",IF(($Y84-TODAY())>=45,"Verde","Amarillo")),O84) -> En_Ejecución | AA84: =+IF(AND(Z84="Amarillo",T84="Rojo"),"En_Seguimiento",IF(AND(Z84="Rojo",T84="Amarillo"),"En_Seguimiento",IF(AND(Z84="Rojo",T84="Rojo"),"En_Seguimiento",IF(AND(Z84="Suspendido",T84="Amarillo"),"En_Seguimiento",IF(AND(Z84="Suspendido",T84="Rojo"),"En_Seguimiento","-"))))) -> - | AD84: 45796 | AE84: EDU-345-2022 | AF84: CONSORCIO EDUCATIVO DISTRITAL | AG84: TURPIAL INGENIERIA S.A.S (65%) BF CONSTRUYE S.A.S (30%) IDC 21 S.A.S (5%) | AH84: Cristian David Jimenez Yejas | AI84: SA-EDU-0001-2022 | AJ84: CONSORCIO IE DISTRITO | AK84: CAYENA CONSULTORES E INTERVENTORES S.A.S (40%) HG INGENIERIA Y DESARROLLO S.A.S.(30%) HM INGENIERIA S.A.S (30%) | AM84: 547819451 | AN84: 0 | AO84: =AM84+AN84 -> 547819451 | AP84: 2.7569081e+10 | AQ84: 2.6728811e+10 | AR84: 31810352 | AT84: =AR84+AS84 -> 31810352 | AU84: 1.5520677e+09 | AV84: 1.5520677e+09 | AW84: 1400 Estudiantes | AX84: Diseños ejecutados y aprobados por mes | AY84: Frentes iniciados por mes | AZ84: Frentes entregados por mes | BA84: FRENTE ENTREGADO | BC84: No
A85: =+A84+1 -> 84 | B85: EDUBAR | C85: CD-05-2022-3691 | D85: Línea Social_Ciudad Segura y Solidaria | E85: Educación | F85: Colegios | G85: InfraEducativa-3691 - IE Simón Bolivar [Cocina] | H85: Suroriente | I85: Simon Bolivar | J85: Cra 5A # 19 - 15 | K85: 10°56'36.56"N 74°46'39.29"O | L85: -74.777579 | M85: 10.943708 | N85: Contractual | O85: En_Ejecución | P85: 447711864 | Q85: 1 | R85: 1 | S85: =+R85-Q85 -> 0 | T85: {=+_xlfn.IFS($P85<=10000000000,IF(S85>-0.05,"Verde",IF(S85<=-0.1,"Rojo","Amarillo")),$P85>10000000000,IF(S85>-0.03,"Verde",IF(S85<=-0.07,"Rojo","Amarillo")))} -> Verde | U85: 44831 | V85: 44862 | W85: 44901 | X85: 44926 | Y85: 45930 | Z85: =+IF(AND(O85="En_Ejecución",OR(T85="Rojo",T85="Amarillo")),IF(($Y85-(TODAY())<15),"Rojo",IF(($Y85-TODAY())>=45,"Verde","Amarillo")),O85) -> En_Ejecución | AA85: =+IF(AND(Z85="Amarillo",T85="Rojo"),"En_Seguimiento",IF(AND(Z85="Rojo",T85="Amarillo"),"En_Seguimiento",IF(AND(Z85="Rojo",T85="Rojo"),"En_Seguimiento",IF(AND(Z85="Suspendido",T85="Amarillo"),"En_Seguimiento",IF(AND(Z85="Suspendido",T85="Rojo"),"En_Seguimiento","-"))))) -> - | AD85: 45772 | AE85: EDU-345-2022 | AF85: CONSORCIO EDUCATIVO DISTRITAL | AG85: TURPIAL INGENIERIA S.A.S (65%) BF CONSTRUYE S.A.S (30%) IDC 21 S.A.S (5%) | AH85: Cristian David Jimenez Yejas | AI85: SA-EDU-0001-2022 | AJ85: CONSORCIO IE DISTRITO | AK85: CAYENA CONSULTORES E INTERVENTORES S.A.S (40%) HG INGENIERIA Y DESARROLLO S.A.S.(30%) HM INGENIERIA S.A.S (30%) | AM85: 447711864 | AN85: 0 | AO85: =AM85+AN85 -> 447711864 | AP85: 2.7569081e+10 | AQ85: 2.6728811e+10 | AR85: 25997383 | AT85: =AR85+AS85 -> 25997383 | AU85: 1.5520677e+09 | AV85: 1.5520677e+09 | AW85: 283 Estudiantes | AX85: Diseños ejecutados y aprobados por mes | AY85: Frentes iniciados por mes | AZ85: Frentes entregados por mes | BA85: FRENTE ENTREGADO | BC85: No
A86: =+A85+1 -> 85 | B86: EDUBAR | C86: CD-05-2022-3691 | D86: Línea Social_Ciudad Segura y Solidaria | E86: Educación | F86: Colegios | G86: InfraEducativa-3691 - IE Carlos Meisel [Cocina] | H86: Suroccidente | I86: Carlos Meisel | J86: Cl 74 # 24 -139 | K86: 10°58'30"N 74°48'52"W | L86: -74.80799 | M86: 10.978852 | N86: Contractual | O86: En_Ejecución | P86: 365000000 | Q86: 1 | R86: 1 | S86: =+R86-Q86 -> 0 | T86: {=+_xlfn.IFS($P86<=10000000000,IF(S86>-0.05,"Verde",IF(S86<=-0.1,"Rojo","Amarillo")),$P86>10000000000,IF(S86>-0.03,"Verde",IF(S86<=-0.07,"Rojo","Amarillo")))} -> Verde | U86: 44831 | V86: 44862 | W86: 44901 | X86: 44926 | Y86: 45930 | Z86: =+IF(AND(O86="En_Ejecución",OR(T86="Rojo",T86="Amarillo")),IF(($Y86-(TODAY())<15),"Rojo",IF(($Y86-TODAY())>=45,"Verde","Amarillo")),O86) -> En_Ejecución | AA86: =+IF(AND(Z86="Amarillo",T86="Rojo"),"En_Seguimiento",IF(AND(Z86="Rojo",T86="Amarillo"),"En_Seguimiento",IF(AND(Z86="Rojo",T86="Rojo"),"En_Seguimiento",IF(AND(Z86="Suspendido",T86="Amarillo"),"En_Seguimiento",IF(AND(Z86="Suspendido",T86="Rojo"),"En_Seguimiento","-"))))) -> - | AD86: 45915 | AE86: EDU-345-2022 | AF86: CONSORCIO EDUCATIVO DISTRITAL | AG86: TURPIAL INGENIERIA S.A.S (65%) BF CONSTRUYE S.A.S (30%) IDC 21 S.A.S (5%) | AH86: Cristian David Jimenez Yejas | AI86: SA-EDU-0001-2022 | AJ86: CONSORCIO IE DISTRITO | AK86: CAYENA CONSULTORES E INTERVENTORES S.A.S (40%) HG INGENIERIA Y DESARROLLO S.A.S.(30%) HM INGENIERIA S.A.S (30%) | AM86: 365000000 | AN86: 0 | AO86: =AM86+AN86 -> 365000000 | AP86: 2.7569081e+10 | AQ86: 2.6728811e+10 | AR86: 21195780 | AS86: 0 | AT86: =AR86+AS86 -> 21195780 | AU86: 1.5520677e+09 | AV86: 1.5520677e+09 | AW86: Estudiantes | AX86: Diseños ejecutados y aprobados por mes | AY86: Frentes iniciados por mes | AZ86: Frentes entregados por mes | BA86: Pañete exterior sobre muro, intalación de piso, construcción de rampa | BC86: No
A87: =+A86+1 -> 86 | B87: EDUBAR | C87: CD-05-2022-3691 | D87: Línea Social_Ciudad Segura y Solidaria | E87: Educación | F87: Colegios | G87: InfraEducativa-3691 - IE Santa María [Cocina] | H87: Metropolitana | I87: Santa Maria | J87: Cra. 5 Sur #78b- 80 | K87: 10°55'52"N 74°49'17"W | L87: -74.821533 | M87: 10.93097 | N87: Contractual | O87: En_Ejecución | P87: 558000000 | Q87: 0.98 | R87: 0.95 | S87: =+R87-Q87 -> -0.03 | T87: {=+_xlfn.IFS($P87<=10000000000,IF(S87>-0.05,"Verde",IF(S87<=-0.1,"Rojo","Amarillo")),$P87>10000000000,IF(S87>-0.03,"Verde",IF(S87<=-0.07,"Rojo","Amarillo")))} -> Verde | U87: 44831 | V87: 44862 | W87: 44901 | X87: 44926 | Y87: 45930 | Z87: =+IF(AND(O87="En_Ejecución",OR(T87="Rojo",T87="Amarillo")),IF(($Y87-(TODAY())<15),"Rojo",IF(($Y87-TODAY())>=45,"Verde","Amarillo")),O87) -> En_Ejecución | AA87: =+IF(AND(Z87="Amarillo",T87="Rojo"),"En_Seguimiento",IF(AND(Z87="Rojo",T87="Amarillo"),"En_Seguimiento",IF(AND(Z87="Rojo",T87="Rojo"),"En_Seguimiento",IF(AND(Z87="Suspendido",T87="Amarillo"),"En_Seguimiento",IF(AND(Z87="Suspendido",T87="Rojo"),"En_Seguimiento","-"))))) -> - | AD87: 45930 | AE87: EDU-345-2022 | AF87: CONSORCIO EDUCATIVO DISTRITAL | AG87: TURPIAL INGENIERIA S.A.S (65%) BF CONSTRUYE S.A.S (30%) IDC 21 S.A.S (5%) | AH87: Cristian David Jimenez Yejas | AI87: SA-EDU-0001-2022 | AJ87: CONSORCIO IE DISTRITO | AK87: CAYENA CONSULTORES E INTERVENTORES S.A.S (40%) HG INGENIERIA Y DESARROLLO S.A.S.(30%) HM INGENIERIA S.A.S (30%) | AM87: 558000000 | AN87: 0 | AO87: =AM87+AN87 -> 558000000 | AP87: 2.7569081e+10 | AQ87: 2.6728811e+10 | AR87: 32452892 | AS87: 0 | AT87: =AR87+AS87 -> 32452892 | AU87: 1.5520677e+09 | AV87: 1.5520677e+09 | AW87: Estudiantes | AX87: Diseños ejecutados y aprobados por mes | AY87: Frentes iniciados por mes | AZ87: Frentes entregados por mes | BA87: Instalación de pisos, media cañas, instalaciones electricas, limpieza general | BC87: No
A88: =+A87+1 -> 87 | B88: EDUBAR | C88: CD-05-2022-3691 | D88: Línea Social_Ciudad Segura y Solidaria | E88: Educación | F88: Colegios | G88: InfraEducativa-3691 - IE Santa Magdalena Sofía[Cocina] | H88: Riomar | I88: San Salvador | J88: Cl. 84b #76-17 | K88: 11°01'24"N 74°48'25"W | L88: -74.807159 | M88: 11.02314 | N88: Contractual | O88: En_Ejecución | P88: 598000000 | Q88: 0.99 | R88: 0.85 | S88: =+R88-Q88 -> -0.14 | T88: {=+_xlfn.IFS($P88<=10000000000,IF(S88>-0.05,"Verde",IF(S88<=-0.1,"Rojo","Amarillo")),$P88>10000000000,IF(S88>-0.03,"Verde",IF(S88<=-0.07,"Rojo","Amarillo")))} -> Rojo | U88: 44831 | V88: 44862 | W88: 44901 | X88: 44926 | Y88: 45930 | Z88: =+IF(AND(O88="En_Ejecución",OR(T88="Rojo",T88="Amarillo")),IF(($Y88-(TODAY())<15),"Rojo",IF(($Y88-TODAY())>=45,"Verde","Amarillo")),O88) -> Rojo | AA88: =+IF(AND(Z88="Amarillo",T88="Rojo"),"En_Seguimiento",IF(AND(Z88="Rojo",T88="Amarillo"),"En_Seguimiento",IF(AND(Z88="Rojo",T88="Rojo"),"En_Seguimiento",IF(AND(Z88="Suspendido",T88="Amarillo"),"En_Seguimiento",IF(AND(Z88="Suspendido",T88="Rojo"),"En_Seguimiento","-"))))) -> En_Seguimiento | AD88: 45926 | AE88: EDU-345-2022 | AF88: CONSORCIO EDUCATIVO DISTRITAL | AG88: TURPIAL INGENIERIA S.A.S (65%) BF CONSTRUYE S.A.S (30%) IDC 21 S.A.S (5%) | AH88: Cristian David Jimenez Yejas | AI88: SA-EDU-0001-2022 | AJ88: CONSORCIO IE DISTRITO | AK88: CAYENA CONSULTORES E INTERVENTORES S.A.S (40%) HG INGENIERIA Y DESARROLLO S.A.S.(30%) HM INGENIERIA S.A.S (30%) | AM88: 598000000 | AN88: 0 | AO88: =AM88+AN88 -> 598000000 | AP88: 2.7569081e+10 | AQ88: 2.6728811e+10 | AR88: 34757323 | AS88: 0 | AT88: 34757323 | AU88: 1.5520677e+09 | AV88: 1.5520677e+09 | AW88: Estudiantes | AX88: Diseños ejecutados y aprobados por mes | AY88: Frentes iniciados por mes | AZ88: Frentes entregados por mes | BA88: Enchape de muro, engoloce de muro, encofrado para meson | BC88: No
A89: =+A88+1 -> 88 | B89: EDUBAR | C89: CD-05-2022-3691 | D89: Línea Social_Ciudad Segura y Solidaria | E89: Educación | F89: Colegios | G89: InfraEducativa-3691 - IE Hilda Muñoz[Cocina] | H89: Suroccidente | I89: San Felipe | J89: CL. 70C # 24B - 24 | K89: 10°58'24"N 74°48'36"W | L89: -74.810269 | M89: 10.97348 | N89: Contractual | O89: En_Ejecución | P89: 133000000 | Q89: 1 | R89: 1 | S89: =+R89-Q89 -> 0 | T89: {=+_xlfn.IFS($P89<=10000000000,IF(S89>-0.05,"Verde",IF(S89<=-0.1,"Rojo","Amarillo")),$P89>10000000000,IF(S89>-0.03,"Verde",IF(S89<=-0.07,"Rojo","Amarillo")))} -> Verde | U89: 44831 | V89: 44862 | W89: 44901 | X89: 44926 | Y89: 45930 | Z89: =+IF(AND(O89="En_Ejecución",OR(T89="Rojo",T89="Amarillo")),IF(($Y89-(TODAY())<15),"Rojo",IF(($Y89-TODAY())>=45,"Verde","Amarillo")),O89) -> En_Ejecución | AA89: =+IF(AND(Z89="Amarillo",T89="Rojo"),"En_Seguimiento",IF(AND(Z89="Rojo",T89="Amarillo"),"En_Seguimiento",IF(AND(Z89="Rojo",T89="Rojo"),"En_Seguimiento",IF(AND(Z89="Suspendido",T89="Amarillo"),"En_Seguimiento",IF(AND(Z89="Suspendido",T89="Rojo"),"En_Seguimiento","-"))))) -> - | AD89: 45868 | AE89: EDU-345-2022 | AF89: CONSORCIO EDUCATIVO DISTRITAL | AG89: TURPIAL INGENIERIA S.A.S (65%) BF CONSTRUYE S.A.S (30%) IDC 21 S.A.S (5%) | AH89: Cristian David Jimenez Yejas | AI89: SA-EDU-0001-2022 | AJ89: CONSORCIO IE DISTRITO | AK89: CAYENA CONSULTORES E INTERVENTORES S.A.S (40%) HG INGENIERIA Y DESARROLLO S.A.S.(30%) HM INGENIERIA S.A.S (30%) | AM89: 133000000 | AN89: 0 | AO89: =AM89+AN89 -> 133000000 | AP89: 2.7569081e+10 | AQ89: 2.6728811e+10 | AR89: 7722940 | AS89: 0 | AT89: 7722940 | AU89: 1.5520677e+09 | AV89: 1.5520677e+09 | AW89: Estudiantes | AX89: Diseños ejecutados y aprobados por mes | AY89: Frentes iniciados por mes | AZ89: Frentes entregados por mes | BA89: Detalles de pintura, instalación de medidor de gas, Instalación de reflectores | BC89: No
A90: =+A89+1 -> 89 | B90: EDUBAR | C90: CD-05-2022-3691 | D90: Línea Social_Ciudad Segura y Solidaria | E90: Educación | F90: Colegios | G90: InfraEducativa-3691 - IE CODEBA[Cocina] | H90: Norte_Centro_Histórico | I90: Boston | J90: Cl. 68 #47-64 | K90: 10°59'37"N 74°48'02"W | L90: -74.800705 | M90: 10.993784 | N90: Contractual | O90: En_Ejecución | P90: 195000000 | Q90: 1 | R90: 1 | S90: =+R90-Q90 -> 0 | T90: {=+_xlfn.IFS($P90<=10000000000,IF(S90>-0.05,"Verde",IF(S90<=-0.1,"Rojo","Amarillo")),$P90>10000000000,IF(S90>-0.03,"Verde",IF(S90<=-0.07,"Rojo","Amarillo")))} -> Verde | U90: 44831 | V90: 44862 | W90: 44901 | X90: 44926 | Y90: 45930 | Z90: =+IF(AND(O90="En_Ejecución",OR(T90="Rojo",T90="Amarillo")),IF(($Y90-(TODAY())<15),"Rojo",IF(($Y90-TODAY())>=45,"Verde","Amarillo")),O90) -> En_Ejecución | AA90: =+IF(AND(Z90="Amarillo",T90="Rojo"),"En_Seguimiento",IF(AND(Z90="Rojo",T90="Amarillo"),"En_Seguimiento",IF(AND(Z90="Rojo",T90="Rojo"),"En_Seguimiento",IF(AND(Z90="Suspendido",T90="Amarillo"),"En_Seguimiento",IF(AND(Z90="Suspendido",T90="Rojo"),"En_Seguimiento","-"))))) -> - | AD90: 45930 | AE90: EDU-345-2022 | AF90: CONSORCIO EDUCATIVO DISTRITAL | AG90: TURPIAL INGENIERIA S.A.S (65%) BF CONSTRUYE S.A.S (30%) IDC 21 S.A.S (5%) | AH90: Cristian David Jimenez Yejas | AI90: SA-EDU-0001-2022 | AJ90: CONSORCIO IE DISTRITO | AK90: CAYENA CONSULTORES E INTERVENTORES S.A.S (40%) HG INGENIERIA Y DESARROLLO S.A.S.(30%) HM INGENIERIA S.A.S (30%) | AM90: 195000000 | AN90: 0 | AO90: =AM90+AN90 -> 195000000 | AP90: 2.7569081e+10 | AQ90: 2.6728811e+10 | AR90: 11323108 | AS90: 0 | AT90: 11323108 | AU90: 1.5520677e+09 | AV90: 1.5520677e+09 | AW90: Estudiantes | AX90: Diseños ejecutados y aprobados por mes | AY90: Frentes iniciados por mes | AZ90: Frentes entregados por mes | BA90: Frente entregado | BC90: No
A91: =+A90+1 -> 90 | B91: EDUBAR | C91: CD-05-2022-3691 | D91: Línea Social_Ciudad Segura y Solidaria | E91: Educación | F91: Colegios | G91: InfraEducativa-3691 - IE Salvador Entregas[Cocina] | H91: Suroccidente | I91: Pumarejo | J91: CL 58 20 B 40 | K91: 10°58'01"N 74°48'08"W | L91: -74.802425 | M91: 10.967206 | N91: Contractual | O91: En_Ejecución | P91: 6.9082122e+08 | Q91: 1 | R91: 0.88 | S91: =+R91-Q91 -> -0.12 | T91: {=+_xlfn.IFS($P91<=10000000000,IF(S91>-0.05,"Verde",IF(S91<=-0.1,"Rojo","Amarillo")),$P91>10000000000,IF(S91>-0.03,"Verde",IF(S91<=-0.07,"Rojo","Amarillo")))} -> Rojo | U91: 44831 | V91: 44862 | W91: 44901 | X91: 44926 | Y91: 45930 | Z91: =+IF(AND(O91="En_Ejecución",OR(T91="Rojo",T91="Amarillo")),IF(($Y91-(TODAY())<15),"Rojo",IF(($Y91-TODAY())>=45,"Verde","Amarillo")),O91) -> Rojo | AA91: =+IF(AND(Z91="Amarillo",T91="Rojo"),"En_Seguimiento",IF(AND(Z91="Rojo",T91="Amarillo"),"En_Seguimiento",IF(AND(Z91="Rojo",T91="Rojo"),"En_Seguimiento",IF(AND(Z91="Suspendido",T91="Amarillo"),"En_Seguimiento",IF(AND(Z91="Suspendido",T91="Rojo"),"En_Seguimiento","-"))))) -> En_Seguimiento | AD91: 45880 | AE91: EDU-345-2022 | AF91: CONSORCIO EDUCATIVO DISTRITAL | AG91: TURPIAL INGENIERIA S.A.S (65%) BF CONSTRUYE S.A.S (30%) IDC 21 S.A.S (5%) | AH91: Cristian David Jimenez Yejas | AI91: SA-EDU-0001-2022 | AJ91: CONSORCIO IE DISTRITO | AK91: CAYENA CONSULTORES E INTERVENTORES S.A.S (40%) HG INGENIERIA Y DESARROLLO S.A.S.(30%) HM INGENIERIA S.A.S (30%) | AM91: 6.9082122e+08 | AN91: 0 | AO91: =AM91+AN91 -> 6.9082122e+08 | AP91: 2.7569081e+10 | AQ91: 2.6728811e+10 | AR91: 40114066 | AS91: 0 | AT91: 40114066 | AU91: 1.5520677e+09 | AV91: 1.5520677e+09 | AW91: Estudiantes | AX91: Diseños ejecutados y aprobados por mes | AY91: Frentes iniciados por mes | AZ91: Frentes entregados por mes | BA91: Levante de muros, pañete de muros, resane de instalaciones electricas, enchape de baños, instalación de correas metalicas | BC91: No
A92: =+A91+1 -> 91 | B92: EDUBAR | C92: CD-05-2022-3691 | D92: Línea Social_Ciudad Segura y Solidaria | E92: Educación | F92: Colegios | G92: InfraEducativa-3691 - IE Hogar Mariano [Cocina] | H92: Suroccidente | I92: Ceiba | J92: KR 14 58 36 | K92: 10°57'37"N 74°48'23"W | L92: -74.806414 | M92: 10.960457 | N92: Contractual | O92: En_Ejecución | P92: 2.881309e+08 | Q92: 1 | R92: 0.72 | S92: =+R92-Q92 -> -0.28 | T92: {=+_xlfn.IFS($P92<=10000000000,IF(S92>-0.05,"Verde",IF(S92<=-0.1,"Rojo","Amarillo")),$P92>10000000000,IF(S92>-0.03,"Verde",IF(S92<=-0.07,"Rojo","Amarillo")))} -> Rojo | U92: 44831 | V92: 44862 | W92: 44901 | X92: 44926 | Y92: 45930 | Z92: =+IF(AND(O92="En_Ejecución",OR(T92="Rojo",T92="Amarillo")),IF(($Y92-(TODAY())<15),"Rojo",IF(($Y92-TODAY())>=45,"Verde","Amarillo")),O92) -> Rojo | AA92: =+IF(AND(Z92="Amarillo",T92="Rojo"),"En_Seguimiento",IF(AND(Z92="Rojo",T92="Amarillo"),"En_Seguimiento",IF(AND(Z92="Rojo",T92="Rojo"),"En_Seguimiento",IF(AND(Z92="Suspendido",T92="Amarillo"),"En_Seguimiento",IF(AND(Z92="Suspendido",T92="Rojo"),"En_Seguimiento","-"))))) -> En_Seguimiento | AD92: 45887 | AE92: EDU-345-2022 | AF92: CONSORCIO EDUCATIVO DISTRITAL | AG92: TURPIAL INGENIERIA S.A.S (65%) BF CONSTRUYE S.A.S (30%) IDC 21 S.A.S (5%) | AH92: Cristian David Jimenez Yejas | AI92: SA-EDU-0001-2022 | AJ92: CONSORCIO IE DISTRITO | AK92: CAYENA CONSULTORES E INTERVENTORES S.A.S (40%) HG INGENIERIA Y DESARROLLO S.A.S.(30%) HM INGENIERIA S.A.S (30%) | AM92: 2.881309e+08 | AN92: 0 | AO92: =AM92+AN92 -> 2.881309e+08 | AP92: 2.7569081e+10 | AQ92: 2.6728811e+10 | AR92: 16730960 | AS92: 0 | AT92: 16730960 | AU92: 1.5520677e+09 | AV92: 1.5520677e+09 | AW92: Estudiantes | AX92: Diseños ejecutados y aprobados por mes | AY92: Frentes iniciados por mes | AZ92: Frentes entregados por mes | BA92: Figurado de acero, excavación de zapatas | BC92: No
A93: =+A92+1 -> 92 | B93: EDUBAR | C93: CD-05-2022-3691 | D93: Línea Social_Ciudad Segura y Solidaria | E93: Educación | F93: Colegios | G93: InfraEducativa-3691 - IE Maria Inmaculada [Cocina] | H93: Suroccidente | I93: Olaya | J93: KR 29 70 B 60 | K93: 10°58'45"N 74°48'34"W | L93: -74.809899 | M93: 10.981923 | N93: Contractual | O93: En_Ejecución | P93: 5.8727628e+08 | Q93: 1 | R93: 0.82 | S93: =+R93-Q93 -> -0.18 | T93: {=+_xlfn.IFS($P93<=10000000000,IF(S93>-0.05,"Verde",IF(S93<=-0.1,"Rojo","Amarillo")),$P93>10000000000,IF(S93>-0.03,"Verde",IF(S93<=-0.07,"Rojo","Amarillo")))} -> Rojo | U93: 44831 | V93: 44862 | W93: 44901 | X93: 44926 | Y93: 45930 | Z93: =+IF(AND(O93="En_Ejecución",OR(T93="Rojo",T93="Amarillo")),IF(($Y93-(TODAY())<15),"Rojo",IF(($Y93-TODAY())>=45,"Verde","Amarillo")),O93) -> Rojo | AA93: =+IF(AND(Z93="Amarillo",T93="Rojo"),"En_Seguimiento",IF(AND(Z93="Rojo",T93="Amarillo"),"En_Seguimiento",IF(AND(Z93="Rojo",T93="Rojo"),"En_Seguimiento",IF(AND(Z93="Suspendido",T93="Amarillo"),"En_Seguimiento",IF(AND(Z93="Suspendido",T93="Rojo"),"En_Seguimiento","-"))))) -> En_Seguimiento | AD93: 45891 | AE93: EDU-345-2022 | AF93: CONSORCIO EDUCATIVO DISTRITAL | AG93: TURPIAL INGENIERIA S.A.S (65%) BF CONSTRUYE S.A.S (30%) IDC 21 S.A.S (5%) | AH93: Cristian David Jimenez Yejas | AI93: SA-EDU-0001-2022 | AJ93: CONSORCIO IE DISTRITO | AK93: CAYENA CONSULTORES E INTERVENTORES S.A.S (40%) HG INGENIERIA Y DESARROLLO S.A.S.(30%) HM INGENIERIA S.A.S (30%) | AM93: 5.8727628e+08 | AN93: 0 | AO93: =AM93+AN93 -> 5.8727628e+08 | AP93: 2.7569081e+10 | AQ93: 2.6728811e+10 | AR93: 34101500 | AS93: 0 | AT93: 34101500 | AU93: 1.5520677e+09 | AV93: 1.5520677e+09 | AW93: Estudiantes | AX93: Diseños ejecutados y aprobados por mes | AY93: Frentes iniciados por mes | AZ93: Frentes entregados por mes | BA93: Instalación de cubierta UPVC, compactación de terreno, fundida de plantilla para comedor | BC93: No
A94: =+A93+1 -> 93 | B94: EDUBAR | C94: CD-05-2022-3691 | D94: Línea Social_Ciudad Segura y Solidaria | E94: Educación | F94: Colegios | G94: InfraEducativa-3691 - IE Mayor de Barranquilla [Cocina] | H94: Norte_Centro_Histórico | I94: Centro | J94: Calle 47 # 44 - 97 | K94: 10°59'08"N 74°47'12"W | L94: -74.786994 | M94: 10.985841 | N94: Contractual | O94: En_Ejecución | P94: 3.4716735e+08 | Q94: 1 | R94: 1 | S94: =+R94-Q94 -> 0 | T94: {=+_xlfn.IFS($P94<=10000000000,IF(S94>-0.05,"Verde",IF(S94<=-0.1,"Rojo","Amarillo")),$P94>10000000000,IF(S94>-0.03,"Verde",IF(S94<=-0.07,"Rojo","Amarillo")))} -> Verde | U94: 44831 | V94: 44862 | W94: 44901 | X94: 44926 | Y94: 45930 | Z94: =+IF(AND(O94="En_Ejecución",OR(T94="Rojo",T94="Amarillo")),IF(($Y94-(TODAY())<15),"Rojo",IF(($Y94-TODAY())>=45,"Verde","Amarillo")),O94) -> En_Ejecución | AA94: =+IF(AND(Z94="Amarillo",T94="Rojo"),"En_Seguimiento",IF(AND(Z94="Rojo",T94="Amarillo"),"En_Seguimiento",IF(AND(Z94="Rojo",T94="Rojo"),"En_Seguimiento",IF(AND(Z94="Suspendido",T94="Amarillo"),"En_Seguimiento",IF(AND(Z94="Suspendido",T94="Rojo"),"En_Seguimiento","-"))))) -> - | AD94: 45869 | AE94: EDU-345-2022 | AF94: CONSORCIO EDUCATIVO DISTRITAL | AG94: TURPIAL INGENIERIA S.A.S (65%) BF CONSTRUYE S.A.S (30%) IDC 21 S.A.S (5%) | AH94: Cristian David Jimenez Yejas | AI94: SA-EDU-0001-2022 | AJ94: CONSORCIO IE DISTRITO | AK94: CAYENA CONSULTORES E INTERVENTORES S.A.S (40%) HG INGENIERIA Y DESARROLLO S.A.S.(30%) HM INGENIERIA S.A.S (30%) | AM94: 3.4716735e+08 | AN94: 0 | AO94: =AM94+AN94 -> 3.4716735e+08 | AP94: 2.7569081e+10 | AQ94: 2.6728811e+10 | AR94: 20159043 | AS94: 0 | AT94: 20159043 | AU94: 1.5520677e+09 | AV94: 1.5520677e+09 | AW94: Estudiantes | AX94: Diseños ejecutados y aprobados por mes | AY94: Frentes iniciados por mes | AZ94: Frentes entregados por mes | BA94: Instalación de sanitario, instalación de griferias, pulida de piso, detalles de pintura | BC94: No
A95: =+A94+1 -> 94 | B95: EDUBAR | C95: No. 012016001893 | D95: Línea Social_Ciudad Segura y Solidaria | E95: Salud | F95: Hospital | G95: InfraSalud-1893 - CAMINO Nuevo Barranquilla | H95: Suroriente | I95: San Roque | J95: Calle 33 #33-09 | L95: -74.780771 | M95: 10.97248 | N95: Postcontractual | O95: Terminado | P95: 1.4905158e+11 | Q95: 1 | R95: 1 | S95: =+R95-Q95 -> 0 | T95: {=+_xlfn.IFS($P95<=10000000000,IF(S95>-0.05,"Verde",IF(S95<=-0.1,"Rojo","Amarillo")),$P95>10000000000,IF(S95>-0.03,"Verde",IF(S95<=-0.07,"Rojo","Amarillo")))} -> Verde | W95: 43065 | X95: 45657 | Y95: 45657 | Z95: =+IF(AND(O95="En_Ejecución",OR(T95="Rojo",T95="Amarillo")),IF(($Y95-(TODAY())<15),"Rojo",IF(($Y95-TODAY())>=45,"Verde","Amarillo")),O95) -> Terminado | AA95: =+IF(AND(Z95="Amarillo",T95="Rojo"),"En_Seguimiento",IF(AND(Z95="Rojo",T95="Amarillo"),"En_Seguimiento",IF(AND(Z95="Rojo",T95="Rojo"),"En_Seguimiento",IF(AND(Z95="Suspendido",T95="Amarillo"),"En_Seguimiento",IF(AND(Z95="Suspendido",T95="Rojo"),"En_Seguimiento","-"))))) -> - | AD95: 45657 | AE95: EDU-277-2016 | AF95: CONSORCIO ICONHO | AG95: ASSIGNIA INFRAESTRUCTURA S.A. - SUCURSAL COLOMBIA (15%) SOLUCIONES DE INFRAESTRUCTURA Y LOGÍSTICA S.A.S. (15%) COMPAÑÍA DE INGENIERÍA Y NEGOCIOS S.A. - COINSES (50%) INGECMAQ S.A.S. (20%) | AH95: Francisco Dominguez Cuellar | AI95: EDU-283-2016 | AJ95: CONSORCIO HOSPITALES 2016 | AK95: HM INGENIERÍA (41%) INGENIERÍA MASTER (29%) SIGT INGENIEROS Y CONSULTORES S.A.S. (5%) TOMÁS LLAMADOR ARQUITECTOS E INGENIEROS S.L. (25%) | AL95: HUGO VARGAS GÓMEZ | AM95: 55169765762 | AN95: 9.3881817e+10 | AO95: =AM95+AN95 -> 1.4905158e+11 | AP95: 66895033860 | AQ95: 66895033860 | AR95: 9900000000 | AS95: 7.8103362e+09 | AT95: =AR95+AS95 -> 1.7710336e+10 | AU95: 1.3623178e+10 | AV95: 1.3055503e+10 | BC95: Si
A96: =+A95+1 -> 95 | B96: EDUBAR | C96: No. 012016001893 | D96: Línea Social_Ciudad Segura y Solidaria | E96: Salud | F96: Pasos | G96: InfraSalud-1893 - PASO San Camilo | H96: Suroccidente | I96: - | N96: Postcontractual | O96: Terminado | P96: 13052523926 | Q96: 1 | R96: 1 | S96: =+R96-Q96 -> 0 | T96: {=+_xlfn.IFS($P96<=10000000000,IF(S96>-0.05,"Verde",IF(S96<=-0.1,"Rojo","Amarillo")),$P96>10000000000,IF(S96>-0.03,"Verde",IF(S96<=-0.07,"Rojo","Amarillo")))} -> Verde | W96: 44866 | X96: 45657 | Y96: 45657 | Z96: =+IF(AND(O96="En_Ejecución",OR(T96="Rojo",T96="Amarillo")),IF(($Y96-(TODAY())<15),"Rojo",IF(($Y96-TODAY())>=45,"Verde","Amarillo")),O96) -> Terminado | AA96: =+IF(AND(Z96="Amarillo",T96="Rojo"),"En_Seguimiento",IF(AND(Z96="Rojo",T96="Amarillo"),"En_Seguimiento",IF(AND(Z96="Rojo",T96="Rojo"),"En_Seguimiento",IF(AND(Z96="Suspendido",T96="Amarillo"),"En_Seguimiento",IF(AND(Z96="Suspendido",T96="Rojo"),"En_Seguimiento","-"))))) -> - | AD96: 45657 | AE96: EDU-277-2016 | AF96: CONSORCIO ICONHO | AG96: ASSIGNIA INFRAESTRUCTURA S.A. - SUCURSAL COLOMBIA (15%) SOLUCIONES DE INFRAESTRUCTURA Y LOGÍSTICA S.A.S. (15%) COMPAÑÍA DE INGENIERÍA Y NEGOCIOS S.A. - COINSES (50%) INGECMAQ S.A.S. (20%) | AH96: Francisco Dominguez Cuellar | AI96: EDU-283-2016 | AJ96: CONSORCIO HOSPITALES 2016 | AK96: HM INGENIERÍA (41%) INGENIERÍA MASTER (29%) SIGT INGENIEROS Y CONSULTORES S.A.S. (5%) TOMÁS LLAMADOR ARQUITECTOS E INGENIEROS S.L. (25%) | AL96: HUGO VARGAS GÓMEZ | AM96: 5.7414467e+09 | AN96: 7.3110772e+09 | AO96: =AM96+AN96 -> 1.3052524e+10 | AP96: 323294569 | AQ96: 323294569 | AR96: 9900000000 | AS96: 7.8103362e+09 | AT96: =AR96+AS96 -> 1.7710336e+10 | AU96: 1.3623178e+10 | AV96: 1.3055503e+10 | BC96: Si
A97: =+A96+1 -> 96 | B97: EDUBAR | C97: CD-58-2023-3275 | D97: Línea Social_Ciudad Segura y Solidaria | E97: Recreación_y_Deporte | F97: Escenarios deportivos | G97: Escenarios - Mantenimiento Escenarios Deportivos | H97: Varias | I97: Barranquilla | J97: - | K97: Varias | N97: Postcontractual | O97: Terminado | P97: 9200000000 | Q97: 0 | R97: 0.731 | S97: =+R97-Q97 -> 0.731 | T97: {=+_xlfn.IFS($P97<=10000000000,IF(S97>-0.05,"Verde",IF(S97<=-0.1,"Rojo","Amarillo")),$P97>10000000000,IF(S97>-0.03,"Verde",IF(S97<=-0.07,"Rojo","Amarillo")))} -> Verde | U97: 45152 | V97: 45187 | W97: 45201 | X97: 45291 | Y97: 45565 | Z97: =+IF(AND(O97="En_Ejecución",OR(T97="Rojo",T97="Amarillo")),IF(($Y97-(TODAY())<15),"Rojo",IF(($Y97-TODAY())>=45,"Verde","Amarillo")),O97) -> Terminado | AA97: =+IF(AND(Z97="Amarillo",T97="Rojo"),"En_Seguimiento",IF(AND(Z97="Rojo",T97="Amarillo"),"En_Seguimiento",IF(AND(Z97="Rojo",T97="Rojo"),"En_Seguimiento",IF(AND(Z97="Suspendido",T97="Amarillo"),"En_Seguimiento",IF(AND(Z97="Suspendido",T97="Rojo"),"En_Seguimiento","-"))))) -> - | AB97: No | AD97: 45565 | AE97: SA-EDU-0005-2023 | AF97: CONSORCIO PARQUES CUBAGO | AG97: AGORASPORT S.A SUCURSAL COLOMBIA (80%) CARLOS FERNANDO CUBIDES BONILLA (20%) | AH97: Ingrid Nathali Torres Cortés | AM97: 9200000000 | AN97: 0 | AO97: =AM97+AN97 -> 9200000000 | AP97: 1.2465392e+10 | AQ97: 4.0900935e+09 | AR97: 0 | AS97: 0 | AT97: =AR97+AS97 -> 0 | AU97: 0 | AV97: 0 | AW97: 85000 Espectadores | AX97: Cumplimiento al 90% del plan de mantenimiento preventivo | AY97: El 80% de los mantenimientos o actividades deben ser completadas según el cronograma establecido | AZ97: Desarrollo mensual de la totalidad de la listas de chequeo para la revisión de la calidad de los mantenimientos realizados | BA97: Operación diaria (aseo), mantenimientos preventivos y correctivos aprovados por la supervisión en los 18 escenarios deportivos | BB97: Edubar se encuentra en proceso de recibo y liquidación del contrato de prestación de servicios | BC97: No
A98: =+A97+1 -> 97 | B98: EDUBAR | C98: CD-12-2024-0003 | D98: Línea Social_Ciudad Segura y Solidaria | E98: Vivienda | F98: Mejoramiento de viviendas | G98: MejoramientoViviendas-0003 - Módulo 1 | H98: Suroccidente | I98: La Manga, las Malvinas, los Olivos II, La Esmeralda, Bellarena, Bernardo Hoyos, El Milagro, El Moderno, Los Laureles | J98: - | K98: Varias | N98: Contractual | O98: En_Ejecución | P98: 2.2962982e+10 | Q98: 0.92 | R98: 0.86 | S98: =+R98-Q98 -> -0.06 | T98: {=+_xlfn.IFS($P98<=10000000000,IF(S98>-0.05,"Verde",IF(S98<=-0.1,"Rojo","Amarillo")),$P98>10000000000,IF(S98>-0.03,"Verde",IF(S98<=-0.07,"Rojo","Amarillo")))} -> Amarillo | U98: 45370 | V98: 45391 | W98: 45415 | X98: 45657 | Y98: 45961 | Z98: =+IF(AND(O98="En_Ejecución",OR(T98="Rojo",T98="Amarillo")),IF(($Y98-(TODAY())<15),"Rojo",IF(($Y98-TODAY())>=45,"Verde","Amarillo")),O98) -> Rojo | AA98: =+IF(AND(Z98="Amarillo",T98="Rojo"),"En_Seguimiento",IF(AND(Z98="Rojo",T98="Amarillo"),"En_Seguimiento",IF(AND(Z98="Rojo",T98="Rojo"),"En_Seguimiento",IF(AND(Z98="Suspendido",T98="Amarillo"),"En_Seguimiento",IF(AND(Z98="Suspendido",T98="Rojo"),"En_Seguimiento","-"))))) -> En_Seguimiento | AD98: 45961 | AE98: SA-EDU-013-2024 | AF98: CONSORCIO VIVIENDAS URBANAS | AG98: CONGLOMERADO TÉCNICO COLOMBIANO S.A.S. (25%) DONADO ARCE & COMPAÑÍA S.A.S.(33%) ORLANDO DONADO & CIA S.A.S.(25% ) JMD INGENIERÍA DE PROYECTOS S.A.S.(17%) | AH98: OLEARIS ALONSO HERNÁNDEZ ORELLANO | AI98: SA-EDU-006-2024 | AJ98: CONSORCIO PROSPERAR HABITABILIDAD | AK98: INGENIERIA MASTER S.A.S. (50%) H.M. INGENIERIA S.A.S (50%) | AL98: DANIELA CAROLINA SINNING ACUÑA | AM98: 21855086929 | AN98: 0 | AO98: =AM98+AN98 -> 21855086929 | AP98: 1.2465392e+10 | AQ98: 1.136199e+10 | AR98: 1.1078948e+09 | AS98: 0 | AT98: =AR98+AS98 -> 1.1078948e+09 | AU98: 0 | AV98: 0 | AW98: 1000 familias | AX98: Género | AY98: Habitan personas en condición de discapacidad | AZ98: Habitan personas de tercera edad | BA98: A la fecha se han intervenido 862 viviendas de las cuales 775se encuentran terminadas y en 87viviendas se avanza en demolición, fundida de plantilla, pañete, estuco, construcción de mesón, instalación de cerámica, instalaciones eléctricas e hidrosanitarias | BC98: No
A99: =+A98+1 -> 98 | B99: EDUBAR | C99: CD-12-2024-0003 | D99: Línea Social_Ciudad Segura y Solidaria | E99: Vivienda | F99: Mejoramiento de viviendas | G99: MejoramientoViviendas-0003 - Módulo 2 | H99: Varias | I99: El bosque, Evaristo Sourdis, Las Malvinas, Villa Blanca, Los Continentes, Villanueva | J99: - | K99: Varias | N99: Contractual | O99: En_Ejecución | P99: 2.2471261e+10 | Q99: 0.71 | R99: 0.48 | S99: =+R99-Q99 -> -0.23 | T99: {=+_xlfn.IFS($P99<=10000000000,IF(S99>-0.05,"Verde",IF(S99<=-0.1,"Rojo","Amarillo")),$P99>10000000000,IF(S99>-0.03,"Verde",IF(S99<=-0.07,"Rojo","Amarillo")))} -> Rojo | U99: 45370 | V99: 45391 | W99: 45427 | X99: 45657 | Y99: 46022 | Z99: =+IF(AND(O99="En_Ejecución",OR(T99="Rojo",T99="Amarillo")),IF(($Y99-(TODAY())<15),"Rojo",IF(($Y99-TODAY())>=45,"Verde","Amarillo")),O99) -> Verde | AA99: =+IF(AND(Z99="Amarillo",T99="Rojo"),"En_Seguimiento",IF(AND(Z99="Rojo",T99="Amarillo"),"En_Seguimiento",IF(AND(Z99="Rojo",T99="Rojo"),"En_Seguimiento",IF(AND(Z99="Suspendido",T99="Amarillo"),"En_Seguimiento",IF(AND(Z99="Suspendido",T99="Rojo"),"En_Seguimiento","-"))))) -> - | AD99: 46022 | AE99: SA-EDU-014-2024 | AF99: CONSORCIO VIVIENDAS DISTRITALES II | AG99: TURPIAL INGENIERIA S.A.S. (80%)CONSTRUCCIONES HHT S.A.S.(10%) EDC PROYECTOS S.A.S. (10%) | AH99: CRISTIAN DAVID JIMÉNEZ YEJAS | AI99: SA-EDU-006-2024 | AJ99: CONSORCIO PROSPERAR HABITABILIDAD | AK99: INGENIERIA MASTER S.A.S. (50%) H.M. INGENIERIA S.A.S (50%) | AL99: DANIELA CAROLINA SINNING ACUÑA | AM99: 21387090725 | AN99: 0 | AO99: =AM99+AN99 -> 21387090725 | AP99: 5.5909588e+09 | AQ99: 5.5909588e+09 | AR99: 1.0841707e+09 | AS99: 0 | AT99: =AR99+AS99 -> 1.0841707e+09 | AU99: 0 | AV99: 0 | AW99: 1000 familias | AX99: Género | AY99: Habitan personas en condición de discapacidad | AZ99: Habitan personas de tercera edad | BA99: Se han interevnido 482 viviendas, de las cuales se han terminado 331 y en 151 viviendas se avanza en demolición, fundida de plantilla, pañete, estuco, instalaciones sanitarias y eléctricas, construcción de mesón, instalación de cerámica | BC99: No
A100: =+A99+1 -> 99 | B100: EDUBAR | C100: CD-12-2024-0003 | D100: Línea Social_Ciudad Segura y Solidaria | E100: Vivienda | F100: Mejoramiento de viviendas | G100: MejoramientoViviendas-0003 - Módulo 3 | H100: Suroccidente | I100: Ciudad Modesto, El Por Fin, La Paz, Lipaya, Los Olivos I | J100: - | K100: Varias | N100: Contractual | O100: En_Ejecución | P100: 2.2620928e+10 | Q100: 0.797 | R100: 0.69 | S100: =+R100-Q100 -> -0.107 | T100: {=+_xlfn.IFS($P100<=10000000000,IF(S100>-0.05,"Verde",IF(S100<=-0.1,"Rojo","Amarillo")),$P100>10000000000,IF(S100>-0.03,"Verde",IF(S100<=-0.07,"Rojo","Amarillo")))} -> Rojo | U100: 45370 | V100: 45391 | W100: 45427 | X100: 45657 | Y100: 45991 | Z100: =+IF(AND(O100="En_Ejecución",OR(T100="Rojo",T100="Amarillo")),IF(($Y100-(TODAY())<15),"Rojo",IF(($Y100-TODAY())>=45,"Verde","Amarillo")),O100) -> Amarillo | AA100: =+IF(AND(Z100="Amarillo",T100="Rojo"),"En_Seguimiento",IF(AND(Z100="Rojo",T100="Amarillo"),"En_Seguimiento",IF(AND(Z100="Rojo",T100="Rojo"),"En_Seguimiento",IF(AND(Z100="Suspendido",T100="Amarillo"),"En_Seguimiento",IF(AND(Z100="Suspendido",T100="Rojo"),"En_Seguimiento","-"))))) -> En_Seguimiento | AD100: 45991 | AE100: SA-EDU-015-2024 | AF100: UNION TEMPORAL VIVIENDAS DISTRITALES | AG100: HB. INGENIEROS CIVILES S.A.S.(70%) A.S.B. S.A.S(25%) CONSTRUCCION Y CONSULTORIAS DE OBRAS DE INGENIERIA URBANISMO Y ARQUITECTURA - CONTINUAR S.A.S.(5%) | AH100: ALVARO HENRIQUEZ MEDRANO | AI100: SA-EDU-006-2024 | AJ100: CONSORCIO PROSPERAR HABITABILIDAD | AK100: INGENIERIA MASTER S.A.S. (50%) H.M. INGENIERIA S.A.S (50%) | AL100: DANIELA CAROLINA SINNING ACUÑA | AM100: 2.1529537e+10 | AN100: 0 | AO100: =AM100+AN100 -> 2.1529537e+10 | AP100: 8.430671e+09 | AQ100: 8.430671e+09 | AR100: 1.0913917e+09 | AS100: 0 | AT100: =AR100+AS100 -> 1.0913917e+09 | AU100: 0 | AV100: 0 | AW100: 1000 familias | AX100: Género | AY100: Habitan personas en condición de discapacidad | AZ100: Habitan personas de tercera edad | BA100: Se han intervenido 687 viviendas, 538 de las cuales ya se encuentran terminadas y en 149 viviendas se encuentran en ejecución avanzando en demolición, fundida de plantilla, pañete estuco, instalaciones sanitarias y eléctricas, construcción de mesón, instalación de cerámica | BC100: No
...

Sheet Proyectos
A1: ID | B1: Reporte a cargo de: | C1: Convenio o Contrato Interadministrativo | D1: Línea Estratégica Plan de Desarrollo 2024-2027 | E1: Sectores | F1: Programas | G1: Nombre Proyecto | H1: Localidad | I1: Barrios | J1: Dirección | K1: Localización | L1: x | M1: y | N1: Estado Proyecto | O1: Subestado Proyecto | P1: Valor total de proyecto | Q1: % Programado físico | R1: % Ejecutado físico | S1: Atraso | T1: Semáforo Cronograma | U1: Fecha de Adjudicación | V1: Fecha de Firma Contrato | W1: Fecha de Inicio | X1: Fecha de Terminación Inicial | Y1: Fecha de Terminación Final | Z1: Semáforo Fecha Terminación | AA1: Semáforo Críticos | AB1: Fecha de Entrega | AC1: No. Contrato Ejecución | AD1: Nombre Contratista Ejecución | AE1: Miembros Consorcios o UT | AF1: Representante Legal | AG1: No. Contrato Interventoría | AH1: Nombre Contratista Interventoría | AI1: Miembros Consorcios o UT 2 | AJ1: Representante Legal3 | AK1: Valor inicial de Obra | AL1: Valor total adicionado de obra | AM1: Valor total de Obra | AN1: Valor total Facturadode Obra | AO1: Valor total Pagado de Obra | AP1: Valor inicial de Interventoría | AQ1: Valor total adicionado de Interventoría | AR1: Valor total de Interventoría | AS1: Valor total Facturado de Interventoría | AT1: Valor total Pagado de Interventoría | AU1: Población Beneficiada [ Indicar cantidad y tipo de población. Ej: 100 Estudiantes ] | AV1: Indicador 1 | AW1: Indicador 2 | AX1: Indicador 3 | AY1: Actividades Ejecutadas ultima semana | AZ1: Observaciones de acciones ejecutivas | BA1: Emblemático Gerente
A2: =+'Proyectos Base digitable'!#REF! -> #REF! | B2: =+'Proyectos Base digitable'!#REF! -> #REF! | C2: =+'Proyectos Base digitable'!#REF! -> #REF! | D2: =+'Proyectos Base digitable'!#REF! -> #REF! | E2: =+'Proyectos Base digitable'!#REF! -> #REF! | F2: =+'Proyectos Base digitable'!#REF! -> #REF! | G2: =+'Proyectos Base digitable'!#REF! -> #REF! | H2: =+'Proyectos Base digitable'!#REF! -> #REF! | ... T2: =+'Proyectos Base digitable'!#REF! -> #REF! | U2: ='Proyectos Base digitable'!#REF! -> #REF! | V2: ='Proyectos Base digitable'!#REF! -> #REF! | W2: ='Proyectos Base digitable'!#REF! -> #REF! | X2: ='Proyectos Base digitable'!#REF! -> #REF! | Y2: ='Proyectos Base digitable'!#REF! -> #REF! | Z2: =+'Proyectos Base digitable'!#REF! -> #REF! | AA2: =+'Proyectos Base digitable'!#REF! -> #REF! | AB2: ='Proyectos Base digitable'!#REF! -> #REF! | AC2: =+'Proyectos Base digitable'!#REF! -> #REF! | AD2: =+'Proyectos Base digitable'!#REF! -> #REF! | AE2: =+'Proyectos Base digitable'!#REF! -> #REF! | AF2: =+'Proyectos Base digitable'!#REF! -> #REF! | AG2: =+'Proyectos Base digitable'!#REF! -> #REF! | AH2: =+'Proyectos Base digitable'!#REF! -> #REF! | AI2: =+'Proyectos Base digitable'!#REF! -> #REF! | AJ2: =+'Proyectos Base digitable'!#REF! -> #REF! | ... BA2: =+'Proyectos Base digitable'!#REF! -> #REF!
A3: =+'Proyectos Base digitable'!#REF! -> #REF! | B3: =+'Proyectos Base digitable'!#REF! -> #REF! | C3: =+'Proyectos Base digitable'!#REF! -> #REF! | D3: =+'Proyectos Base digitable'!#REF! -> #REF! | E3: =+'Proyectos Base digitable'!#REF! -> #REF! | F3: =+'Proyectos Base digitable'!#REF! -> #REF! | G3: =+'Proyectos Base digitable'!#REF! -> #REF! | H3: =+'Proyectos Base digitable'!#REF! -> #REF! | ... T3: =+'Proyectos Base digitable'!#REF! -> #REF! | U3: ='Proyectos Base digitable'!#REF! -> #REF! | V3: ='Proyectos Base digitable'!#REF! -> #REF! | W3: ='Proyectos Base digitable'!#REF! -> #REF! | X3: ='Proyectos Base digitable'!#REF! -> #REF! | Y3: ='Proyectos Base digitable'!#REF! -> #REF! | Z3: =+'Proyectos Base digitable'!#REF! -> #REF! | AA3: =+'Proyectos Base digitable'!#REF! -> #REF! | AB3: ='Proyectos Base digitable'!#REF! -> #REF! | AC3: =+'Proyectos Base digitable'!#REF! -> #REF! | AD3: =+'Proyectos Base digitable'!#REF! -> #REF! | AE3: =+'Proyectos Base digitable'!#REF! -> #REF! | AF3: =+'Proyectos Base digitable'!#REF! -> #REF! | AG3: =+'Proyectos Base digitable'!#REF! -> #REF! | AH3: =+'Proyectos Base digitable'!#REF! -> #REF! | AI3: =+'Proyectos Base digitable'!#REF! -> #REF! | AJ3: =+'Proyectos Base digitable'!#REF! -> #REF! | ... BA3: =+'Proyectos Base digitable'!#REF! -> #REF!
A4: =+'Proyectos Base digitable'!#REF! -> #REF! | B4: =+'Proyectos Base digitable'!#REF! -> #REF! | C4: =+'Proyectos Base digitable'!#REF! -> #REF! | D4: =+'Proyectos Base digitable'!#REF! -> #REF! | E4: =+'Proyectos Base digitable'!#REF! -> #REF! | F4: =+'Proyectos Base digitable'!#REF! -> #REF! | G4: =+'Proyectos Base digitable'!#REF! -> #REF! | H4: =+'Proyectos Base digitable'!#REF! -> #REF! | ... T4: =+'Proyectos Base digitable'!#REF! -> #REF! | U4: ='Proyectos Base digitable'!#REF! -> #REF! | V4: ='Proyectos Base digitable'!#REF! -> #REF! | W4: ='Proyectos Base digitable'!#REF! -> #REF! | X4: ='Proyectos Base digitable'!#REF! -> #REF! | Y4: ='Proyectos Base digitable'!#REF! -> #REF! | Z4: =+'Proyectos Base digitable'!#REF! -> #REF! | AA4: =+'Proyectos Base digitable'!#REF! -> #REF! | AB4: ='Proyectos Base digitable'!#REF! -> #REF! | AC4: =+'Proyectos Base digitable'!#REF! -> #REF! | AD4: =+'Proyectos Base digitable'!#REF! -> #REF! | AE4: =+'Proyectos Base digitable'!#REF! -> #REF! | AF4: =+'Proyectos Base digitable'!#REF! -> #REF! | AG4: =+'Proyectos Base digitable'!#REF! -> #REF! | AH4: =+'Proyectos Base digitable'!#REF! -> #REF! | AI4: =+'Proyectos Base digitable'!#REF! -> #REF! | AJ4: =+'Proyectos Base digitable'!#REF! -> #REF! | ... BA4: =+'Proyectos Base digitable'!#REF! -> #REF!
A5: =+'Proyectos Base digitable'!#REF! -> #REF! | B5: =+'Proyectos Base digitable'!#REF! -> #REF! | C5: =+'Proyectos Base digitable'!#REF! -> #REF! | D5: =+'Proyectos Base digitable'!#REF! -> #REF! | E5: =+'Proyectos Base digitable'!#REF! -> #REF! | F5: =+'Proyectos Base digitable'!#REF! -> #REF! | G5: =+'Proyectos Base digitable'!#REF! -> #REF! | H5: =+'Proyectos Base digitable'!#REF! -> #REF! | ... T5: =+'Proyectos Base digitable'!#REF! -> #REF! | U5: ='Proyectos Base digitable'!#REF! -> #REF! | V5: ='Proyectos Base digitable'!#REF! -> #REF! | W5: ='Proyectos Base digitable'!#REF! -> #REF! | X5: ='Proyectos Base digitable'!#REF! -> #REF! | Y5: ='Proyectos Base digitable'!#REF! -> #REF! | Z5: =+'Proyectos Base digitable'!#REF! -> #REF! | AA5: =+'Proyectos Base digitable'!#REF! -> #REF! | AB5: ='Proyectos Base digitable'!#REF! -> #REF! | AC5: =+'Proyectos Base digitable'!#REF! -> #REF! | AD5: =+'Proyectos Base digitable'!#REF! -> #REF! | AE5: =+'Proyectos Base digitable'!#REF! -> #REF! | AF5: =+'Proyectos Base digitable'!#REF! -> #REF! | AG5: =+'Proyectos Base digitable'!#REF! -> #REF! | AH5: =+'Proyectos Base digitable'!#REF! -> #REF! | AI5: =+'Proyectos Base digitable'!#REF! -> #REF! | AJ5: =+'Proyectos Base digitable'!#REF! -> #REF! | ... BA5: =+'Proyectos Base digitable'!#REF! -> #REF!
A6: =+'Proyectos Base digitable'!#REF! -> #REF! | B6: =+'Proyectos Base digitable'!#REF! -> #REF! | C6: =+'Proyectos Base digitable'!#REF! -> #REF! | D6: =+'Proyectos Base digitable'!#REF! -> #REF! | E6: =+'Proyectos Base digitable'!#REF! -> #REF! | F6: =+'Proyectos Base digitable'!#REF! -> #REF! | G6: =+'Proyectos Base digitable'!#REF! -> #REF! | H6: =+'Proyectos Base digitable'!#REF! -> #REF! | ... T6: =+'Proyectos Base digitable'!#REF! -> #REF! | U6: ='Proyectos Base digitable'!#REF! -> #REF! | V6: ='Proyectos Base digitable'!#REF! -> #REF! | W6: ='Proyectos Base digitable'!#REF! -> #REF! | X6: ='Proyectos Base digitable'!#REF! -> #REF! | Y6: ='Proyectos Base digitable'!#REF! -> #REF! | Z6: =+'Proyectos Base digitable'!#REF! -> #REF! | AA6: =+'Proyectos Base digitable'!#REF! -> #REF! | AB6: ='Proyectos Base digitable'!#REF! -> #REF! | AC6: =+'Proyectos Base digitable'!#REF! -> #REF! | AD6: =+'Proyectos Base digitable'!#REF! -> #REF! | AE6: =+'Proyectos Base digitable'!#REF! -> #REF! | AF6: =+'Proyectos Base digitable'!#REF! -> #REF! | AG6: =+'Proyectos Base digitable'!#REF! -> #REF! | AH6: =+'Proyectos Base digitable'!#REF! -> #REF! | AI6: =+'Proyectos Base digitable'!#REF! -> #REF! | AJ6: =+'Proyectos Base digitable'!#REF! -> #REF! | ... BA6: =+'Proyectos Base digitable'!#REF! -> #REF!
A7: =+'Proyectos Base digitable'!#REF! -> #REF! | B7: =+'Proyectos Base digitable'!#REF! -> #REF! | C7: =+'Proyectos Base digitable'!#REF! -> #REF! | D7: =+'Proyectos Base digitable'!#REF! -> #REF! | E7: =+'Proyectos Base digitable'!#REF! -> #REF! | F7: =+'Proyectos Base digitable'!#REF! -> #REF! | G7: =+'Proyectos Base digitable'!#REF! -> #REF! | H7: =+'Proyectos Base digitable'!#REF! -> #REF! | ... T7: =+'Proyectos Base digitable'!#REF! -> #REF! | U7: ='Proyectos Base digitable'!#REF! -> #REF! | V7: ='Proyectos Base digitable'!#REF! -> #REF! | W7: ='Proyectos Base digitable'!#REF! -> #REF! | X7: ='Proyectos Base digitable'!#REF! -> #REF! | Y7: ='Proyectos Base digitable'!#REF! -> #REF! | Z7: =+'Proyectos Base digitable'!#REF! -> #REF! | AA7: =+'Proyectos Base digitable'!#REF! -> #REF! | AB7: ='Proyectos Base digitable'!#REF! -> #REF! | AC7: =+'Proyectos Base digitable'!#REF! -> #REF! | AD7: =+'Proyectos Base digitable'!#REF! -> #REF! | AE7: =+'Proyectos Base digitable'!#REF! -> #REF! | AF7: =+'Proyectos Base digitable'!#REF! -> #REF! | AG7: =+'Proyectos Base digitable'!#REF! -> #REF! | AH7: =+'Proyectos Base digitable'!#REF! -> #REF! | AI7: =+'Proyectos Base digitable'!#REF! -> #REF! | AJ7: =+'Proyectos Base digitable'!#REF! -> #REF! | ... BA7: =+'Proyectos Base digitable'!#REF! -> #REF!
A8: =+'Proyectos Base digitable'!#REF! -> #REF! | B8: =+'Proyectos Base digitable'!#REF! -> #REF! | C8: =+'Proyectos Base digitable'!#REF! -> #REF! | D8: =+'Proyectos Base digitable'!#REF! -> #REF! | E8: =+'Proyectos Base digitable'!#REF! -> #REF! | F8: =+'Proyectos Base digitable'!#REF! -> #REF! | G8: =+'Proyectos Base digitable'!#REF! -> #REF! | H8: =+'Proyectos Base digitable'!#REF! -> #REF! | ... T8: =+'Proyectos Base digitable'!#REF! -> #REF! | U8: ='Proyectos Base digitable'!#REF! -> #REF! | V8: ='Proyectos Base digitable'!#REF! -> #REF! | W8: ='Proyectos Base digitable'!#REF! -> #REF! | X8: ='Proyectos Base digitable'!#REF! -> #REF! | Y8: ='Proyectos Base digitable'!#REF! -> #REF! | Z8: =+'Proyectos Base digitable'!#REF! -> #REF! | AA8: =+'Proyectos Base digitable'!#REF! -> #REF! | AB8: ='Proyectos Base digitable'!#REF! -> #REF! | AC8: =+'Proyectos Base digitable'!#REF! -> #REF! | AD8: =+'Proyectos Base digitable'!#REF! -> #REF! | AE8: =+'Proyectos Base digitable'!#REF! -> #REF! | AF8: =+'Proyectos Base digitable'!#REF! -> #REF! | AG8: =+'Proyectos Base digitable'!#REF! -> #REF! | AH8: =+'Proyectos Base digitable'!#REF! -> #REF! | AI8: =+'Proyectos Base digitable'!#REF! -> #REF! | AJ8: =+'Proyectos Base digitable'!#REF! -> #REF! | ... BA8: =+'Proyectos Base digitable'!#REF! -> #REF!
A9: =+'Proyectos Base digitable'!#REF! -> #REF! | B9: =+'Proyectos Base digitable'!#REF! -> #REF! | C9: =+'Proyectos Base digitable'!#REF! -> #REF! | D9: =+'Proyectos Base digitable'!#REF! -> #REF! | E9: =+'Proyectos Base digitable'!#REF! -> #REF! | F9: =+'Proyectos Base digitable'!#REF! -> #REF! | G9: =+'Proyectos Base digitable'!#REF! -> #REF! | H9: =+'Proyectos Base digitable'!#REF! -> #REF! | ... T9: =+'Proyectos Base digitable'!#REF! -> #REF! | U9: ='Proyectos Base digitable'!#REF! -> #REF! | V9: ='Proyectos Base digitable'!#REF! -> #REF! | W9: ='Proyectos Base digitable'!#REF! -> #REF! | X9: ='Proyectos Base digitable'!#REF! -> #REF! | Y9: ='Proyectos Base digitable'!#REF! -> #REF! | Z9: =+'Proyectos Base digitable'!#REF! -> #REF! | AA9: =+'Proyectos Base digitable'!#REF! -> #REF! | AB9: ='Proyectos Base digitable'!#REF! -> #REF! | AC9: =+'Proyectos Base digitable'!#REF! -> #REF! | AD9: =+'Proyectos Base digitable'!#REF! -> #REF! | AE9: =+'Proyectos Base digitable'!#REF! -> #REF! | AF9: =+'Proyectos Base digitable'!#REF! -> #REF! | AG9: =+'Proyectos Base digitable'!#REF! -> #REF! | AH9: =+'Proyectos Base digitable'!#REF! -> #REF! | AI9: =+'Proyectos Base digitable'!#REF! -> #REF! | AJ9: =+'Proyectos Base digitable'!#REF! -> #REF! | ... BA9: =+'Proyectos Base digitable'!#REF! -> #REF!
A10: =+'Proyectos Base digitable'!#REF! -> #REF! | B10: =+'Proyectos Base digitable'!#REF! -> #REF! | C10: =+'Proyectos Base digitable'!#REF! -> #REF! | D10: =+'Proyectos Base digitable'!#REF! -> #REF! | E10: =+'Proyectos Base digitable'!#REF! -> #REF! | F10: =+'Proyectos Base digitable'!#REF! -> #REF! | G10: =+'Proyectos Base digitable'!#REF! -> #REF! | H10: =+'Proyectos Base digitable'!#REF! -> #REF! | ... T10: =+'Proyectos Base digitable'!#REF! -> #REF! | U10: ='Proyectos Base digitable'!#REF! -> #REF! | V10: ='Proyectos Base digitable'!#REF! -> #REF! | W10: ='Proyectos Base digitable'!#REF! -> #REF! | X10: ='Proyectos Base digitable'!#REF! -> #REF! | Y10: ='Proyectos Base digitable'!#REF! -> #REF! | Z10: =+'Proyectos Base digitable'!#REF! -> #REF! | AA10: =+'Proyectos Base digitable'!#REF! -> #REF! | AB10: ='Proyectos Base digitable'!#REF! -> #REF! | AC10: =+'Proyectos Base digitable'!#REF! -> #REF! | AD10: =+'Proyectos Base digitable'!#REF! -> #REF! | AE10: =+'Proyectos Base digitable'!#REF! -> #REF! | AF10: =+'Proyectos Base digitable'!#REF! -> #REF! | AG10: =+'Proyectos Base digitable'!#REF! -> #REF! | AH10: =+'Proyectos Base digitable'!#REF! -> #REF! | AI10: =+'Proyectos Base digitable'!#REF! -> #REF! | AJ10: =+'Proyectos Base digitable'!#REF! -> #REF! | ... BA10: =+'Proyectos Base digitable'!#REF! -> #REF!
A11: =+'Proyectos Base digitable'!#REF! -> #REF! | B11: =+'Proyectos Base digitable'!#REF! -> #REF! | C11: =+'Proyectos Base digitable'!#REF! -> #REF! | D11: =+'Proyectos Base digitable'!#REF! -> #REF! | E11: =+'Proyectos Base digitable'!#REF! -> #REF! | F11: =+'Proyectos Base digitable'!#REF! -> #REF! | G11: =+'Proyectos Base digitable'!#REF! -> #REF! | H11: =+'Proyectos Base digitable'!#REF! -> #REF! | ... T11: =+'Proyectos Base digitable'!#REF! -> #REF! | U11: ='Proyectos Base digitable'!#REF! -> #REF! | V11: ='Proyectos Base digitable'!#REF! -> #REF! | W11: ='Proyectos Base digitable'!#REF! -> #REF! | X11: ='Proyectos Base digitable'!#REF! -> #REF! | Y11: ='Proyectos Base digitable'!#REF! -> #REF! | Z11: =+'Proyectos Base digitable'!#REF! -> #REF! | AA11: =+'Proyectos Base digitable'!#REF! -> #REF! | AB11: ='Proyectos Base digitable'!#REF! -> #REF! | AC11: =+'Proyectos Base digitable'!#REF! -> #REF! | AD11: =+'Proyectos Base digitable'!#REF! -> #REF! | AE11: =+'Proyectos Base digitable'!#REF! -> #REF! | AF11: =+'Proyectos Base digitable'!#REF! -> #REF! | AG11: =+'Proyectos Base digitable'!#REF! -> #REF! | AH11: =+'Proyectos Base digitable'!#REF! -> #REF! | AI11: =+'Proyectos Base digitable'!#REF! -> #REF! | AJ11: =+'Proyectos Base digitable'!#REF! -> #REF! | ... BA11: =+'Proyectos Base digitable'!#REF! -> #REF!
A12: =+'Proyectos Base digitable'!#REF! -> #REF! | B12: =+'Proyectos Base digitable'!#REF! -> #REF! | C12: =+'Proyectos Base digitable'!#REF! -> #REF! | D12: =+'Proyectos Base digitable'!#REF! -> #REF! | E12: =+'Proyectos Base digitable'!#REF! -> #REF! | F12: =+'Proyectos Base digitable'!#REF! -> #REF! | G12: =+'Proyectos Base digitable'!#REF! -> #REF! | H12: =+'Proyectos Base digitable'!#REF! -> #REF! | ... T12: =+'Proyectos Base digitable'!#REF! -> #REF! | U12: ='Proyectos Base digitable'!#REF! -> #REF! | V12: ='Proyectos Base digitable'!#REF! -> #REF! | W12: ='Proyectos Base digitable'!#REF! -> #REF! | X12: ='Proyectos Base digitable'!#REF! -> #REF! | Y12: ='Proyectos Base digitable'!#REF! -> #REF! | Z12: =+'Proyectos Base digitable'!#REF! -> #REF! | AA12: =+'Proyectos Base digitable'!#REF! -> #REF! | AB12: ='Proyectos Base digitable'!#REF! -> #REF! | AC12: =+'Proyectos Base digitable'!#REF! -> #REF! | AD12: =+'Proyectos Base digitable'!#REF! -> #REF! | AE12: =+'Proyectos Base digitable'!#REF! -> #REF! | AF12: =+'Proyectos Base digitable'!#REF! -> #REF! | AG12: =+'Proyectos Base digitable'!#REF! -> #REF! | AH12: =+'Proyectos Base digitable'!#REF! -> #REF! | AI12: =+'Proyectos Base digitable'!#REF! -> #REF! | AJ12: =+'Proyectos Base digitable'!#REF! -> #REF! | ... BA12: =+'Proyectos Base digitable'!#REF! -> #REF!
